Workbook

Sheet 3 Demonstrações
B1: Empresa: | F1: First Year | G1: 2025 | I1: Unidade | J1: R$
A3: X | B3: Premissas | D3: =$G$1 -> 2025 | E3: =D3+1 -> 2026 | F3: =E3+1 -> 2027 | G3: =F3+1 -> 2028 | H3: =G3+1 -> 2029 | I3: =H3+1 -> 2030 | J3: =I3+1 -> 2031 | K3: =J3+1 -> 2032 | L3: =K3+1 -> 2033 | ... R3: =Q3+1 -> 2039
B5: Crescimento da Receita (Var %) | E5: -1
B6: Impostos (% Simples nacional) | D6: =Precificação!$C$26 -> 0.078
B7: Devoluções (% Faturamento) | D7: 0.01
B8: CPV (% Faturamento) | D8: =-Precificação!$D$5/Precificação!$D$2 -> 0.46752446
B9: SG&A (% Faturamento) | D9: =-Precificação!$D$6/Precificação!$D$2 -> 0.35604893
B10: D&A (% Imob. e Intang.) | D10: =Precificação!C25 -> 0
B11: Juros (% Dívida)
B12: Juros Revolver (% Dívida)
B13: Prazo Médio de Recebimento (Dias)
B14: Prazo Médio de Estoque (Dias)
B15: Prazo Médio de Pagamentos (Dias)
B16: Outras Receitas (Despesas) Operacionais (% Faturamento)
B17: Capex (R$)
B18: Captação Empréstimos (Pagamentos) (R$)
B19: Vendas (Unidades de 250g/Ano) | D19: =Precificação!B5*12 -> 8640
B20: Preço da Unidade (R$/Unidades de 250g) | D20: =Precificação!B34 -> 46.859699
B21: Sacas Compradas (Sacas/Ano) | D21: ='Investimento Inicial'!C5 -> 45
B22: Preço da Saca (R$) | D22: =Precificação!B4*60 -> 3100 | E22: =D22 -> 3100 | F22: =E22 -> 3100 | G22: =F22 -> 3100 | H22: =G22 -> 3100 | I22: =H22 -> 3100 | J22: =I22 -> 3100 | K22: =J22 -> 3100 | L22: =K22 -> 3100 | ... R22: =Q22 -> 3100
A24: X | B24: DRE | D24: =$G$1 -> 2025 | E24: =D24+1 -> 2026 | F24: =E24+1 -> 2027 | G24: =F24+1 -> 2028 | H24: =G24+1 -> 2029 | I24: =H24+1 -> 2030 | J24: =I24+1 -> 2031 | K24: =J24+1 -> 2032 | L24: =K24+1 -> 2033 | ... R24: =Q24+1 -> 2039
B26: Receita Operacional Bruta | D26: =D19*D20 -> 404867.8 | E26: =E19*E20 -> 0 | F26: =F19*F20 -> 0 | G26: =G19*G20 -> 0 | H26: =H19*H20 -> 0 | I26: =I19*I20 -> 0 | J26: =J19*J20 -> 0 | K26: =K19*K20 -> 0 | ... R26: =R19*R20 -> 0
B27: Deduções Das Receitas | D27: =D28+D29 -> 35628.367 | E27: =E28+E29 -> 0 | F27: =F28+F29 -> 0 | G27: =G28+G29 -> 0 | H27: =H28+H29 -> 0 | I27: =I28+I29 -> 0 | J27: =J28+J29 -> 0 | K27: =K28+K29 -> 0 | ... R27: =R28+R29 -> 0
B28: Impostos sobre vendas | D28: =D6*D26 -> 31579.689 | I28: =H28*(1+I6) -> 0 | J28: =I28*(1+J6) -> 0 | K28: =J28*(1+K6) -> 0 | L28: =K28*(1+L6) -> 0 | M28: =L28*(1+M6) -> 0 | N28: =M28*(1+N6) -> 0 | O28: =N28*(1+O6) -> 0 | P28: =O28*(1+P6) -> 0 | ... R28: =Q28*(1+R6) -> 0
B29: Devoluções | D29: =$D$7*$D$26 -> 4048.678
B30: Receita Operacional Líquida | D30: =D26-D27 -> 369239.44 | E30: =E26-E27 -> 0 | F30: =F26-F27 -> 0 | G30: =G26-G27 -> 0 | H30: =H26-H27 -> 0 | I30: =I26-I27 -> 0 | J30: =J26-J27 -> 0 | K30: =K26-K27 -> 0 | ... R30: =R26-R27 -> 0
B31: Custo dos Produtos Vendidos | D31: =$D$8*D26 -> 189285.6 | I31: =H31*(1+I8) -> 0 | J31: =I31*(1+J8) -> 0 | K31: =J31*(1+K8) -> 0 | L31: =K31*(1+L8) -> 0 | M31: =L31*(1+M8) -> 0 | N31: =M31*(1+N8) -> 0 | O31: =N31*(1+O8) -> 0 | P31: =O31*(1+P8) -> 0 | ... R31: =Q31*(1+R8) -> 0
B32: Lucro Operacional Bruto | D32: =D30-D31 -> 179953.84 | E32: =E30-E31 -> 0 | F32: =F30-F31 -> 0 | G32: =G30-G31 -> 0 | H32: =H30-H31 -> 0 | I32: =I30-I31 -> 0 | J32: =J30-J31 -> 0 | K32: =K30-K31 -> 0 | ... R32: =R30-R31 -> 0
B33: SG&A | D33: =$D$9*$D$26 -> 144152.75 | I33: =H33+(1*I9) -> 0 | J33: =I33+(1*J9) -> 0 | K33: =J33+(1*K9) -> 0 | L33: =K33+(1*L9) -> 0 | M33: =L33+(1*M9) -> 0 | N33: =M33+(1*N9) -> 0 | O33: =N33+(1*O9) -> 0 | P33: =O33+(1*P9) -> 0 | ... R33: =Q33+(1*R9) -> 0
B34: Resultado Operacional | D34: =D32-D33 -> 35801.09 | E34: =E32-E33 -> 0 | F34: =F32-F33 -> 0 | G34: =G32-G33 -> 0 | H34: =H32-H33 -> 0 | I34: =I32-I33 -> 0 | J34: =J32-J33 -> 0 | K34: =K32-K33 -> 0 | ... R34: =R32-R33 -> 0
B35: Outros Resultados | D35: 0 | I35: =H35 -> 0 | J35: =I35 -> 0 | K35: =J35 -> 0 | L35: =K35 -> 0 | M35: =L35 -> 0 | N35: =M35 -> 0 | O35: =N35 -> 0 | P35: =O35 -> 0 | ... R35: =Q35 -> 0
B36: Lucro Antes do Resultado Financeiro (EBIT) | D36: =D34+D35 -> 35801.09 | E36: =E34+E35 -> 0 | F36: =F34+F35 -> 0 | G36: =G34+G35 -> 0 | H36: =H34+H35 -> 0 | I36: =I34+I35 -> 0 | J36: =J34+J35 -> 0 | K36: =K34+K35 -> 0 | ... R36: =R34+R35 -> 0
B37: Receita Financeira Líquida | D37: =D38-D39 -> -12938.099 | E37: =E38-E39 -> 0 | F37: =F38-F39 -> 0 | G37: =G38-G39 -> 0 | H37: =H38-H39 -> 0 | I37: =I38-I39 -> 0 | J37: =J38-J39 -> 0 | K37: =K38-K39 -> 0 | ... R37: =R38-R39 -> 0
B38: Receita Financeira | I38: =H38*(1+I108) -> 0 | J38: =I38*(1+J108) -> 0 | K38: =J38*(1+K108) -> 0 | L38: =K38*(1+L108) -> 0 | M38: =L38*(1+M108) -> 0 | N38: =M38*(1+N108) -> 0 | O38: =N38*(1+O108) -> 0 | P38: =O38*(1+P108) -> 0 | ... R38: =Q38*(1+R108) -> 0
B39: Despesas Financeira | D39: ='Simulação Empréstimo'!K6 -> 12938.099 | I39: =I135 -> 0 | J39: =J135 -> 0 | K39: =K135 -> 0 | L39: =L135 -> 0 | M39: =M135 -> 0 | N39: =N135 -> 0 | O39: =O135 -> 0 | P39: =P135 -> 0 | ... R39: =R135 -> 0
B40: Lucro Antes dos Impostos (EBT) | D40: =D36+D37 -> 22862.991 | E40: =E36+E37 -> 0 | F40: =F36+F37 -> 0 | G40: =G36+G37 -> 0 | H40: =H36+H37 -> 0 | I40: =I36+I37 -> 0 | J40: =J36+J37 -> 0 | K40: =K36+K37 -> 0 | ... R40: =R36+R37 -> 0
B41: Tributos (Não se Aplica no Simples) | D41: =D42+D43 -> 0 | E41: =E42+E43 -> 0 | F41: =F42+F43 -> 0 | G41: =G42+G43 -> 0 | H41: =H42+H43 -> 0 | I41: =I42+I43 -> 0 | J41: =J42+J43 -> 0 | K41: =K42+K43 -> 0 | ... R41: =R42+R43 -> 0
B42: Imposto de Renda Pessoa Jurídica - IRPJ | I42: 0 | J42: 0 | K42: 0 | L42: 0 | M42: 0 | N42: 0 | O42: 0 | P42: 0 | Q42: 0 | R42: 0
B43: Contribuição Social s/Lucro Líquido - CSLL | I43: 0 | J43: 0 | K43: 0 | L43: 0 | M43: 0 | N43: 0 | O43: 0 | P43: 0 | Q43: 0 | R43: 0
B44: Lucro Líquido Do Exercício | D44: =D40-D41 -> 22862.991 | E44: =E40-E41 -> 0 | F44: =F40-F41 -> 0 | G44: =G40-G41 -> 0 | H44: =H40-H41 -> 0 | I44: =I40-I41 -> 0 | J44: =J40-J41 -> 0 | K44: =K40-K41 -> 0 | ... R44: =R40-R41 -> 0
B45: D&A | D45: =$D$10*$D$56 -> 0 | I45: =I10*I56 -> 0 | J45: =J10*J56 -> 0 | K45: =K10*K56 -> 0 | L45: =L10*L56 -> 0 | M45: =M10*M56 -> 0 | N45: =N10*N56 -> 0 | O45: =O10*O56 -> 0 | P45: =P10*P56 -> 0 | ... R45: =R10*R56 -> 0
B46: EBITDA | D46: =D36+D45 -> 35801.09 | E46: =E36+E45 -> 0 | F46: =F36+F45 -> 0 | G46: =G36+G45 -> 0 | H46: =H36+H45 -> 0 | I46: =I36+I45 -> 0 | J46: =J36+J45 -> 0 | K46: =K36+K45 -> 0 | ... R46: =R36+R45 -> 0
A48: X | B48: BP | D48: =$G$1 -> 2025 | E48: =D48+1 -> 2026 | F48: =E48+1 -> 2027 | G48: =F48+1 -> 2028 | H48: =G48+1 -> 2029 | I48: =H48+1 -> 2030 | J48: =I48+1 -> 2031 | K48: =J48+1 -> 2032 | L48: =K48+1 -> 2033 | ... R48: =Q48+1 -> 2039
B50: Ativo Circulante | D50: =SUM(D51:D53) -> 0 | E50: =SUM(E51:E53) -> 0 | F50: =SUM(F51:F53) -> 0 | G50: =SUM(G51:G53) -> 0 | H50: =SUM(H51:H53) -> 0 | I50: =SUM(I51:I53) -> 0 | J50: =SUM(J51:J53) -> 0 | K50: =SUM(K51:K53) -> 0 | ... R50: =SUM(R51:R53) -> 0
B51: Caixa | I51: =I91 -> 0 | J51: =J91 -> 0 | K51: =K91 -> 0 | L51: =L91 -> 0 | M51: =M91 -> 0 | N51: =N91 -> 0 | O51: =O91 -> 0 | P51: =P91 -> 0 | ... R51: =R91 -> 0
B52: Contas a Receber | I52: =I26*I13/365 -> 0 | J52: =J26*J13/365 -> 0 | K52: =K26*K13/365 -> 0 | L52: =L26*L13/365 -> 0 | M52: =M26*M13/365 -> 0 | N52: =N26*N13/365 -> 0 | O52: =O26*O13/365 -> 0 | P52: =P26*P13/365 -> 0 | ... R52: =R26*R13/365 -> 0
B53: Estoques | I53: =I31*I14/365 -> 0 | J53: =J31*J14/365 -> 0 | K53: =K31*K14/365 -> 0 | L53: =L31*L14/365 -> 0 | M53: =M31*M14/365 -> 0 | N53: =N31*N14/365 -> 0 | O53: =O31*O14/365 -> 0 | P53: =P31*P14/365 -> 0 | ... R53: =R31*R14/365 -> 0
B54: Outros | I54: =H54 -> 0 | J54: =I54 -> 0 | K54: =J54 -> 0 | L54: =K54 -> 0 | M54: =L54 -> 0 | N54: =M54 -> 0 | O54: =N54 -> 0 | P54: =O54 -> 0 | ... R54: =Q54 -> 0
B55: Ativo Não Circulante | D55: =SUM(D56:D57) -> 0 | E55: =SUM(E56:E57) -> 0 | F55: =SUM(F56:F57) -> 0 | G55: =SUM(G56:G57) -> 0 | H55: =SUM(H56:H57) -> 0 | I55: =SUM(I56:I57) -> 0 | J55: =SUM(J56:J57) -> 0 | K55: =SUM(K56:K57) -> 0 | ... R55: =SUM(R56:R57) -> 0
B56: Imobilizado e Intangível | I56: =I115 -> 0 | J56: =J115 -> 0 | K56: =K115 -> 0 | L56: =L115 -> 0 | M56: =M115 -> 0 | N56: =N115 -> 0 | O56: =O115 -> 0 | P56: =P115 -> 0 | ... R56: =R115 -> 0
B57: Outros | I57: =H57 -> 0 | J57: =I57 -> 0 | K57: =J57 -> 0 | L57: =K57 -> 0 | M57: =L57 -> 0 | N57: =M57 -> 0 | O57: =N57 -> 0 | P57: =O57 -> 0 | ... R57: =Q57 -> 0
B58: Total do Ativo | D58: =D55+D50 -> 0 | E58: =E55+E50 -> 0 | F58: =F55+F50 -> 0 | G58: =G55+G50 -> 0 | H58: =H55+H50 -> 0 | I58: =I55+I50 -> 0 | J58: =J55+J50 -> 0 | K58: =K55+K50 -> 0 | ... R58: =R55+R50 -> 0
B60: Passivo Circulante | D60: =SUM(D61:D63) -> 0 | E60: =SUM(E61:E63) -> 0 | F60: =SUM(F61:F63) -> 0 | G60: =SUM(G61:G63) -> 0 | H60: =SUM(H61:H63) -> 0 | I60: =SUM(I61:I63) -> 0 | J60: =SUM(J61:J63) -> 0 | K60: =SUM(K61:K63) -> 0 | ... R60: =SUM(R61:R63) -> 0
B61: Empréstimos e Financiamentos | I61: =I130 -> 0 | J61: =J130 -> 0 | K61: =K130 -> 0 | L61: =L130 -> 0 | M61: =M130 -> 0 | N61: =N130 -> 0 | O61: =O130 -> 0 | P61: =P130 -> 0 | ... R61: =R130 -> 0
B62: Contas a Pagar | I62: =I31*I15/365 -> 0 | J62: =J31*J15/365 -> 0 | K62: =K31*K15/365 -> 0 | L62: =L31*L15/365 -> 0 | M62: =M31*M15/365 -> 0 | N62: =N31*N15/365 -> 0 | O62: =O31*O15/365 -> 0 | P62: =P31*P15/365 -> 0 | ... R62: =R31*R15/365 -> 0
B63: Outros | I63: =H63 -> 0 | J63: =I63 -> 0 | K63: =J63 -> 0 | L63: =K63 -> 0 | M63: =L63 -> 0 | N63: =M63 -> 0 | O63: =N63 -> 0 | P63: =O63 -> 0 | ... R63: =Q63 -> 0
B64: Passivo Não Circulante | D64: =SUM(D65:D66) -> 0 | E64: =SUM(E65:E66) -> 0 | F64: =SUM(F65:F66) -> 0 | G64: =SUM(G65:G66) -> 0 | H64: =SUM(H65:H66) -> 0 | I64: =SUM(I65:I66) -> 0 | J64: =SUM(J65:J66) -> 0 | K64: =SUM(K65:K66) -> 0 | ... R64: =SUM(R65:R66) -> 0
B65: Empréstimos e Financiamentos
B66: Outros | I66: =H66 -> 0 | J66: =I66 -> 0 | K66: =J66 -> 0 | L66: =K66 -> 0 | M66: =L66 -> 0 | N66: =M66 -> 0 | O66: =N66 -> 0 | P66: =O66 -> 0 | ... R66: =Q66 -> 0
B67: Total do Passivo | D67: =D64+D60 -> 0 | E67: =E64+E60 -> 0 | F67: =F64+F60 -> 0 | G67: =G64+G60 -> 0 | H67: =H64+H60 -> 0 | I67: =I64+I60 -> 0 | J67: =J64+J60 -> 0 | K67: =K64+K60 -> 0 | ... R67: =R64+R60 -> 0
B68: Patrimônio Líquido
B69: Passivo + PL | D69: =D67+D68 -> 0 | E69: =E67+E68 -> 0 | F69: =F67+F68 -> 0 | G69: =G67+G68 -> 0 | H69: =H67+H68 -> 0 | I69: =I67+I68 -> 0 | J69: =J67+J68 -> 0 | K69: =K67+K68 -> 0 | ... R69: =R67+R68 -> 0
B70: Check | D70: ✓ | E70: ✓ | F70: ✓ | G70: ✓ | H70: ✓ | I70: ✓ | J70: ✓ | K70: ✓ | L70: ✓ | M70: ✓ | N70: ✓ | O70: ✓ | P70: ✓ | Q70: ✓ | R70: ✓
A72: X | B72: DFC | D72: =$G$1 -> 2025 | E72: =D72+1 -> 2026 | F72: =E72+1 -> 2027 | G72: =F72+1 -> 2028 | H72: =G72+1 -> 2029 | I72: =H72+1 -> 2030 | J72: =I72+1 -> 2031 | K72: =J72+1 -> 2032 | L72: =K72+1 -> 2033 | ... R72: =Q72+1 -> 2039
B74: CFO | D74: =SUM(D75:D77) -> 22862.991 | E74: =SUM(E75:E77) -> 0 | F74: =SUM(F75:F77) -> 0 | G74: =SUM(G75:G77) -> 0 | H74: =SUM(H75:H77) -> 0 | I74: =SUM(I75:I77) -> 0 | J74: =SUM(J75:J77) -> 0 | K74: =SUM(K75:K77) -> 0 | ... R74: =SUM(R75:R77) -> 0
B75: (+) Lucro Líquido | D75: =D44 -> 22862.991 | E75: =E44 -> 0 | F75: =F44 -> 0 | G75: =G44 -> 0 | H75: =H44 -> 0 | I75: =I44 -> 0 | J75: =J44 -> 0 | K75: =K44 -> 0 | ... R75: =R44 -> 0
B76: (+) D&A | D76: =D45 -> 0 | E76: =E45 -> 0 | F76: =F45 -> 0 | G76: =G45 -> 0 | H76: =H45 -> 0 | I76: =I45 -> 0 | J76: =J45 -> 0 | K76: =K45 -> 0 | ... R76: =R45 -> 0
B77: (+) Var. NCG | D77: =D99 -> 0 | E77: =E99 -> 0 | F77: =F99 -> 0 | G77: =G99 -> 0 | H77: =H99 -> 0 | I77: =I99 -> 0 | J77: =J99 -> 0 | K77: =K99 -> 0 | ... R77: =R99 -> 0
B79: CFI | D79: =D80 -> 0 | E79: =E80 -> 0 | F79: =F80 -> 0 | G79: =G80 -> 0 | H79: =H80 -> 0 | I79: =I80 -> 0 | J79: =J80 -> 0 | K79: =K80 -> 0 | ... R79: =R80 -> 0
B80: (+) Capex
B82: CFF | D82: =D83-D84-D85 -> 0 | E82: =E83-E84-E85 -> 0 | F82: =F83-F84-F85 -> 0 | G82: =G83-G84-G85 -> 0 | H82: =H83-H84-H85 -> 0 | I82: =I83-I84-I85 -> 0 | J82: =J83-J84-J85 -> 0 | K82: =K83-K84-K85 -> 0 | ... R82: =R83-R84-R85 -> 0
B83: (+) Variação dos Empréstimos
B84: (-) Juros
B85: (-) Dividendos Pagos
B87: Outros | D87: =D91-D89-D90 -> -22862.991 | E87: =E91-E89-E90 -> 0 | F87: =F91-F89-F90 -> 0 | G87: =G91-G89-G90 -> 0 | H87: =H91-H89-H90 -> 0 | I87: =I91-I89-I90 -> 0 | J87: =J91-J89-J90 -> 0 | K87: =K91-K89-K90 -> 0 | ... R87: =R91-R89-R90 -> 0
B89: Var. Caixa | D89: =D82+D79+D74 -> 22862.991 | E89: =E82+E79+E74 -> 0 | F89: =F82+F79+F74 -> 0 | G89: =G82+G79+G74 -> 0 | H89: =H82+H79+H74 -> 0 | I89: =I82+I79+I74 -> 0 | J89: =J82+J79+J74 -> 0 | K89: =K82+K79+K74 -> 0 | ... R89: =R82+R79+R74 -> 0
B90: Abertura do Caixa | D90: 0 | E90: =D91 -> 0 | F90: =E91 -> 0 | G90: =F91 -> 0 | H90: =G91 -> 0 | I90: =H91 -> 0 | J90: =I91 -> 0 | K90: =J91 -> 0 | L90: =K91 -> 0 | ... R90: =Q91 -> 0
B91: Posição Final de Caixa | D91: =D51 -> 0 | E91: =E51 -> 0 | F91: =F51 -> 0 | G91: =G51 -> 0 | H91: =H51 -> 0 | I91: =I89+I90 -> 0 | J91: =J89+J90 -> 0 | K91: =K89+K90 -> 0 | L91: =L89+L90 -> 0 | M91: =M89+M90 -> 0 | N91: =N89+N90 -> 0 | O91: =O89+O90 -> 0 | P91: =P89+P90 -> 0 | ... R91: =R89+R90 -> 0
A93: X | B93: Tabela Auxiliar | D93: =$G$1 -> 2025 | E93: =D93+1 -> 2026 | F93: =E93+1 -> 2027 | G93: =F93+1 -> 2028 | H93: =G93+1 -> 2029 | I93: =H93+1 -> 2030 | J93: =I93+1 -> 2031 | K93: =J93+1 -> 2032 | L93: =K93+1 -> 2033 | ... R93: =Q93+1 -> 2039
B95: NCG
B96: Contas a Receber | D96: =D52 -> 0 | E96: =E52 -> 0 | F96: =F52 -> 0 | G96: =G52 -> 0 | H96: =H52 -> 0 | I96: =I52 -> 0 | J96: =J52 -> 0 | K96: =K52 -> 0 | ... R96: =R52 -> 0
B97: Estoques | D97: =D53 -> 0 | E97: =E53 -> 0 | F97: =F53 -> 0 | G97: =G53 -> 0 | H97: =H53 -> 0 | I97: =I53 -> 0 | J97: =J53 -> 0 | K97: =K53 -> 0 | ... R97: =R53 -> 0
B98: Contas a Pagar | D98: =D62 -> 0 | E98: =E62 -> 0 | F98: =F62 -> 0 | G98: =G62 -> 0 | H98: =H62 -> 0 | I98: =I62 -> 0 | J98: =J62 -> 0 | K98: =K62 -> 0 | ... R98: =R62 -> 0
B99: Necessidade de Capital de Giro (NCG) (Inputar Manual)
B100: Var. NCG | E100: =E99-D99 -> 0 | F100: =F99-E99 -> 0 | G100: =G99-F99 -> 0 | H100: =H99-G99 -> 0 | I100: =I99-H99 -> 0 | J100: =J99-I99 -> 0 | K100: =K99-J99 -> 0 | L100: =L99-K99 -> 0 | ... R100: =R99-Q99 -> 0
B102: Dívida
B103: Posição Inicial da Dívida | E103: =D105 -> 0 | F103: =E105 -> 0 | G103: =F105 -> 0 | H103: =G105 -> 0 | I103: =H105 -> 0 | J103: =I105 -> 0 | K103: =J105 -> 0 | L103: =K105 -> 0 | ... R103: =Q105 -> 0
B104: Variação dos Empréstimos | D104: =D83 -> 0 | E104: =E83 -> 0 | F104: =F83 -> 0 | G104: =G83 -> 0 | H104: =H83 -> 0 | I104: =I83 -> 0 | J104: =J83 -> 0 | K104: =K83 -> 0 | ... R104: =R83 -> 0
B105: Posição Final da Dívida | D105: =D61+D65 -> 0 | E105: =E61+E65 -> 0 | F105: =F61+F65 -> 0 | G105: =G61+G65 -> 0 | H105: =H61+H65 -> 0 | I105: =I61+I65 -> 0 | J105: =J61+J65 -> 0 | K105: =K61+K65 -> 0 | ... R105: =R61+R65 -> 0
B107: Indicadores
B108: CDI | D108: 0.1465 | E108: 0.119 | F108: 0.099 | G108: =F108 -> 0.099 | H108: =G108 -> 0.099 | I108: =H108 -> 0.099 | J108: =I108 -> 0.099 | K108: =J108 -> 0.099 | L108: =K108 -> 0.099 | M108: =L108 -> 0.099 | N108: =M108 -> 0.099 | ... R108: =Q108 -> 0.099
B109: IPCA | D109: 0.0496 | E109: 0.0401 | F109: 0.0383 | G109: =F109 -> 0.0383 | H109: =G109 -> 0.0383 | I109: =H109 -> 0.0383 | J109: =I109 -> 0.0383 | K109: =J109 -> 0.0383 | L109: =K109 -> 0.0383 | M109: =L109 -> 0.0383 | N109: =M109 -> 0.0383 | ... R109: =Q109 -> 0.0383
B111: Imobilizado
B112: Abertura Imobilizado | E112: =D115 -> 0 | F112: =E115 -> 0 | G112: =F115 -> 0 | H112: =G115 -> 0 | I112: =H115 -> 0 | J112: =I115 -> 0 | K112: =J115 -> 0 | L112: =K115 -> 0 | ... R112: =Q115 -> 0
B113: (+) CapEx | D113: =D80 -> 0 | E113: =E80 -> 0 | F113: =F80 -> 0 | G113: =G80 -> 0 | H113: =H80 -> 0 | I113: =I80 -> 0 | J113: =J80 -> 0 | K113: =K80 -> 0 | ... R113: =R80 -> 0
B114: (-) D&A (Inputar manual) | D114: =D10*D112 -> 0 | E114: =E10*E112 -> 0 | F114: =F10*F112 -> 0 | G114: =G10*G112 -> 0 | H114: =H10*H112 -> 0 | I114: =I10*I112 -> 0 | J114: =J10*J112 -> 0 | K114: =K10*K112 -> 0 | ... R114: =R10*R112 -> 0
B115: Imobilizado Final | D115: =D112+D113-D114 -> 0 | E115: =E112+E113-E114 -> 0 | F115: =F112+F113-F114 -> 0 | G115: =G112+G113-G114 -> 0 | H115: =H112+H113-H114 -> 0 | I115: =I112+I113-I114 -> 0 | J115: =J112+J113-J114 -> 0 | K115: =K112+K113-K114 -> 0 | ... R115: =R112+R113-R114 -> 0
A117: X | B117: Revolver | D117: =$G$1 -> 2025 | E117: =D117+1 -> 2026 | F117: =E117+1 -> 2027 | G117: =F117+1 -> 2028 | H117: =G117+1 -> 2029 | I117: =H117+1 -> 2030 | J117: =I117+1 -> 2031 | K117: =J117+1 -> 2032 | L117: =K117+1 -> 2033 | ... R117: =Q117+1 -> 2039
B119: Caixa Disponível
B120: Abertura do Caixa
...

Sheet Fontes
B2: IPCA | C2: https://www.bcb.gov.br/content/focus/focus/R20241227.pdf
B3: CDI | C3: https://www.bcb.gov.br/content/focus/focus/R20241227.pdf
B5: Sacas/ano
B30: Preço da Saca | C30: https://www.noticiasagricolas.com.br/cotacoes/cafe
B31: Prêmio Café Especial | C31: Conversa com Torrador
B32: Alíquota Simples Nacional (Anexo 2) | C32: https://www.contabilizei.com.br/contabilidade-online/tabela-simples-nacional-completa/
B33: Exemplo de Empresa | C33: https://www.3coracoes.com.br/wp-content/uploads/2024/08/Demonstracoes-Financeira-2023-Tres-Coracoes-Alimentos-SA-BR-GAAP.pdf?x20808
B34: Energia (R$/kWh) Grupo A4 - Modalidade Tarifária Verde | C34: https://www.dme-pc.com.br/atendimento/tarifas
B35: Consumo de Energia
B36: Preço GLP | C36: https://precos.petrobras.com.br/sele%C3%A7%C3%A3o-de-estados-glp
B37: Consumo GLP | C37: https://kaffeetorradores.com/product/torrador-basico-15kg/
B38: Preço Água
B39: Consumo Água

Sheet Simulação Empréstimo
C1: =YEAR(TODAY()) -> 2026 | D1: =C1+1 -> 2027 | E1: =D1+1 -> 2028 | F1: =E1+1 -> 2029 | G1: =F1+1 -> 2030 | H1: =G1+1 -> 2031
B2: IPCA | C2: 0.039 | D2: 0.0378 | E2: 0.036 | F2: 0.035 | G2: 0.035 | H2: 0.035
B3: CDI | C3: 0.1475 | D3: 0.125 | E3: 0.105 | F3: 0.1 | G3: 0.1 | H3: 0.1
B5: Volume | C5: 250000 | E5: Custos Mensais | J5: Ano | K5: Juros | L5: Amortização | M5: Saldo Devedor
B6: Indexador | C6: CDI+ | E6: Custos Anuais | J6: 2025 | K6: 12938.099 | L6: 0 | M6: 250000
B7: ="Taxa "&" ("&C6&")" -> Taxa (CDI+) | C7: 0.07 | J7: 2026 | K7: 44124.906 | L7: 41666.667 | M7: 208333.33
B8: Prazo | C8: 60 | E8: Custos Flat | J8: 2027 | K8: 30846.301 | L8: 55555.556 | M8: 152777.78
B9: Carência Amort. | C9: 6 | E9: Fundo de Despesa | J9: 2028 | K9: 20889.875 | L9: 55555.556 | M9: 97222.222
B10: Data estimada emissão | C10: 45901 | E10: Trigger | F10: 0 | J10: 2029 | K10: 11774.293 | L10: 55555.556 | M10: 41666.667
B11: Amortização | C11: Mensal | D11: 1 | E11: Fundo de Reserva | J11: 2030 | K11: 2848.6193 | L11: 41666.667 | M11: -1.891749e-10
B12: Tipo Amortização | C12: SAC | E12: Volume Líquido | F12: =C5-F11-F9-F8 -> 250000
B14: # | C14: DATA | D14: ANO | E14: AMORTIZAÇÃO | F14: TAXA EFETIVA | G14: JUROS | H14: PARCELA | I14: SALDO DEVEDOR
B15: 0 | C15: 45901 | D15: =YEAR(C15) -> 2025 | E15: 0 | F15: 0 | I15: =$C$5 -> 250000
B16: 1 | C16: 45931 | D16: =YEAR(C16) -> 2025 | E16: 0 | F16: 0.017250798 | G16: 4312.6996 | H16: 4312.6996 | I16: 250000
B17: 2 | C17: 45962 | D17: =YEAR(C17) -> 2025 | E17: 0 | F17: 0.017250798 | G17: 4312.6996 | H17: 4312.6996 | I17: 250000
B18: 3 | C18: 45992 | D18: =YEAR(C18) -> 2025 | E18: 0 | F18: 0.017250798 | G18: 4312.6996 | H18: 4312.6996 | I18: 250000
B19: 4 | C19: 46023 | D19: =YEAR(C19) -> 2026 | E19: 0 | F19: 0.015573496 | G19: 3893.374 | H19: 3893.374 | I19: 250000
B20: 5 | C20: 46054 | D20: =YEAR(C20) -> 2026 | E20: 0 | F20: 0.015573496 | G20: 3893.374 | H20: 3893.374 | I20: 250000
B21: 6 | C21: 46082 | D21: =YEAR(C21) -> 2026 | E21: 0 | F21: 0.015573496 | G21: 3893.374 | H21: 3893.374 | I21: 250000
B22: 7 | C22: 46113 | D22: =YEAR(C22) -> 2026 | E22: 4629.6296 | F22: 0.015573496 | G22: 3893.374 | H22: 8523.0036 | I22: 245370.37
B23: 8 | C23: 46143 | D23: =YEAR(C23) -> 2026 | E23: 4629.6296 | F23: 0.015573496 | G23: 3821.2745 | H23: 8450.9041 | I23: 240740.74
B24: 9 | C24: 46174 | D24: =YEAR(C24) -> 2026 | E24: 4629.6296 | F24: 0.015573496 | G24: 3749.175 | H24: 8378.8046 | I24: 236111.11
B25: 10 | C25: 46204 | D25: =YEAR(C25) -> 2026 | E25: 4629.6296 | F25: 0.015573496 | G25: 3677.0755 | H25: 8306.7051 | I25: 231481.48
B26: 11 | C26: 46235 | D26: =YEAR(C26) -> 2026 | E26: 4629.6296 | F26: 0.015573496 | G26: 3604.9759 | H26: 8234.6056 | I26: 226851.85
B27: 12 | C27: 46266 | D27: =YEAR(C27) -> 2026 | E27: 4629.6296 | F27: 0.015573496 | G27: 3532.8764 | H27: 8162.5061 | I27: 222222.22
... B75: 60 | C75: 47727 | D75: =YEAR(C75) -> 2030 | E75: 4629.6296 | F75: 0.013673373 | G75: 63.302652 | H75: 4692.9323 | I75: -1.891749e-10

Sheet Investimento Inicial
A2: Máquina de torra seminova | B2: 70000
A3: Balança de comércio | B3: 500
A4: 6 meses de aluguel | B4: =$C$4*6 -> 30000 | C4: =-Precificação!$B$10 -> 5000
A5: 12 meses de café | B5: =$C$5*$D$5 -> 139500 | C5: =SUM('Fluxo de Caixa'!$C$4:$AZ$4) -> 45 | D5: 3100
A6: Seguro | B6: 5000
A7: Marketing | B7: 3000
A8: Identidade visual | B8: 4000
A9: Site | B9: 3000
A10: 6 meses de contabilidade | B10: =$C$10*6 -> 6000 | C10: 1000
A11: Total | B11: =SUM(B2:B10) -> 261000

Sheet Precificação
A2: Produção mensal (kg) | B2: 180 | C2: Faturamento | D2: =$B$5*B34 -> 33738.984
A3: Data | B3: 45840 | C3: Lucro | D3: =$D$2+B32 -> 1606.6183
A4: Preço café verde (R$/kg) | B4: =3100/60 -> 51.666667 | C4: Margem | D4: =$D$3/$D$2 -> 0.047619048
A5: Pacotinhos | B5: =$B$2/$B$6 -> 720 | C5: CPV | D5: =($B$12-$B$10)+$B$17+$B$22 -> -15773.8
A6: Peso do Pacotinho | B6: 0.25 | C6: SG&A | D6: =$B$10+$B$24+$B$27+$B$28+$B$29 -> -12012.729
B8: Torrefação | E8: %
A9: Frete do café verde | B9: =-1000 -> -1000 | E9: =-B9/$B$32 -> -0.031121269
A10: Aluguel do galpão | B10: -5000 | E10: =-B10/$B$32 -> -0.15560635
A11: Custo café verde | B11: =-$B$4*$B$2 -> -9300 | E11: =-B11/$B$32 -> -0.28942781
A12: Custos na torrefação | B12: =SUM(B9:B11) -> -15300 | E12: =-B12/$B$32 -> -0.47615542
A14: Perda de peso na torra | B14: =-$C$14*$B$4*$B$2 -> -1674 | C14: 0.18 | E14: =-B14/$B$32 -> -0.052097005
A15: Água e luz | B15: =-300 -> -300 | E15: =-B15/$B$32 -> -0.0093363808
A16: GLP | B16: =-$C$16*$B$2 -> -154.8 | C16: 0.86 | E16: =-B16/$B$32 -> -0.0048175725
A17: Custos de torra | B17: =SUM(B14:B16) -> -2128.8 | E17: =-B17/$B$32 -> -0.066250958
A19: Pacotes | B19: =-$C$19*$D$19 -> -2880 | C19: =$B$5 -> 720 | D19: 4 | E19: =-B19/$B$32 -> -0.089629256
A20: Trabalho direto | B20: 0 | C20: Inclui INSS e FGTS | D20: 0.3 | E20: =-B20/$B$32 -> 0
A21: Outros materiais | B21: =-$C$21*($B$2*$B$4) -> -465 | C21: 0.05 | E21: =-B21/$B$32 -> -0.01447139
A22: Custos materiais | B22: =SUM(B19:B21) -> -3345 | E22: =-B22/$B$32 -> -0.10410065
A24: Outros Custos | B24: =-$C$24*$B$2*$B$4 -> -465 | C24: 0.05 | E24: =-B24/$B$32 -> -0.01447139
A25: Juros | B25: =-AVERAGE('Simulação Empréstimo'!$K$6:$K$11)/12 -> -1714.1957 | E25: =-B25/$B$32 -> -0.053347947
A26: Impostos Simples | B26: =-$C$26*$D$2 -> -2631.6407 | C26: 0.078 | D26: Tabela II Simples | E26: =-B26/$B$32 -> -0.0819
A27: Perdas operacionais | B27: =-$C$27*($B$2*$B$4) -> -186 | C27: 0.02 | E27: =-B27/$B$32 -> -0.0057885561
A28: Pró-labore | B28: =-$D$2*$C$28 -> -2361.7288 | C28: 0.07 | E28: =-B28/$B$32 -> -0.0735
A29: Marketing e Contabilidade | B29: -4000
A30: Outros custos | B30: =SUM(B24:B29) -> -11358.565 | E30: =-B30/$B$32 -> -0.35349297
A32: Custos totais | B32: =SUM($B$30+$B$22+$B$17+$B$12) -> -32132.365
A34: Preço por pacotinho | B34: =(-B32+(-$B$32*$C$34))/$B$5 -> 46.859699 | C34: 0.05

Sheet Fluxo de Caixa
A1: Preço Saca de Café | C1: 0 | G1: =C$1+1 -> 1 | K1: =G$1+1 -> 2 | O1: =K$1+1 -> 3 | S1: =O$1+1 -> 4 | W1: =S$1+1 -> 5 | AA1: =W$1+1 -> 6 | AE1: =AA$1+1 -> 7 | AI1: =AE$1+1 -> 8 | AM1: =AI$1+1 -> 9 | AQ1: =AM$1+1 -> 10 | AU1: =AQ$1+1 -> 11 | AY1: =AU$1+1 -> 12 | BC1: =AY$1+1 -> 13 | BG1: =BC$1+1 -> 14 | BK1: =BG$1+1 -> 15 | BO1: =BK$1+1 -> 16 | BS1: =BO$1+1 -> 17 | BW1: =BS$1+1 -> 18 | CA1: =BW$1+1 -> 19 | CE1: =CA$1+1 -> 20 | CI1: =CE$1+1 -> 21 | CM1: =CI$1+1 -> 22 | CQ1: =CM$1+1 -> 23 | CU1: =CQ$1+1 -> 24 | CY1: =CU$1+1 -> 25 | DC1: =CY$1+1 -> 26 | DG1: =DC$1+1 -> 27 | DK1: =DG$1+1 -> 28 | DO1: =DK$1+1 -> 29 | DS1: =DO$1+1 -> 30 | DW1: =DS$1+1 -> 31 | EA1: =DW$1+1 -> 32 | EE1: =EA$1+1 -> 33 | EI1: =EE$1+1 -> 34 | EM1: =EI$1+1 -> 35 | EQ1: =EM$1+1 -> 36 | EU1: =EQ$1+1 -> 37 | EY1: =EU$1+1 -> 38 | FC1: =EY$1+1 -> 39 | FG1: =FC$1+1 -> 40 | FK1: =FG$1+1 -> 41 | FO1: =FK$1+1 -> 42 | FS1: =FO$1+1 -> 43 | FW1: =FS$1+1 -> 44 | GA1: =FW$1+1 -> 45 | GE1: =GA$1+1 -> 46 | GI1: =GE$1+1 -> 47 | GM1: =GI$1+1 -> 48 | GQ1: =GM$1+1 -> 49 | GU1: =GQ$1+1 -> 50 | GY1: =GU$1+1 -> 51 | HC1: =GY$1+1 -> 52 | HG1: =HC$1+1 -> 53 | HK1: =HG$1+1 -> 54 | HO1: =HK$1+1 -> 55 | HS1: =HO$1+1 -> 56 | HW1: =HS$1+1 -> 57 | IA1: =HW$1+1 -> 58 | IE1: =IA$1+1 -> 59 | II1: =IE$1+1 -> 60 | IM1: =II$1+1 -> 61 | IQ1: =IM$1+1 -> 62 | IU1: =IQ$1+1 -> 63 | IY1: =IU$1+1 -> 64 | JC1: =IY$1+1 -> 65 | JG1: =JC$1+1 -> 66 | JK1: =JG$1+1 -> 67 | JO1: =JK$1+1 -> 68 | JS1: =JO$1+1 -> 69 | JW1: =JS$1+1 -> 70 | KA1: =JW$1+1 -> 71 | KE1: =KA$1+1 -> 72
A2: 3100 | C2: Receitas | D2: R$ | G2: Receitas | H2: R$ | K2: Receitas | L2: R$ | O2: Receitas | P2: R$ | S2: Receitas | T2: R$ | W2: Receitas | X2: R$ | AA2: Receitas | AB2: R$ | AE2: Receitas | AF2: R$ | AI2: Receitas | AJ2: R$ | AM2: Receitas | AN2: R$ | AQ2: Receitas | AR2: R$ | AU2: Receitas | AV2: R$ | AY2: Receitas | AZ2: R$ | BC2: Receitas | BD2: R$ | BG2: Receitas | BH2: R$ | BK2: Receitas | BL2: R$ | BO2: Receitas | BP2: R$ | BS2: Receitas | BT2: R$ | BW2: Receitas | BX2: R$ | CA2: Receitas | CB2: R$ | CE2: Receitas | CF2: R$ | CI2: Receitas | CJ2: R$ | CM2: Receitas | CN2: R$ | CQ2: Receitas | CR2: R$ | CU2: Receitas | CV2: R$ | CY2: Receitas | CZ2: R$ | DC2: Receitas | DD2: R$ | DG2: Receitas | DH2: R$ | DK2: Receitas | DL2: R$ | DO2: Receitas | DP2: R$ | DS2: Receitas | DT2: R$ | DW2: Receitas | DX2: R$ | EA2: Receitas | EB2: R$ | EE2: Receitas | EF2: R$ | EI2: Receitas | EJ2: R$ | EM2: Receitas | EN2: R$ | EQ2: Receitas | ER2: R$ | EU2: Receitas | EV2: R$ | EY2: Receitas | EZ2: R$ | FC2: Receitas | FD2: R$ | FG2: Receitas | FH2: R$ | FK2: Receitas | FL2: R$ | FO2: Receitas | FP2: R$ | FS2: Receitas | FT2: R$ | FW2: Receitas | FX2: R$ | GA2: Receitas | GB2: R$ | GE2: Receitas | GF2: R$ | GI2: Receitas | GJ2: R$ | GM2: Receitas | GN2: R$ | GQ2: Receitas | GR2: R$ | GU2: Receitas | GV2: R$ | GY2: Receitas | GZ2: R$ | HC2: Receitas | HD2: R$ | HG2: Receitas | HH2: R$ | HK2: Receitas | HL2: R$ | HO2: Receitas | HP2: R$ | HS2: Receitas | HT2: R$ | HW2: Receitas | HX2: R$ | IA2: Receitas | IB2: R$ | IE2: Receitas | IF2: R$ | II2: Receitas | IJ2: R$ | IM2: Receitas | IN2: R$ | IQ2: Receitas | IR2: R$ | IU2: Receitas | IV2: R$ | IY2: Receitas | IZ2: R$ | JC2: Receitas | JD2: R$ | JG2: Receitas | JH2: R$ | JK2: Receitas | JL2: R$ | JO2: Receitas | JP2: R$ | JS2: Receitas | JT2: R$ | JW2: Receitas | JX2: R$ | KA2: Receitas | KB2: R$ | KE2: Receitas | KF2: R$
A3: 40 | C3: Venda de café | D3: =((D$4*60)/0.25)*D$5 -> 28800 | E3: =-(D$3+D$30)/D$30 -> -0.78362458 | G3: Venda de café | H3: =((H$4*60)/0.25)*H$5 -> 28800 | I3: =-(H$3+H$30)/H$30 -> 0.32706689 | K3: Venda de café | L3: =((L$4*60)/0.25)*L$5 -> 28800 | M3: =-(L$3+L$30)/L$30 -> 0.32706689 | O3: Venda de café | P3: =((P$4*60)/0.25)*P$5 -> 28800 | Q3: =-(P$3+P$30)/P$30 -> -0.43085249 | S3: Venda de café | T3: =((T$4*60)/0.25)*T$5 -> 28800 | U3: =-(T$3+T$30)/T$30 -> 0.32706689 | W3: Venda de café | X3: =((X$4*60)/0.25)*X$5 -> 28800 | Y3: =-(X$3+X$30)/X$30 -> 0.32706689 | AA3: Venda de café | AB3: =((AB$4*60)/0.25)*AB$5 -> 28800 | AC3: =-(AB$3+AB$30)/AB$30 -> -0.50131939 | AE3: Venda de café | AF3: =((AF$4*60)/0.25)*AF$5 -> 38400 | AG3: =-(AF$3+AF$30)/AF$30 -> 0.44732005 | AI3: Venda de café | AJ3: =((AJ$4*60)/0.25)*AJ$5 -> 38400 | AK3: =-(AJ$3+AJ$30)/AJ$30 -> 0.44732005 | AM3: Venda de café | AN3: =((AN$4*60)/0.25)*AN$5 -> 38400 | AO3: =-(AN$3+AN$30)/AN$30 -> -0.40678303 | AQ3: Venda de café | AR3: =((AR$4*60)/0.25)*AR$5 -> 38400 | AS3: =-(AR$3+AR$30)/AR$30 -> 0.44732005 | AU3: Venda de café | AV3: =((AV$4*60)/0.25)*AV$5 -> 38400 | AW3: =-(AV$3+AV$30)/AV$30 -> 0.40265796 | AY3: Venda de café | AZ3: =((AZ$4*60)/0.25)*AZ$5 -> 38400 | BA3: =-(AZ$3+AZ$30)/AZ$30 -> -0.44085755 | BC3: Venda de café | BD3: =((BD$4*60)/0.25)*BD$5 -> 38400 | BE3: =-(BD$3+BD$30)/BD$30 -> 0.40265796 | BG3: Venda de café | BH3: =((BH$4*60)/0.25)*BH$5 -> 48000 | BI3: =-(BH$3+BH$30)/BH$30 -> 0.52539808 | BK3: Venda de café | BL3: =((BL$4*60)/0.25)*BL$5 -> 48000 | BM3: =-(BL$3+BL$30)/BL$30 -> -0.39215266 | BO3: Venda de café | BP3: =((BP$4*60)/0.25)*BP$5 -> 48000 | BQ3: =-(BP$3+BP$30)/BP$30 -> 0.52539808 | BS3: Venda de café | BT3: =((BT$4*60)/0.25)*BT$5 -> 48000 | BU3: =-(BT$3+BT$30)/BT$30 -> 0.52539808 | BW3: Venda de café | BX3: =((BX$4*60)/0.25)*BX$5 -> 48000 | BY3: =-(BX$3+BX$30)/BX$30 -> -0.41511344 | CA3: Venda de café | CB3: =((CB$4*60)/0.25)*CB$5 -> 48000 | CC3: =-(CB$3+CB$30)/CB$30 -> 0.52539808 | CE3: Venda de café | CF3: =((CF$4*60)/0.25)*CF$5 -> 57600 | CG3: =-(CF$3+CF$30)/CF$30 -> 0.61989794 | CI3: Venda de café | CJ3: =((CJ$4*60)/0.25)*CJ$5 -> 57600 | CK3: =-(CJ$3+CJ$30)/CJ$30 -> -0.37633852 | CM3: Venda de café | CN3: =((CN$4*60)/0.25)*CN$5 -> 57600 | CO3: =-(CN$3+CN$30)/CN$30 -> 0.61989794 | CQ3: Venda de café | CR3: =((CR$4*60)/0.25)*CR$5 -> 57600 | CS3: =-(CR$3+CR$30)/CR$30 -> 0.61989794 | CU3: Venda de café | CV3: =((CV$4*60)/0.25)*CV$5 -> 57600 | CW3: =-(CV$3+CV$30)/CV$30 -> -0.37633852 | CY3: Venda de café | CZ3: =((CZ$4*60)/0.25)*CZ$5 -> 57600 | DA3: =-(CZ$3+CZ$30)/CZ$30 -> 0.61989794 | DC3: Venda de café | DD3: =((DD$4*60)/0.25)*DD$5 -> 57600 | DE3: =-(DD$3+DD$30)/DD$30 -> 0.61989794 | DG3: Venda de café | DH3: =((DH$4*60)/0.25)*DH$5 -> 67200 | DI3: =-(DH$3+DH$30)/DH$30 -> -0.36452937 | DK3: Venda de café | DL3: =((DL$4*60)/0.25)*DL$5 -> 67200 | DM3: =-(DL$3+DL$30)/DL$30 -> 0.69489834 | DO3: Venda de café | DP3: =((DP$4*60)/0.25)*DP$5 -> 67200 | DQ3: =-(DP$3+DP$30)/DP$30 -> 0.69489834 | DS3: Venda de café | DT3: =((DT$4*60)/0.25)*DT$5 -> 67200 | DU3: =-(DT$3+DT$30)/DT$30 -> -0.36452937 | DW3: Venda de café | DX3: =((DX$4*60)/0.25)*DX$5 -> 67200 | DY3: =-(DX$3+DX$30)/DX$30 -> 0.66111332 | EA3: Venda de café | EB3: =((EB$4*60)/0.25)*EB$5 -> 67200 | EC3: =-(EB$3+EB$30)/EB$30 -> 0.66111332 | EE3: Venda de café | EF3: =((EF$4*60)/0.25)*EF$5 -> 67200 | EG3: =-(EF$3+EF$30)/EF$30 -> -0.40401648 | EI3: Venda de café | EJ3: =((EJ$4*60)/0.25)*EJ$5 -> 76800 | EK3: =-(EJ$3+EJ$30)/EJ$30 -> 0.71963671 | EM3: Venda de café | EN3: =((EN$4*60)/0.25)*EN$5 -> 76800 | EO3: =-(EN$3+EN$30)/EN$30 -> 0.71963671 | EQ3: Venda de café | ER3: =((ER$4*60)/0.25)*ER$5 -> 76800 | ES3: =-(ER$3+ER$30)/ER$30 -> -0.36032301 | EU3: Venda de café | EV3: =((EV$4*60)/0.25)*EV$5 -> 76800 | EW3: =-(EV$3+EV$30)/EV$30 -> 0.71963671 | EY3: Venda de café | EZ3: =((EZ$4*60)/0.25)*EZ$5 -> 76800 | FA3: =-(EZ$3+EZ$30)/EZ$30 -> 0.71963671 | FC3: Venda de café | FD3: =((FD$4*60)/0.25)*FD$5 -> 76800 | FE3: =-(FD$3+FD$30)/FD$30 -> -0.39173422 | FG3: Venda de café | FH3: =((FH$4*60)/0.25)*FH$5 -> 86400 | FI3: =-(FH$3+FH$30)/FH$30 -> 0.7680862 | FK3: Venda de café | FL3: =((FL$4*60)/0.25)*FL$5 -> 86400 | FM3: =-(FL$3+FL$30)/FL$30 -> 0.7680862 | FO3: Venda de café | FP3: =((FP$4*60)/0.25)*FP$5 -> 86400 | FQ3: =-(FP$3+FP$30)/FP$30 -> -0.35313071 | FS3: Venda de café | FT3: =((FT$4*60)/0.25)*FT$5 -> 86400 | FU3: =-(FT$3+FT$30)/FT$30 -> 0.7680862 | FW3: Venda de café | FX3: =((FX$4*60)/0.25)*FX$5 -> 86400 | FY3: =-(FX$3+FX$30)/FX$30 -> 0.7680862 | GA3: Venda de café | GB3: =((GB$4*60)/0.25)*GB$5 -> 86400 | GC3: =-(GB$3+GB$30)/GB$30 -> -0.36780362 | GE3: Venda de café | GF3: =((GF$4*60)/0.25)*GF$5 -> 86400 | GG3: =-(GF$3+GF$30)/GF$30 -> 0.7680862 | GI3: Venda de café | GJ3: =((GJ$4*60)/0.25)*GJ$5 -> 96000 | GK3: =-(GJ$3+GJ$30)/GJ$30 -> 0.80885676 | GM3: Venda de café | GN3: =((GN$4*60)/0.25)*GN$5 -> 96000 | GO3: =-(GN$3+GN$30)/GN$30 -> -0.34725935 | GQ3: Venda de café | GR3: =((GR$4*60)/0.25)*GR$5 -> 96000 | GS3: =-(GR$3+GR$30)/GR$30 -> 0.80885676 | GU3: Venda de café | GV3: =((GV$4*60)/0.25)*GV$5 -> 96000 | GW3: =-(GV$3+GV$30)/GV$30 -> 0.80885676 | GY3: Venda de café | GZ3: =((GZ$4*60)/0.25)*GZ$5 -> 96000 | HA3: =-(GZ$3+GZ$30)/GZ$30 -> -0.34725935 | HC3: Venda de café | HD3: =((HD$4*60)/0.25)*HD$5 -> 96000 | HE3: =-(HD$3+HD$30)/HD$30 -> 0.80885676 | HG3: Venda de café | HH3: =((HH$4*60)/0.25)*HH$5 -> 96000 | HI3: =-(HH$3+HH$30)/HH$30 -> 0.80885676 | HK3: Venda de café | HL3: =((HL$4*60)/0.25)*HL$5 -> 105600 | HM3: =-(HL$3+HL$30)/HL$30 -> -0.34237565 | HO3: Venda de café | HP3: =((HP$4*60)/0.25)*HP$5 -> 105600 | HQ3: =-(HP$3+HP$30)/HP$30 -> 0.84363993 | HS3: Venda de café | HT3: =((HT$4*60)/0.25)*HT$5 -> 105600 | HU3: =-(HT$3+HT$30)/HT$30 -> 0.84363993 | HW3: Venda de café | HX3: =((HX$4*60)/0.25)*HX$5 -> 105600 | HY3: =-(HX$3+HX$30)/HX$30 -> -0.34237565 | IA3: Venda de café | IB3: =((IB$4*60)/0.25)*IB$5 -> 105600 | IC3: =-(IB$3+IB$30)/IB$30 -> 0.84363993 | IE3: Venda de café | IF3: =((IF$4*60)/0.25)*IF$5 -> 105600 | IG3: =-(IF$3+IF$30)/IF$30 -> 0.84363993 | II3: Venda de café | IJ3: =((IJ$4*60)/0.25)*IJ$5 -> 115200 | IK3: =-(IJ$3+IJ$30)/IJ$30 -> -0.33824972 | IM3: Venda de café | IN3: =((IN$4*60)/0.25)*IN$5 -> 115200 | IO3: =-(IN$3+IN$30)/IN$30 -> 0.87366441 | IQ3: Venda de café | IR3: =((IR$4*60)/0.25)*IR$5 -> 115200 | IS3: =-(IR$3+IR$30)/IR$30 -> 0.87366441 | IU3: Venda de café | IV3: =((IV$4*60)/0.25)*IV$5 -> 115200 | IW3: =-(IV$3+IV$30)/IV$30 -> -0.33824972 | IY3: Venda de café | IZ3: =((IZ$4*60)/0.25)*IZ$5 -> 115200 | JA3: =-(IZ$3+IZ$30)/IZ$30 -> 0.87366441 | JC3: Venda de café | JD3: =((JD$4*60)/0.25)*JD$5 -> 115200 | JE3: =-(JD$3+JD$30)/JD$30 -> 0.87366441 | JG3: Venda de café | JH3: =((JH$4*60)/0.25)*JH$5 -> 115200 | JI3: =-(JH$3+JH$30)/JH$30 -> -0.36100746 | JK3: Venda de café | JL3: =((JL$4*60)/0.25)*JL$5 -> 124800 | JM3: =-(JL$3+JL$30)/JL$30 -> 0.89984424 | JO3: Venda de café | JP3: =((JP$4*60)/0.25)*JP$5 -> 124800 | JQ3: =-(JP$3+JP$30)/JP$30 -> 0.89984424 | JS3: Venda de café | JT3: =((JT$4*60)/0.25)*JT$5 -> 124800 | JU3: =-(JT$3+JT$30)/JT$30 -> -0.3347179 | JW3: Venda de café | JX3: =((JX$4*60)/0.25)*JX$5 -> 124800 | JY3: =-(JX$3+JX$30)/JX$30 -> 0.89984424 | KA3: Venda de café | KB3: =((KB$4*60)/0.25)*KB$5 -> 124800 | KC3: =-(KB$3+KB$30)/KB$30 -> 0.89984424 | KE3: Venda de café | KF3: =((KF$4*60)/0.25)*KF$5 -> 124800 | KG3: =-(KF$3+KF$30)/KF$30 -> 0.16646856
A4: 0.15 | C4: Sacas vendidas | D4: 3 | G4: Sacas vendidas | H4: =INT(3 + (COLUMN()-COLUMN($D4))/4 * $A$4) -> 3 | K4: Sacas vendidas | L4: =INT(3 + (COLUMN()-COLUMN($D4))/4 * $A$4) -> 3 | O4: Sacas vendidas | P4: =INT(3 + (COLUMN()-COLUMN($D4))/4 * $A$4) -> 3 | S4: Sacas vendidas | T4: =INT(3 + (COLUMN()-COLUMN($D4))/4 * $A$4) -> 3 | W4: Sacas vendidas | X4: =INT(3 + (COLUMN()-COLUMN($D4))/4 * $A$4) -> 3 | AA4: Sacas vendidas | AB4: =INT(3 + (COLUMN()-COLUMN($D4))/4 * $A$4) -> 3 | AE4: Sacas vendidas | AF4: =INT(3 + (COLUMN()-COLUMN($D4))/4 * $A$4) -> 4 | AI4: Sacas vendidas | AJ4: =INT(3 + (COLUMN()-COLUMN($D4))/4 * $A$4) -> 4 | AM4: Sacas vendidas | AN4: =INT(3 + (COLUMN()-COLUMN($D4))/4 * $A$4) -> 4 | AQ4: Sacas vendidas | AR4: =INT(3 + (COLUMN()-COLUMN($D4))/4 * $A$4) -> 4 | AU4: Sacas vendidas | AV4: =INT(3 + (COLUMN()-COLUMN($D4))/4 * $A$4) -> 4 | AY4: Sacas vendidas | AZ4: =INT(3 + (COLUMN()-COLUMN($D4))/4 * $A$4) -> 4 | BC4: Sacas vendidas | BD4: =INT(3 + (COLUMN()-COLUMN($D4))/4 * $A$4) -> 4 | BG4: Sacas vendidas | BH4: =INT(3 + (COLUMN()-COLUMN($D4))/4 * $A$4) -> 5 | BK4: Sacas vendidas | BL4: =INT(3 + (COLUMN()-COLUMN($D4))/4 * $A$4) -> 5 | BO4: Sacas vendidas | BP4: =INT(3 + (COLUMN()-COLUMN($D4))/4 * $A$4) -> 5 | BS4: Sacas vendidas | BT4: =INT(3 + (COLUMN()-COLUMN($D4))/4 * $A$4) -> 5 | BW4: Sacas vendidas | BX4: =INT(3 + (COLUMN()-COLUMN($D4))/4 * $A$4) -> 5 | CA4: Sacas vendidas | CB4: =INT(3 + (COLUMN()-COLUMN($D4))/4 * $A$4) -> 5 | CE4: Sacas vendidas | CF4: =INT(3 + (COLUMN()-COLUMN($D4))/4 * $A$4) -> 6 | CI4: Sacas vendidas | CJ4: =INT(3 + (COLUMN()-COLUMN($D4))/4 * $A$4) -> 6 | CM4: Sacas vendidas | CN4: =INT(3 + (COLUMN()-COLUMN($D4))/4 * $A$4) -> 6 | CQ4: Sacas vendidas | CR4: =INT(3 + (COLUMN()-COLUMN($D4))/4 * $A$4) -> 6 | CU4: Sacas vendidas | CV4: =INT(3 + (COLUMN()-COLUMN($D4))/4 * $A$4) -> 6 | CY4: Sacas vendidas | CZ4: =INT(3 + (COLUMN()-COLUMN($D4))/4 * $A$4) -> 6 | DC4: Sacas vendidas | DD4: =INT(3 + (COLUMN()-COLUMN($D4))/4 * $A$4) -> 6 | DG4: Sacas vendidas | DH4: =INT(3 + (COLUMN()-COLUMN($D4))/4 * $A$4) -> 7 | DK4: Sacas vendidas | DL4: =INT(3 + (COLUMN()-COLUMN($D4))/4 * $A$4) -> 7 | DO4: Sacas vendidas | DP4: =INT(3 + (COLUMN()-COLUMN($D4))/4 * $A$4) -> 7 | DS4: Sacas vendidas | DT4: =INT(3 + (COLUMN()-COLUMN($D4))/4 * $A$4) -> 7 | DW4: Sacas vendidas | DX4: =INT(3 + (COLUMN()-COLUMN($D4))/4 * $A$4) -> 7 | EA4: Sacas vendidas | EB4: =INT(3 + (COLUMN()-COLUMN($D4))/4 * $A$4) -> 7 | EE4: Sacas vendidas | EF4: =INT(3 + (COLUMN()-COLUMN($D4))/4 * $A$4) -> 7 | EI4: Sacas vendidas | EJ4: =INT(3 + (COLUMN()-COLUMN($D4))/4 * $A$4) -> 8 | EM4: Sacas vendidas | EN4: =INT(3 + (COLUMN()-COLUMN($D4))/4 * $A$4) -> 8 | EQ4: Sacas vendidas | ER4: =INT(3 + (COLUMN()-COLUMN($D4))/4 * $A$4) -> 8 | EU4: Sacas vendidas | EV4: =INT(3 + (COLUMN()-COLUMN($D4))/4 * $A$4) -> 8 | EY4: Sacas vendidas | EZ4: =INT(3 + (COLUMN()-COLUMN($D4))/4 * $A$4) -> 8 | FC4: Sacas vendidas | FD4: =INT(3 + (COLUMN()-COLUMN($D4))/4 * $A$4) -> 8 | FG4: Sacas vendidas | FH4: =INT(3 + (COLUMN()-COLUMN($D4))/4 * $A$4) -> 9 | FK4: Sacas vendidas | FL4: =INT(3 + (COLUMN()-COLUMN($D4))/4 * $A$4) -> 9 | FO4: Sacas vendidas | FP4: =INT(3 + (COLUMN()-COLUMN($D4))/4 * $A$4) -> 9 | FS4: Sacas vendidas | FT4: =INT(3 + (COLUMN()-COLUMN($D4))/4 * $A$4) -> 9 | FW4: Sacas vendidas | FX4: =INT(3 + (COLUMN()-COLUMN($D4))/4 * $A$4) -> 9 | GA4: Sacas vendidas | GB4: =INT(3 + (COLUMN()-COLUMN($D4))/4 * $A$4) -> 9 | GE4: Sacas vendidas | GF4: =INT(3 + (COLUMN()-COLUMN($D4))/4 * $A$4) -> 9 | GI4: Sacas vendidas | GJ4: =INT(3 + (COLUMN()-COLUMN($D4))/4 * $A$4) -> 10 | GM4: Sacas vendidas | GN4: =INT(3 + (COLUMN()-COLUMN($D4))/4 * $A$4) -> 10 | GQ4: Sacas vendidas | GR4: =INT(3 + (COLUMN()-COLUMN($D4))/4 * $A$4) -> 10 | GU4: Sacas vendidas | GV4: =INT(3 + (COLUMN()-COLUMN($D4))/4 * $A$4) -> 10 | GY4: Sacas vendidas | GZ4: =INT(3 + (COLUMN()-COLUMN($D4))/4 * $A$4) -> 10 | HC4: Sacas vendidas | HD4: =INT(3 + (COLUMN()-COLUMN($D4))/4 * $A$4) -> 10 | HG4: Sacas vendidas | HH4: =INT(3 + (COLUMN()-COLUMN($D4))/4 * $A$4) -> 10 | HK4: Sacas vendidas | HL4: =INT(3 + (COLUMN()-COLUMN($D4))/4 * $A$4) -> 11 | HO4: Sacas vendidas | HP4: =INT(3 + (COLUMN()-COLUMN($D4))/4 * $A$4) -> 11 | HS4: Sacas vendidas | HT4: =INT(3 + (COLUMN()-COLUMN($D4))/4 * $A$4) -> 11 | HW4: Sacas vendidas | HX4: =INT(3 + (COLUMN()-COLUMN($D4))/4 * $A$4) -> 11 | IA4: Sacas vendidas | IB4: =INT(3 + (COLUMN()-COLUMN($D4))/4 * $A$4) -> 11 | IE4: Sacas vendidas | IF4: =INT(3 + (COLUMN()-COLUMN($D4))/4 * $A$4) -> 11 | II4: Sacas vendidas | IJ4: =INT(3 + (COLUMN()-COLUMN($D4))/4 * $A$4) -> 12 | IM4: Sacas vendidas | IN4: =INT(3 + (COLUMN()-COLUMN($D4))/4 * $A$4) -> 12 | IQ4: Sacas vendidas | IR4: =INT(3 + (COLUMN()-COLUMN($D4))/4 * $A$4) -> 12 | IU4: Sacas vendidas | IV4: =INT(3 + (COLUMN()-COLUMN($D4))/4 * $A$4) -> 12 | IY4: Sacas vendidas | IZ4: =INT(3 + (COLUMN()-COLUMN($D4))/4 * $A$4) -> 12 | JC4: Sacas vendidas | JD4: =INT(3 + (COLUMN()-COLUMN($D4))/4 * $A$4) -> 12 | JG4: Sacas vendidas | JH4: =INT(3 + (COLUMN()-COLUMN($D4))/4 * $A$4) -> 12 | JK4: Sacas vendidas | JL4: =INT(3 + (COLUMN()-COLUMN($D4))/4 * $A$4) -> 13 | JO4: Sacas vendidas | JP4: =INT(3 + (COLUMN()-COLUMN($D4))/4 * $A$4) -> 13 | JS4: Sacas vendidas | JT4: =INT(3 + (COLUMN()-COLUMN($D4))/4 * $A$4) -> 13 | JW4: Sacas vendidas | JX4: =INT(3 + (COLUMN()-COLUMN($D4))/4 * $A$4) -> 13 | KA4: Sacas vendidas | KB4: =INT(3 + (COLUMN()-COLUMN($D4))/4 * $A$4) -> 13 | KE4: Sacas vendidas | KF4: =INT(3 + (COLUMN()-COLUMN($D4))/4 * $A$4) -> 13
C5: Preço por pacotinho | D5: =$A$3 -> 40 | G5: Preço por pacotinho | H5: =$A$3 -> 40 | K5: Preço por pacotinho | L5: =$A$3 -> 40 | O5: Preço por pacotinho | P5: =$A$3 -> 40 | S5: Preço por pacotinho | T5: =$A$3 -> 40 | W5: Preço por pacotinho | X5: =$A$3 -> 40 | AA5: Preço por pacotinho | AB5: =$A$3 -> 40 | AE5: Preço por pacotinho | AF5: =$A$3 -> 40 | AI5: Preço por pacotinho | AJ5: =$A$3 -> 40 | AM5: Preço por pacotinho | AN5: =$A$3 -> 40 | AQ5: Preço por pacotinho | AR5: =$A$3 -> 40 | AU5: Preço por pacotinho | AV5: =$A$3 -> 40 | AY5: Preço por pacotinho | AZ5: =$A$3 -> 40 | BC5: Preço por pacotinho | BD5: =$A$3 -> 40 | BG5: Preço por pacotinho | BH5: =$A$3 -> 40 | BK5: Preço por pacotinho | BL5: =$A$3 -> 40 | BO5: Preço por pacotinho | BP5: =$A$3 -> 40 | BS5: Preço por pacotinho | BT5: =$A$3 -> 40 | BW5: Preço por pacotinho | BX5: =$A$3 -> 40 | CA5: Preço por pacotinho | CB5: =$A$3 -> 40 | CE5: Preço por pacotinho | CF5: =$A$3 -> 40 | CI5: Preço por pacotinho | CJ5: =$A$3 -> 40 | CM5: Preço por pacotinho | CN5: =$A$3 -> 40 | CQ5: Preço por pacotinho | CR5: =$A$3 -> 40 | CU5: Preço por pacotinho | CV5: =$A$3 -> 40 | CY5: Preço por pacotinho | CZ5: =$A$3 -> 40 | DC5: Preço por pacotinho | DD5: =$A$3 -> 40 | DG5: Preço por pacotinho | DH5: =$A$3 -> 40 | DK5: Preço por pacotinho | DL5: =$A$3 -> 40 | DO5: Preço por pacotinho | DP5: =$A$3 -> 40 | DS5: Preço por pacotinho | DT5: =$A$3 -> 40 | DW5: Preço por pacotinho | DX5: =$A$3 -> 40 | EA5: Preço por pacotinho | EB5: =$A$3 -> 40 | EE5: Preço por pacotinho | EF5: =$A$3 -> 40 | EI5: Preço por pacotinho | EJ5: =$A$3 -> 40 | EM5: Preço por pacotinho | EN5: =$A$3 -> 40 | EQ5: Preço por pacotinho | ER5: =$A$3 -> 40 | EU5: Preço por pacotinho | EV5: =$A$3 -> 40 | EY5: Preço por pacotinho | EZ5: =$A$3 -> 40 | FC5: Preço por pacotinho | FD5: =$A$3 -> 40 | FG5: Preço por pacotinho | FH5: =$A$3 -> 40 | FK5: Preço por pacotinho | FL5: =$A$3 -> 40 | FO5: Preço por pacotinho | FP5: =$A$3 -> 40 | FS5: Preço por pacotinho | FT5: =$A$3 -> 40 | FW5: Preço por pacotinho | FX5: =$A$3 -> 40 | GA5: Preço por pacotinho | GB5: =$A$3 -> 40 | GE5: Preço por pacotinho | GF5: =$A$3 -> 40 | GI5: Preço por pacotinho | GJ5: =$A$3 -> 40 | GM5: Preço por pacotinho | GN5: =$A$3 -> 40 | GQ5: Preço por pacotinho | GR5: =$A$3 -> 40 | GU5: Preço por pacotinho | GV5: =$A$3 -> 40 | GY5: Preço por pacotinho | GZ5: =$A$3 -> 40 | HC5: Preço por pacotinho | HD5: =$A$3 -> 40 | HG5: Preço por pacotinho | HH5: =$A$3 -> 40 | HK5: Preço por pacotinho | HL5: =$A$3 -> 40 | HO5: Preço por pacotinho | HP5: =$A$3 -> 40 | HS5: Preço por pacotinho | HT5: =$A$3 -> 40 | HW5: Preço por pacotinho | HX5: =$A$3 -> 40 | IA5: Preço por pacotinho | IB5: =$A$3 -> 40 | IE5: Preço por pacotinho | IF5: =$A$3 -> 40 | II5: Preço por pacotinho | IJ5: =$A$3 -> 40 | IM5: Preço por pacotinho | IN5: =$A$3 -> 40 | IQ5: Preço por pacotinho | IR5: =$A$3 -> 40 | IU5: Preço por pacotinho | IV5: =$A$3 -> 40 | IY5: Preço por pacotinho | IZ5: =$A$3 -> 40 | JC5: Preço por pacotinho | JD5: =$A$3 -> 40 | JG5: Preço por pacotinho | JH5: =$A$3 -> 40 | JK5: Preço por pacotinho | JL5: =$A$3 -> 40 | JO5: Preço por pacotinho | JP5: =$A$3 -> 40 | JS5: Preço por pacotinho | JT5: =$A$3 -> 40 | JW5: Preço por pacotinho | JX5: =$A$3 -> 40 | KA5: Preço por pacotinho | KB5: =$A$3 -> 40 | KE5: Preço por pacotinho | KF5: =$A$3 -> 40
C7: Total receitas | D7: =SUM(D$3) -> 28800 | G7: Total receitas | H7: =SUM(H$3) -> 28800 | K7: Total receitas | L7: =SUM(L$3) -> 28800 | O7: Total receitas | P7: =SUM(P$3) -> 28800 | S7: Total receitas | T7: =SUM(T$3) -> 28800 | W7: Total receitas | X7: =SUM(X$3) -> 28800 | AA7: Total receitas | AB7: =SUM(AB$3) -> 28800 | AE7: Total receitas | AF7: =SUM(AF$3) -> 38400 | AI7: Total receitas | AJ7: =SUM(AJ$3) -> 38400 | AM7: Total receitas | AN7: =SUM(AN$3) -> 38400 | AQ7: Total receitas | AR7: =SUM(AR$3) -> 38400 | AU7: Total receitas | AV7: =SUM(AV$3) -> 38400 | AY7: Total receitas | AZ7: =SUM(AZ$3) -> 38400 | BC7: Total receitas | BD7: =SUM(BD$3) -> 38400 | BG7: Total receitas | BH7: =SUM(BH$3) -> 48000 | BK7: Total receitas | BL7: =SUM(BL$3) -> 48000 | BO7: Total receitas | BP7: =SUM(BP$3) -> 48000 | BS7: Total receitas | BT7: =SUM(BT$3) -> 48000 | BW7: Total receitas | BX7: =SUM(BX$3) -> 48000 | CA7: Total receitas | CB7: =SUM(CB$3) -> 48000 | CE7: Total receitas | CF7: =SUM(CF$3) -> 57600 | CI7: Total receitas | CJ7: =SUM(CJ$3) -> 57600 | CM7: Total receitas | CN7: =SUM(CN$3) -> 57600 | CQ7: Total receitas | CR7: =SUM(CR$3) -> 57600 | CU7: Total receitas | CV7: =SUM(CV$3) -> 57600 | CY7: Total receitas | CZ7: =SUM(CZ$3) -> 57600 | DC7: Total receitas | DD7: =SUM(DD$3) -> 57600 | DG7: Total receitas | DH7: =SUM(DH$3) -> 67200 | DK7: Total receitas | DL7: =SUM(DL$3) -> 67200 | DO7: Total receitas | DP7: =SUM(DP$3) -> 67200 | DS7: Total receitas | DT7: =SUM(DT$3) -> 67200 | DW7: Total receitas | DX7: =SUM(DX$3) -> 67200 | EA7: Total receitas | EB7: =SUM(EB$3) -> 67200 | EE7: Total receitas | EF7: =SUM(EF$3) -> 67200 | EI7: Total receitas | EJ7: =SUM(EJ$3) -> 76800 | EM7: Total receitas | EN7: =SUM(EN$3) -> 76800 | EQ7: Total receitas | ER7: =SUM(ER$3) -> 76800 | EU7: Total receitas | EV7: =SUM(EV$3) -> 76800 | EY7: Total receitas | EZ7: =SUM(EZ$3) -> 76800 | FC7: Total receitas | FD7: =SUM(FD$3) -> 76800 | FG7: Total receitas | FH7: =SUM(FH$3) -> 86400 | FK7: Total receitas | FL7: =SUM(FL$3) -> 86400 | FO7: Total receitas | FP7: =SUM(FP$3) -> 86400 | FS7: Total receitas | FT7: =SUM(FT$3) -> 86400 | FW7: Total receitas | FX7: =SUM(FX$3) -> 86400 | GA7: Total receitas | GB7: =SUM(GB$3) -> 86400 | GE7: Total receitas | GF7: =SUM(GF$3) -> 86400 | GI7: Total receitas | GJ7: =SUM(GJ$3) -> 96000 | GM7: Total receitas | GN7: =SUM(GN$3) -> 96000 | GQ7: Total receitas | GR7: =SUM(GR$3) -> 96000 | GU7: Total receitas | GV7: =SUM(GV$3) -> 96000 | GY7: Total receitas | GZ7: =SUM(GZ$3) -> 96000 | HC7: Total receitas | HD7: =SUM(HD$3) -> 96000 | HG7: Total receitas | HH7: =SUM(HH$3) -> 96000 | HK7: Total receitas | HL7: =SUM(HL$3) -> 105600 | HO7: Total receitas | HP7: =SUM(HP$3) -> 105600 | HS7: Total receitas | HT7: =SUM(HT$3) -> 105600 | HW7: Total receitas | HX7: =SUM(HX$3) -> 105600 | IA7: Total receitas | IB7: =SUM(IB$3) -> 105600 | IE7: Total receitas | IF7: =SUM(IF$3) -> 105600 | II7: Total receitas | IJ7: =SUM(IJ$3) -> 115200 | IM7: Total receitas | IN7: =SUM(IN$3) -> 115200 | IQ7: Total receitas | IR7: =SUM(IR$3) -> 115200 | IU7: Total receitas | IV7: =SUM(IV$3) -> 115200 | IY7: Total receitas | IZ7: =SUM(IZ$3) -> 115200 | JC7: Total receitas | JD7: =SUM(JD$3) -> 115200 | JG7: Total receitas | JH7: =SUM(JH$3) -> 115200 | JK7: Total receitas | JL7: =SUM(JL$3) -> 124800 | JO7: Total receitas | JP7: =SUM(JP$3) -> 124800 | JS7: Total receitas | JT7: =SUM(JT$3) -> 124800 | JW7: Total receitas | JX7: =SUM(JX$3) -> 124800 | KA7: Total receitas | KB7: =SUM(KB$3) -> 124800 | KE7: Total receitas | KF7: =SUM(KF$3) -> 124800
C9: Despesas | D9: R$ | G9: Despesas | H9: R$ | K9: Despesas | L9: R$ | O9: Despesas | P9: R$ | S9: Despesas | T9: R$ | W9: Despesas | X9: R$ | AA9: Despesas | AB9: R$ | AE9: Despesas | AF9: R$ | AI9: Despesas | AJ9: R$ | AM9: Despesas | AN9: R$ | AQ9: Despesas | AR9: R$ | AU9: Despesas | AV9: R$ | AY9: Despesas | AZ9: R$ | BC9: Despesas | BD9: R$ | BG9: Despesas | BH9: R$ | BK9: Despesas | BL9: R$ | BO9: Despesas | BP9: R$ | BS9: Despesas | BT9: R$ | BW9: Despesas | BX9: R$ | CA9: Despesas | CB9: R$ | CE9: Despesas | CF9: R$ | CI9: Despesas | CJ9: R$ | CM9: Despesas | CN9: R$ | CQ9: Despesas | CR9: R$ | CU9: Despesas | CV9: R$ | CY9: Despesas | CZ9: R$ | DC9: Despesas | DD9: R$ | DG9: Despesas | DH9: R$ | DK9: Despesas | DL9: R$ | DO9: Despesas | DP9: R$ | DS9: Despesas | DT9: R$ | DW9: Despesas | DX9: R$ | EA9: Despesas | EB9: R$ | EE9: Despesas | EF9: R$ | EI9: Despesas | EJ9: R$ | EM9: Despesas | EN9: R$ | EQ9: Despesas | ER9: R$ | EU9: Despesas | EV9: R$ | EY9: Despesas | EZ9: R$ | FC9: Despesas | FD9: R$ | FG9: Despesas | FH9: R$ | FK9: Despesas | FL9: R$ | FO9: Despesas | FP9: R$ | FS9: Despesas | FT9: R$ | FW9: Despesas | FX9: R$ | GA9: Despesas | GB9: R$ | GE9: Despesas | GF9: R$ | GI9: Despesas | GJ9: R$ | GM9: Despesas | GN9: R$ | GQ9: Despesas | GR9: R$ | GU9: Despesas | GV9: R$ | GY9: Despesas | GZ9: R$ | HC9: Despesas | HD9: R$ | HG9: Despesas | HH9: R$ | HK9: Despesas | HL9: R$ | HO9: Despesas | HP9: R$ | HS9: Despesas | HT9: R$ | HW9: Despesas | HX9: R$ | IA9: Despesas | IB9: R$ | IE9: Despesas | IF9: R$ | II9: Despesas | IJ9: R$ | IM9: Despesas | IN9: R$ | IQ9: Despesas | IR9: R$ | IU9: Despesas | IV9: R$ | IY9: Despesas | IZ9: R$ | JC9: Despesas | JD9: R$ | JG9: Despesas | JH9: R$ | JK9: Despesas | JL9: R$ | JO9: Despesas | JP9: R$ | JS9: Despesas | JT9: R$ | JW9: Despesas | JX9: R$ | KA9: Despesas | KB9: R$ | KE9: Despesas | KF9: R$
A10: Despesas iniciais | C10: Máquina de torra seminova | D10: =-'Investimento Inicial'!$B$2 -> -70000
A11: Despesas fixas | C11: Balança de comércio | D11: =-'Investimento Inicial'!$B$3 -> -500
A12: Despesas variáveis | C12: =IF(D12<>"", $A$14&" meses de café", "") -> 3 meses de café | D12: =IF(AND(NOT(ISBLANK(C$1)), MOD(C$1,$A$14)=0), -$A$2*SUM(OFFSET(C4,0,0,1,$A$14*4)), "") -> -27900 | E12: =IF(F12<>"", $A$14&" meses de café", "") | F12: =IF(AND(NOT(ISBLANK(E$1)), MOD(E$1,$A$14)=0), -$A$2*SUM(OFFSET(E4,0,0,1,$A$14*4)), "") | G12: =IF(H12<>"", $A$14&" meses de café", "") | H12: =IF(AND(NOT(ISBLANK(G$1)), MOD(G$1,$A$14)=0), -$A$2*SUM(OFFSET(G4,0,0,1,$A$14*4)), "") | I12: =IF(J12<>"", $A$14&" meses de café", "") | J12: =IF(AND(NOT(ISBLANK(I$1)), MOD(I$1,$A$14)=0), -$A$2*SUM(OFFSET(I4,0,0,1,$A$14*4)), "") | K12: =IF(L12<>"", $A$14&" meses de café", "") | L12: =IF(AND(NOT(ISBLANK(K$1)), MOD(K$1,$A$14)=0), -$A$2*SUM(OFFSET(K4,0,0,1,$A$14*4)), "") | M12: =IF(N12<>"", $A$14&" meses de café", "") | N12: =IF(AND(NOT(ISBLANK(M$1)), MOD(M$1,$A$14)=0), -$A$2*SUM(OFFSET(M4,0,0,1,$A$14*4)), "") | O12: =IF(P12<>"", $A$14&" meses de café", "") -> 3 meses de café | P12: =IF(AND(NOT(ISBLANK(O$1)), MOD(O$1,$A$14)=0), -$A$2*SUM(OFFSET(O4,0,0,1,$A$14*4)), "") -> -27900 | Q12: =IF(R12<>"", $A$14&" meses de café", "") | R12: =IF(AND(NOT(ISBLANK(Q$1)), MOD(Q$1,$A$14)=0), -$A$2*SUM(OFFSET(Q4,0,0,1,$A$14*4)), "") | S12: =IF(T12<>"", $A$14&" meses de café", "") | T12: =IF(AND(NOT(ISBLANK(S$1)), MOD(S$1,$A$14)=0), -$A$2*SUM(OFFSET(S4,0,0,1,$A$14*4)), "") | U12: =IF(V12<>"", $A$14&" meses de café", "") | V12: =IF(AND(NOT(ISBLANK(U$1)), MOD(U$1,$A$14)=0), -$A$2*SUM(OFFSET(U4,0,0,1,$A$14*4)), "") | W12: =IF(X12<>"", $A$14&" meses de café", "") | X12: =IF(AND(NOT(ISBLANK(W$1)), MOD(W$1,$A$14)=0), -$A$2*SUM(OFFSET(W4,0,0,1,$A$14*4)), "") | Y12: =IF(Z12<>"", $A$14&" meses de café", "") | Z12: =IF(AND(NOT(ISBLANK(Y$1)), MOD(Y$1,$A$14)=0), -$A$2*SUM(OFFSET(Y4,0,0,1,$A$14*4)), "") | AA12: =IF(AB12<>"", $A$14&" meses de café", "") -> 3 meses de café | AB12: =IF(AND(NOT(ISBLANK(AA$1)), MOD(AA$1,$A$14)=0), -$A$2*SUM(OFFSET(AA4,0,0,1,$A$14*4)), "") -> -34100 | AC12: =IF(AD12<>"", $A$14&" meses de café", "") | AD12: =IF(AND(NOT(ISBLANK(AC$1)), MOD(AC$1,$A$14)=0), -$A$2*SUM(OFFSET(AC4,0,0,1,$A$14*4)), "") | AE12: =IF(AF12<>"", $A$14&" meses de café", "") | AF12: =IF(AND(NOT(ISBLANK(AE$1)), MOD(AE$1,$A$14)=0), -$A$2*SUM(OFFSET(AE4,0,0,1,$A$14*4)), "") | AG12: =IF(AH12<>"", $A$14&" meses de café", "") | AH12: =IF(AND(NOT(ISBLANK(AG$1)), MOD(AG$1,$A$14)=0), -$A$2*SUM(OFFSET(AG4,0,0,1,$A$14*4)), "") | AI12: =IF(AJ12<>"", $A$14&" meses de café", "") | AJ12: =IF(AND(NOT(ISBLANK(AI$1)), MOD(AI$1,$A$14)=0), -$A$2*SUM(OFFSET(AI4,0,0,1,$A$14*4)), "") | AK12: =IF(AL12<>"", $A$14&" meses de café", "") | AL12: =IF(AND(NOT(ISBLANK(AK$1)), MOD(AK$1,$A$14)=0), -$A$2*SUM(OFFSET(AK4,0,0,1,$A$14*4)), "") | AM12: =IF(AN12<>"", $A$14&" meses de café", "") -> 3 meses de café | AN12: =IF(AND(NOT(ISBLANK(AM$1)), MOD(AM$1,$A$14)=0), -$A$2*SUM(OFFSET(AM4,0,0,1,$A$14*4)), "") -> -37200 | AO12: =IF(AP12<>"", $A$14&" meses de café", "") | AP12: =IF(AND(NOT(ISBLANK(AO$1)), MOD(AO$1,$A$14)=0), -$A$2*SUM(OFFSET(AO4,0,0,1,$A$14*4)), "") | AQ12: =IF(AR12<>"", $A$14&" meses de café", "") | AR12: =IF(AND(NOT(ISBLANK(AQ$1)), MOD(AQ$1,$A$14)=0), -$A$2*SUM(OFFSET(AQ4,0,0,1,$A$14*4)), "") | AS12: =IF(AT12<>"", $A$14&" meses de café", "") | AT12: =IF(AND(NOT(ISBLANK(AS$1)), MOD(AS$1,$A$14)=0), -$A$2*SUM(OFFSET(AS4,0,0,1,$A$14*4)), "") | AU12: =IF(AV12<>"", $A$14&" meses de café", "") | AV12: =IF(AND(NOT(ISBLANK(AU$1)), MOD(AU$1,$A$14)=0), -$A$2*SUM(OFFSET(AU4,0,0,1,$A$14*4)), "") | AW12: =IF(AX12<>"", $A$14&" meses de café", "") | AX12: =IF(AND(NOT(ISBLANK(AW$1)), MOD(AW$1,$A$14)=0), -$A$2*SUM(OFFSET(AW4,0,0,1,$A$14*4)), "") | AY12: =IF(AZ12<>"", $A$14&" meses de café", "") -> 3 meses de café | AZ12: =IF(AND(NOT(ISBLANK(AY$1)), MOD(AY$1,$A$14)=0), -$A$2*SUM(OFFSET(AY4,0,0,1,$A$14*4)), "") -> -40300 | BA12: =IF(BB12<>"", $A$14&" meses de café", "") | BB12: =IF(AND(NOT(ISBLANK(BA$1)), MOD(BA$1,$A$14)=0), -$A$2*SUM(OFFSET(BA4,0,0,1,$A$14*4)), "") | BC12: =IF(BD12<>"", $A$14&" meses de café", "") | BD12: =IF(AND(NOT(ISBLANK(BC$1)), MOD(BC$1,$A$14)=0), -$A$2*SUM(OFFSET(BC4,0,0,1,$A$14*4)), "") | BE12: =IF(BF12<>"", $A$14&" meses de café", "") | BF12: =IF(AND(NOT(ISBLANK(BE$1)), MOD(BE$1,$A$14)=0), -$A$2*SUM(OFFSET(BE4,0,0,1,$A$14*4)), "") | BG12: =IF(BH12<>"", $A$14&" meses de café", "") | BH12: =IF(AND(NOT(ISBLANK(BG$1)), MOD(BG$1,$A$14)=0), -$A$2*SUM(OFFSET(BG4,0,0,1,$A$14*4)), "") | BI12: =IF(BJ12<>"", $A$14&" meses de café", "") | BJ12: =IF(AND(NOT(ISBLANK(BI$1)), MOD(BI$1,$A$14)=0), -$A$2*SUM(OFFSET(BI4,0,0,1,$A$14*4)), "") | BK12: =IF(BL12<>"", $A$14&" meses de café", "") -> 3 meses de café | BL12: =IF(AND(NOT(ISBLANK(BK$1)), MOD(BK$1,$A$14)=0), -$A$2*SUM(OFFSET(BK4,0,0,1,$A$14*4)), "") -> -46500 | BM12: =IF(BN12<>"", $A$14&" meses de café", "") | BN12: =IF(AND(NOT(ISBLANK(BM$1)), MOD(BM$1,$A$14)=0), -$A$2*SUM(OFFSET(BM4,0,0,1,$A$14*4)), "") | BO12: =IF(BP12<>"", $A$14&" meses de café", "") | BP12: =IF(AND(NOT(ISBLANK(BO$1)), MOD(BO$1,$A$14)=0), -$A$2*SUM(OFFSET(BO4,0,0,1,$A$14*4)), "") | BQ12: =IF(BR12<>"", $A$14&" meses de café", "") | BR12: =IF(AND(NOT(ISBLANK(BQ$1)), MOD(BQ$1,$A$14)=0), -$A$2*SUM(OFFSET(BQ4,0,0,1,$A$14*4)), "") | BS12: =IF(BT12<>"", $A$14&" meses de café", "") | BT12: =IF(AND(NOT(ISBLANK(BS$1)), MOD(BS$1,$A$14)=0), -$A$2*SUM(OFFSET(BS4,0,0,1,$A$14*4)), "") | BU12: =IF(BV12<>"", $A$14&" meses de café", "") | BV12: =IF(AND(NOT(ISBLANK(BU$1)), MOD(BU$1,$A$14)=0), -$A$2*SUM(OFFSET(BU4,0,0,1,$A$14*4)), "") | BW12: =IF(BX12<>"", $A$14&" meses de café", "") -> 3 meses de café | BX12: =IF(AND(NOT(ISBLANK(BW$1)), MOD(BW$1,$A$14)=0), -$A$2*SUM(OFFSET(BW4,0,0,1,$A$14*4)), "") -> -49600 | BY12: =IF(BZ12<>"", $A$14&" meses de café", "") | BZ12: =IF(AND(NOT(ISBLANK(BY$1)), MOD(BY$1,$A$14)=0), -$A$2*SUM(OFFSET(BY4,0,0,1,$A$14*4)), "") | CA12: =IF(CB12<>"", $A$14&" meses de café", "") | CB12: =IF(AND(NOT(ISBLANK(CA$1)), MOD(CA$1,$A$14)=0), -$A$2*SUM(OFFSET(CA4,0,0,1,$A$14*4)), "") | CC12: =IF(CD12<>"", $A$14&" meses de café", "") | CD12: =IF(AND(NOT(ISBLANK(CC$1)), MOD(CC$1,$A$14)=0), -$A$2*SUM(OFFSET(CC4,0,0,1,$A$14*4)), "") | CE12: =IF(CF12<>"", $A$14&" meses de café", "") | CF12: =IF(AND(NOT(ISBLANK(CE$1)), MOD(CE$1,$A$14)=0), -$A$2*SUM(OFFSET(CE4,0,0,1,$A$14*4)), "") | CG12: =IF(CH12<>"", $A$14&" meses de café", "") | CH12: =IF(AND(NOT(ISBLANK(CG$1)), MOD(CG$1,$A$14)=0), -$A$2*SUM(OFFSET(CG4,0,0,1,$A$14*4)), "") | CI12: =IF(CJ12<>"", $A$14&" meses de café", "") -> 3 meses de café | CJ12: =IF(AND(NOT(ISBLANK(CI$1)), MOD(CI$1,$A$14)=0), -$A$2*SUM(OFFSET(CI4,0,0,1,$A$14*4)), "") -> -55800 | CK12: =IF(CL12<>"", $A$14&" meses de café", "") | CL12: =IF(AND(NOT(ISBLANK(CK$1)), MOD(CK$1,$A$14)=0), -$A$2*SUM(OFFSET(CK4,0,0,1,$A$14*4)), "") | CM12: =IF(CN12<>"", $A$14&" meses de café", "") | CN12: =IF(AND(NOT(ISBLANK(CM$1)), MOD(CM$1,$A$14)=0), -$A$2*SUM(OFFSET(CM4,0,0,1,$A$14*4)), "") | CO12: =IF(CP12<>"", $A$14&" meses de café", "") | CP12: =IF(AND(NOT(ISBLANK(CO$1)), MOD(CO$1,$A$14)=0), -$A$2*SUM(OFFSET(CO4,0,0,1,$A$14*4)), "") | CQ12: =IF(CR12<>"", $A$14&" meses de café", "") | CR12: =IF(AND(NOT(ISBLANK(CQ$1)), MOD(CQ$1,$A$14)=0), -$A$2*SUM(OFFSET(CQ4,0,0,1,$A$14*4)), "") | CS12: =IF(CT12<>"", $A$14&" meses de café", "") | CT12: =IF(AND(NOT(ISBLANK(CS$1)), MOD(CS$1,$A$14)=0), -$A$2*SUM(OFFSET(CS4,0,0,1,$A$14*4)), "") | CU12: =IF(CV12<>"", $A$14&" meses de café", "") -> 3 meses de café | CV12: =IF(AND(NOT(ISBLANK(CU$1)), MOD(CU$1,$A$14)=0), -$A$2*SUM(OFFSET(CU4,0,0,1,$A$14*4)), "") -> -55800 | CW12: =IF(CX12<>"", $A$14&" meses de café", "") | CX12: =IF(AND(NOT(ISBLANK(CW$1)), MOD(CW$1,$A$14)=0), -$A$2*SUM(OFFSET(CW4,0,0,1,$A$14*4)), "") | CY12: =IF(CZ12<>"", $A$14&" meses de café", "") | CZ12: =IF(AND(NOT(ISBLANK(CY$1)), MOD(CY$1,$A$14)=0), -$A$2*SUM(OFFSET(CY4,0,0,1,$A$14*4)), "") | DA12: =IF(DB12<>"", $A$14&" meses de café", "") | DB12: =IF(AND(NOT(ISBLANK(DA$1)), MOD(DA$1,$A$14)=0), -$A$2*SUM(OFFSET(DA4,0,0,1,$A$14*4)), "") | DC12: =IF(DD12<>"", $A$14&" meses de café", "") | DD12: =IF(AND(NOT(ISBLANK(DC$1)), MOD(DC$1,$A$14)=0), -$A$2*SUM(OFFSET(DC4,0,0,1,$A$14*4)), "") | DE12: =IF(DF12<>"", $A$14&" meses de café", "") | DF12: =IF(AND(NOT(ISBLANK(DE$1)), MOD(DE$1,$A$14)=0), -$A$2*SUM(OFFSET(DE4,0,0,1,$A$14*4)), "") | DG12: =IF(DH12<>"", $A$14&" meses de café", "") -> 3 meses de café | DH12: =IF(AND(NOT(ISBLANK(DG$1)), MOD(DG$1,$A$14)=0), -$A$2*SUM(OFFSET(DG4,0,0,1,$A$14*4)), "") -> -65100 | DI12: =IF(DJ12<>"", $A$14&" meses de café", "") | DJ12: =IF(AND(NOT(ISBLANK(DI$1)), MOD(DI$1,$A$14)=0), -$A$2*SUM(OFFSET(DI4,0,0,1,$A$14*4)), "") | DK12: =IF(DL12<>"", $A$14&" meses de café", "") | DL12: =IF(AND(NOT(ISBLANK(DK$1)), MOD(DK$1,$A$14)=0), -$A$2*SUM(OFFSET(DK4,0,0,1,$A$14*4)), "") | DM12: =IF(DN12<>"", $A$14&" meses de café", "") | DN12: =IF(AND(NOT(ISBLANK(DM$1)), MOD(DM$1,$A$14)=0), -$A$2*SUM(OFFSET(DM4,0,0,1,$A$14*4)), "") | DO12: =IF(DP12<>"", $A$14&" meses de café", "") | DP12: =IF(AND(NOT(ISBLANK(DO$1)), MOD(DO$1,$A$14)=0), -$A$2*SUM(OFFSET(DO4,0,0,1,$A$14*4)), "") | DQ12: =IF(DR12<>"", $A$14&" meses de café", "") | DR12: =IF(AND(NOT(ISBLANK(DQ$1)), MOD(DQ$1,$A$14)=0), -$A$2*SUM(OFFSET(DQ4,0,0,1,$A$14*4)), "") | DS12: =IF(DT12<>"", $A$14&" meses de café", "") -> 3 meses de café | DT12: =IF(AND(NOT(ISBLANK(DS$1)), MOD(DS$1,$A$14)=0), -$A$2*SUM(OFFSET(DS4,0,0,1,$A$14*4)), "") -> -65100 | DU12: =IF(DV12<>"", $A$14&" meses de café", "") | DV12: =IF(AND(NOT(ISBLANK(DU$1)), MOD(DU$1,$A$14)=0), -$A$2*SUM(OFFSET(DU4,0,0,1,$A$14*4)), "") | DW12: =IF(DX12<>"", $A$14&" meses de café", "") | DX12: =IF(AND(NOT(ISBLANK(DW$1)), MOD(DW$1,$A$14)=0), -$A$2*SUM(OFFSET(DW4,0,0,1,$A$14*4)), "") | DY12: =IF(DZ12<>"", $A$14&" meses de café", "") | DZ12: =IF(AND(NOT(ISBLANK(DY$1)), MOD(DY$1,$A$14)=0), -$A$2*SUM(OFFSET(DY4,0,0,1,$A$14*4)), "") | EA12: =IF(EB12<>"", $A$14&" meses de café", "") | EB12: =IF(AND(NOT(ISBLANK(EA$1)), MOD(EA$1,$A$14)=0), -$A$2*SUM(OFFSET(EA4,0,0,1,$A$14*4)), "") | EC12: =IF(ED12<>"", $A$14&" meses de café", "") | ED12: =IF(AND(NOT(ISBLANK(EC$1)), MOD(EC$1,$A$14)=0), -$A$2*SUM(OFFSET(EC4,0,0,1,$A$14*4)), "") | EE12: =IF(EF12<>"", $A$14&" meses de café", "") -> 3 meses de café | EF12: =IF(AND(NOT(ISBLANK(EE$1)), MOD(EE$1,$A$14)=0), -$A$2*SUM(OFFSET(EE4,0,0,1,$A$14*4)), "") -> -71300 | EG12: =IF(EH12<>"", $A$14&" meses de café", "") | EH12: =IF(AND(NOT(ISBLANK(EG$1)), MOD(EG$1,$A$14)=0), -$A$2*SUM(OFFSET(EG4,0,0,1,$A$14*4)), "") | EI12: =IF(EJ12<>"", $A$14&" meses de café", "") | EJ12: =IF(AND(NOT(ISBLANK(EI$1)), MOD(EI$1,$A$14)=0), -$A$2*SUM(OFFSET(EI4,0,0,1,$A$14*4)), "") | EK12: =IF(EL12<>"", $A$14&" meses de café", "") | EL12: =IF(AND(NOT(ISBLANK(EK$1)), MOD(EK$1,$A$14)=0), -$A$2*SUM(OFFSET(EK4,0,0,1,$A$14*4)), "") | EM12: =IF(EN12<>"", $A$14&" meses de café", "") | EN12: =IF(AND(NOT(ISBLANK(EM$1)), MOD(EM$1,$A$14)=0), -$A$2*SUM(OFFSET(EM4,0,0,1,$A$14*4)), "") | EO12: =IF(EP12<>"", $A$14&" meses de café", "") | EP12: =IF(AND(NOT(ISBLANK(EO$1)), MOD(EO$1,$A$14)=0), -$A$2*SUM(OFFSET(EO4,0,0,1,$A$14*4)), "") | EQ12: =IF(ER12<>"", $A$14&" meses de café", "") -> 3 meses de café | ER12: =IF(AND(NOT(ISBLANK(EQ$1)), MOD(EQ$1,$A$14)=0), -$A$2*SUM(OFFSET(EQ4,0,0,1,$A$14*4)), "") -> -74400 | ES12: =IF(ET12<>"", $A$14&" meses de café", "") | ET12: =IF(AND(NOT(ISBLANK(ES$1)), MOD(ES$1,$A$14)=0), -$A$2*SUM(OFFSET(ES4,0,0,1,$A$14*4)), "") | EU12: =IF(EV12<>"", $A$14&" meses de café", "") | EV12: =IF(AND(NOT(ISBLANK(EU$1)), MOD(EU$1,$A$14)=0), -$A$2*SUM(OFFSET(EU4,0,0,1,$A$14*4)), "") | EW12: =IF(EX12<>"", $A$14&" meses de café", "") | EX12: =IF(AND(NOT(ISBLANK(EW$1)), MOD(EW$1,$A$14)=0), -$A$2*SUM(OFFSET(EW4,0,0,1,$A$14*4)), "") | EY12: =IF(EZ12<>"", $A$14&" meses de café", "") | EZ12: =IF(AND(NOT(ISBLANK(EY$1)), MOD(EY$1,$A$14)=0), -$A$2*SUM(OFFSET(EY4,0,0,1,$A$14*4)), "") | FA12: =IF(FB12<>"", $A$14&" meses de café", "") | FB12: =IF(AND(NOT(ISBLANK(FA$1)), MOD(FA$1,$A$14)=0), -$A$2*SUM(OFFSET(FA4,0,0,1,$A$14*4)), "") | FC12: =IF(FD12<>"", $A$14&" meses de café", "") -> 3 meses de café | FD12: =IF(AND(NOT(ISBLANK(FC$1)), MOD(FC$1,$A$14)=0), -$A$2*SUM(OFFSET(FC4,0,0,1,$A$14*4)), "") -> -80600 | FE12: =IF(FF12<>"", $A$14&" meses de café", "") | FF12: =IF(AND(NOT(ISBLANK(FE$1)), MOD(FE$1,$A$14)=0), -$A$2*SUM(OFFSET(FE4,0,0,1,$A$14*4)), "") | FG12: =IF(FH12<>"", $A$14&" meses de café", "") | FH12: =IF(AND(NOT(ISBLANK(FG$1)), MOD(FG$1,$A$14)=0), -$A$2*SUM(OFFSET(FG4,0,0,1,$A$14*4)), "") | FI12: =IF(FJ12<>"", $A$14&" meses de café", "") | FJ12: =IF(AND(NOT(ISBLANK(FI$1)), MOD(FI$1,$A$14)=0), -$A$2*SUM(OFFSET(FI4,0,0,1,$A$14*4)), "") | FK12: =IF(FL12<>"", $A$14&" meses de café", "") | FL12: =IF(AND(NOT(ISBLANK(FK$1)), MOD(FK$1,$A$14)=0), -$A$2*SUM(OFFSET(FK4,0,0,1,$A$14*4)), "") | FM12: =IF(FN12<>"", $A$14&" meses de café", "") | FN12: =IF(AND(NOT(ISBLANK(FM$1)), MOD(FM$1,$A$14)=0), -$A$2*SUM(OFFSET(FM4,0,0,1,$A$14*4)), "") | FO12: =IF(FP12<>"", $A$14&" meses de café", "") -> 3 meses de café | FP12: =IF(AND(NOT(ISBLANK(FO$1)), MOD(FO$1,$A$14)=0), -$A$2*SUM(OFFSET(FO4,0,0,1,$A$14*4)), "") -> -83700 | FQ12: =IF(FR12<>"", $A$14&" meses de café", "") | FR12: =IF(AND(NOT(ISBLANK(FQ$1)), MOD(FQ$1,$A$14)=0), -$A$2*SUM(OFFSET(FQ4,0,0,1,$A$14*4)), "") | FS12: =IF(FT12<>"", $A$14&" meses de café", "") | FT12: =IF(AND(NOT(ISBLANK(FS$1)), MOD(FS$1,$A$14)=0), -$A$2*SUM(OFFSET(FS4,0,0,1,$A$14*4)), "") | FU12: =IF(FV12<>"", $A$14&" meses de café", "") | FV12: =IF(AND(NOT(ISBLANK(FU$1)), MOD(FU$1,$A$14)=0), -$A$2*SUM(OFFSET(FU4,0,0,1,$A$14*4)), "") | FW12: =IF(FX12<>"", $A$14&" meses de café", "") | FX12: =IF(AND(NOT(ISBLANK(FW$1)), MOD(FW$1,$A$14)=0), -$A$2*SUM(OFFSET(FW4,0,0,1,$A$14*4)), "") | FY12: =IF(FZ12<>"", $A$14&" meses de café", "") | FZ12: =IF(AND(NOT(ISBLANK(FY$1)), MOD(FY$1,$A$14)=0), -$A$2*SUM(OFFSET(FY4,0,0,1,$A$14*4)), "") | GA12: =IF(GB12<>"", $A$14&" meses de café", "") -> 3 meses de café | GB12: =IF(AND(NOT(ISBLANK(GA$1)), MOD(GA$1,$A$14)=0), -$A$2*SUM(OFFSET(GA4,0,0,1,$A$14*4)), "") -> -86800 | GC12: =IF(GD12<>"", $A$14&" meses de café", "") | GD12: =IF(AND(NOT(ISBLANK(GC$1)), MOD(GC$1,$A$14)=0), -$A$2*SUM(OFFSET(GC4,0,0,1,$A$14*4)), "") | GE12: =IF(GF12<>"", $A$14&" meses de café", "") | GF12: =IF(AND(NOT(ISBLANK(GE$1)), MOD(GE$1,$A$14)=0), -$A$2*SUM(OFFSET(GE4,0,0,1,$A$14*4)), "") | GG12: =IF(GH12<>"", $A$14&" meses de café", "") | GH12: =IF(AND(NOT(ISBLANK(GG$1)), MOD(GG$1,$A$14)=0), -$A$2*SUM(OFFSET(GG4,0,0,1,$A$14*4)), "") | GI12: =IF(GJ12<>"", $A$14&" meses de café", "") | GJ12: =IF(AND(NOT(ISBLANK(GI$1)), MOD(GI$1,$A$14)=0), -$A$2*SUM(OFFSET(GI4,0,0,1,$A$14*4)), "") | GK12: =IF(GL12<>"", $A$14&" meses de café", "") | GL12: =IF(AND(NOT(ISBLANK(GK$1)), MOD(GK$1,$A$14)=0), -$A$2*SUM(OFFSET(GK4,0,0,1,$A$14*4)), "") | GM12: =IF(GN12<>"", $A$14&" meses de café", "") -> 3 meses de café | GN12: =IF(AND(NOT(ISBLANK(GM$1)), MOD(GM$1,$A$14)=0), -$A$2*SUM(OFFSET(GM4,0,0,1,$A$14*4)), "") -> -93000 | GO12: =IF(GP12<>"", $A$14&" meses de café", "") | GP12: =IF(AND(NOT(ISBLANK(GO$1)), MOD(GO$1,$A$14)=0), -$A$2*SUM(OFFSET(GO4,0,0,1,$A$14*4)), "") | GQ12: =IF(GR12<>"", $A$14&" meses de café", "") | GR12: =IF(AND(NOT(ISBLANK(GQ$1)), MOD(GQ$1,$A$14)=0), -$A$2*SUM(OFFSET(GQ4,0,0,1,$A$14*4)), "") | GS12: =IF(GT12<>"", $A$14&" meses de café", "") | GT12: =IF(AND(NOT(ISBLANK(GS$1)), MOD(GS$1,$A$14)=0), -$A$2*SUM(OFFSET(GS4,0,0,1,$A$14*4)), "") | GU12: =IF(GV12<>"", $A$14&" meses de café", "") | GV12: =IF(AND(NOT(ISBLANK(GU$1)), MOD(GU$1,$A$14)=0), -$A$2*SUM(OFFSET(GU4,0,0,1,$A$14*4)), "") | GW12: =IF(GX12<>"", $A$14&" meses de café", "") | GX12: =IF(AND(NOT(ISBLANK(GW$1)), MOD(GW$1,$A$14)=0), -$A$2*SUM(OFFSET(GW4,0,0,1,$A$14*4)), "") | GY12: =IF(GZ12<>"", $A$14&" meses de café", "") -> 3 meses de café | GZ12: =IF(AND(NOT(ISBLANK(GY$1)), MOD(GY$1,$A$14)=0), -$A$2*SUM(OFFSET(GY4,0,0,1,$A$14*4)), "") -> -93000 | HA12: =IF(HB12<>"", $A$14&" meses de café", "") | HB12: =IF(AND(NOT(ISBLANK(HA$1)), MOD(HA$1,$A$14)=0), -$A$2*SUM(OFFSET(HA4,0,0,1,$A$14*4)), "") | HC12: =IF(HD12<>"", $A$14&" meses de café", "") | HD12: =IF(AND(NOT(ISBLANK(HC$1)), MOD(HC$1,$A$14)=0), -$A$2*SUM(OFFSET(HC4,0,0,1,$A$14*4)), "") | HE12: =IF(HF12<>"", $A$14&" meses de café", "") | HF12: =IF(AND(NOT(ISBLANK(HE$1)), MOD(HE$1,$A$14)=0), -$A$2*SUM(OFFSET(HE4,0,0,1,$A$14*4)), "") | HG12: =IF(HH12<>"", $A$14&" meses de café", "") | HH12: =IF(AND(NOT(ISBLANK(HG$1)), MOD(HG$1,$A$14)=0), -$A$2*SUM(OFFSET(HG4,0,0,1,$A$14*4)), "") | HI12: =IF(HJ12<>"", $A$14&" meses de café", "") | HJ12: =IF(AND(NOT(ISBLANK(HI$1)), MOD(HI$1,$A$14)=0), -$A$2*SUM(OFFSET(HI4,0,0,1,$A$14*4)), "") | HK12: =IF(HL12<>"", $A$14&" meses de café", "") -> 3 meses de café | HL12: =IF(AND(NOT(ISBLANK(HK$1)), MOD(HK$1,$A$14)=0), -$A$2*SUM(OFFSET(HK4,0,0,1,$A$14*4)), "") -> -102300 | HM12: =IF(HN12<>"", $A$14&" meses de café", "") | HN12: =IF(AND(NOT(ISBLANK(HM$1)), MOD(HM$1,$A$14)=0), -$A$2*SUM(OFFSET(HM4,0,0,1,$A$14*4)), "") | HO12: =IF(HP12<>"", $A$14&" meses de café", "") | HP12: =IF(AND(NOT(ISBLANK(HO$1)), MOD(HO$1,$A$14)=0), -$A$2*SUM(OFFSET(HO4,0,0,1,$A$14*4)), "") | HQ12: =IF(HR12<>"", $A$14&" meses de café", "") | HR12: =IF(AND(NOT(ISBLANK(HQ$1)), MOD(HQ$1,$A$14)=0), -$A$2*SUM(OFFSET(HQ4,0,0,1,$A$14*4)), "") | HS12: =IF(HT12<>"", $A$14&" meses de café", "") | HT12: =IF(AND(NOT(ISBLANK(HS$1)), MOD(HS$1,$A$14)=0), -$A$2*SUM(OFFSET(HS4,0,0,1,$A$14*4)), "") | HU12: =IF(HV12<>"", $A$14&" meses de café", "") | HV12: =IF(AND(NOT(ISBLANK(HU$1)), MOD(HU$1,$A$14)=0), -$A$2*SUM(OFFSET(HU4,0,0,1,$A$14*4)), "") | HW12: =IF(HX12<>"", $A$14&" meses de café", "") -> 3 meses de café | HX12: =IF(AND(NOT(ISBLANK(HW$1)), MOD(HW$1,$A$14)=0), -$A$2*SUM(OFFSET(HW4,0,0,1,$A$14*4)), "") -> -102300 | HY12: =IF(HZ12<>"", $A$14&" meses de café", "") | HZ12: =IF(AND(NOT(ISBLANK(HY$1)), MOD(HY$1,$A$14)=0), -$A$2*SUM(OFFSET(HY4,0,0,1,$A$14*4)), "") | IA12: =IF(IB12<>"", $A$14&" meses de café", "") | IB12: =IF(AND(NOT(ISBLANK(IA$1)), MOD(IA$1,$A$14)=0), -$A$2*SUM(OFFSET(IA4,0,0,1,$A$14*4)), "") | IC12: =IF(ID12<>"", $A$14&" meses de café", "") | ID12: =IF(AND(NOT(ISBLANK(IC$1)), MOD(IC$1,$A$14)=0), -$A$2*SUM(OFFSET(IC4,0,0,1,$A$14*4)), "") | IE12: =IF(IF12<>"", $A$14&" meses de café", "") | IF12: =IF(AND(NOT(ISBLANK(IE$1)), MOD(IE$1,$A$14)=0), -$A$2*SUM(OFFSET(IE4,0,0,1,$A$14*4)), "") | IG12: =IF(IH12<>"", $A$14&" meses de café", "") | IH12: =IF(AND(NOT(ISBLANK(IG$1)), MOD(IG$1,$A$14)=0), -$A$2*SUM(OFFSET(IG4,0,0,1,$A$14*4)), "") | II12: =IF(IJ12<>"", $A$14&" meses de café", "") -> 3 meses de café | IJ12: =IF(AND(NOT(ISBLANK(II$1)), MOD(II$1,$A$14)=0), -$A$2*SUM(OFFSET(II4,0,0,1,$A$14*4)), "") -> -111600 | IK12: =IF(IL12<>"", $A$14&" meses de café", "") | IL12: =IF(AND(NOT(ISBLANK(IK$1)), MOD(IK$1,$A$14)=0), -$A$2*SUM(OFFSET(IK4,0,0,1,$A$14*4)), "") | IM12: =IF(IN12<>"", $A$14&" meses de café", "") | IN12: =IF(AND(NOT(ISBLANK(IM$1)), MOD(IM$1,$A$14)=0), -$A$2*SUM(OFFSET(IM4,0,0,1,$A$14*4)), "") | IO12: =IF(IP12<>"", $A$14&" meses de café", "") | IP12: =IF(AND(NOT(ISBLANK(IO$1)), MOD(IO$1,$A$14)=0), -$A$2*SUM(OFFSET(IO4,0,0,1,$A$14*4)), "") | IQ12: =IF(IR12<>"", $A$14&" meses de café", "") | IR12: =IF(AND(NOT(ISBLANK(IQ$1)), MOD(IQ$1,$A$14)=0), -$A$2*SUM(OFFSET(IQ4,0,0,1,$A$14*4)), "") | IS12: =IF(IT12<>"", $A$14&" meses de café", "") | IT12: =IF(AND(NOT(ISBLANK(IS$1)), MOD(IS$1,$A$14)=0), -$A$2*SUM(OFFSET(IS4,0,0,1,$A$14*4)), "") | IU12: =IF(IV12<>"", $A$14&" meses de café", "") -> 3 meses de café | IV12: =IF(AND(NOT(ISBLANK(IU$1)), MOD(IU$1,$A$14)=0), -$A$2*SUM(OFFSET(IU4,0,0,1,$A$14*4)), "") -> -111600 | IW12: =IF(IX12<>"", $A$14&" meses de café", "") | IX12: =IF(AND(NOT(ISBLANK(IW$1)), MOD(IW$1,$A$14)=0), -$A$2*SUM(OFFSET(IW4,0,0,1,$A$14*4)), "") | IY12: =IF(IZ12<>"", $A$14&" meses de café", "") | IZ12: =IF(AND(NOT(ISBLANK(IY$1)), MOD(IY$1,$A$14)=0), -$A$2*SUM(OFFSET(IY4,0,0,1,$A$14*4)), "") | JA12: =IF(JB12<>"", $A$14&" meses de café", "") | JB12: =IF(AND(NOT(ISBLANK(JA$1)), MOD(JA$1,$A$14)=0), -$A$2*SUM(OFFSET(JA4,0,0,1,$A$14*4)), "") | JC12: =IF(JD12<>"", $A$14&" meses de café", "") | JD12: =IF(AND(NOT(ISBLANK(JC$1)), MOD(JC$1,$A$14)=0), -$A$2*SUM(OFFSET(JC4,0,0,1,$A$14*4)), "") | JE12: =IF(JF12<>"", $A$14&" meses de café", "") | JF12: =IF(AND(NOT(ISBLANK(JE$1)), MOD(JE$1,$A$14)=0), -$A$2*SUM(OFFSET(JE4,0,0,1,$A$14*4)), "") | JG12: =IF(JH12<>"", $A$14&" meses de café", "") -> 3 meses de café | JH12: =IF(AND(NOT(ISBLANK(JG$1)), MOD(JG$1,$A$14)=0), -$A$2*SUM(OFFSET(JG4,0,0,1,$A$14*4)), "") -> -117800 | JI12: =IF(JJ12<>"", $A$14&" meses de café", "") | JJ12: =IF(AND(NOT(ISBLANK(JI$1)), MOD(JI$1,$A$14)=0), -$A$2*SUM(OFFSET(JI4,0,0,1,$A$14*4)), "") | JK12: =IF(JL12<>"", $A$14&" meses de café", "") | JL12: =IF(AND(NOT(ISBLANK(JK$1)), MOD(JK$1,$A$14)=0), -$A$2*SUM(OFFSET(JK4,0,0,1,$A$14*4)), "") | JM12: =IF(JN12<>"", $A$14&" meses de café", "") | JN12: =IF(AND(NOT(ISBLANK(JM$1)), MOD(JM$1,$A$14)=0), -$A$2*SUM(OFFSET(JM4,0,0,1,$A$14*4)), "") | JO12: =IF(JP12<>"", $A$14&" meses de café", "") | JP12: =IF(AND(NOT(ISBLANK(JO$1)), MOD(JO$1,$A$14)=0), -$A$2*SUM(OFFSET(JO4,0,0,1,$A$14*4)), "") | JQ12: =IF(JR12<>"", $A$14&" meses de café", "") | JR12: =IF(AND(NOT(ISBLANK(JQ$1)), MOD(JQ$1,$A$14)=0), -$A$2*SUM(OFFSET(JQ4,0,0,1,$A$14*4)), "") | JS12: =IF(JT12<>"", $A$14&" meses de café", "") -> 3 meses de café | JT12: =IF(AND(NOT(ISBLANK(JS$1)), MOD(JS$1,$A$14)=0), -$A$2*SUM(OFFSET(JS4,0,0,1,$A$14*4)), "") -> -120900 | JU12: =IF(JV12<>"", $A$14&" meses de café", "") | JV12: =IF(AND(NOT(ISBLANK(JU$1)), MOD(JU$1,$A$14)=0), -$A$2*SUM(OFFSET(JU4,0,0,1,$A$14*4)), "") | JW12: =IF(JX12<>"", $A$14&" meses de café", "") | JX12: =IF(AND(NOT(ISBLANK(JW$1)), MOD(JW$1,$A$14)=0), -$A$2*SUM(OFFSET(JW4,0,0,1,$A$14*4)), "") | JY12: =IF(JZ12<>"", $A$14&" meses de café", "") | JZ12: =IF(AND(NOT(ISBLANK(JY$1)), MOD(JY$1,$A$14)=0), -$A$2*SUM(OFFSET(JY4,0,0,1,$A$14*4)), "") | KA12: =IF(KB12<>"", $A$14&" meses de café", "") | KB12: =IF(AND(NOT(ISBLANK(KA$1)), MOD(KA$1,$A$14)=0), -$A$2*SUM(OFFSET(KA4,0,0,1,$A$14*4)), "") | KC12: =IF(KD12<>"", $A$14&" meses de café", "") | KD12: =IF(AND(NOT(ISBLANK(KC$1)), MOD(KC$1,$A$14)=0), -$A$2*SUM(OFFSET(KC4,0,0,1,$A$14*4)), "") | KE12: =IF(KF12<>"", $A$14&" meses de café", "") -> 3 meses de café | KF12: =IF(AND(NOT(ISBLANK(KE$1)), MOD(KE$1,$A$14)=0), -$A$2*SUM(OFFSET(KE4,0,0,1,$A$14*4)), "") -> -40300 | KG12: =IF(KH12<>"", $A$14&" meses de café", "") | KH12: =IF(AND(NOT(ISBLANK(KG$1)), MOD(KG$1,$A$14)=0), -$A$2*SUM(OFFSET(KG4,0,0,1,$A$14*4)), "")
C13: Seguro | D13: =-'Investimento Inicial'!$B$6 -> -5000
A14: 3 | C14: Identidade visual | D14: =-'Investimento Inicial'!$B$8 -> -4000
C15: Site | D15: =-'Investimento Inicial'!$B$9 -> -3000
C16: =IF(C$12<>"", "Frete do café verde", "") -> Frete do café verde | D16: =IF(D$12<>"", -1000,"") -> -1000 | G16: =IF(G$12<>"", "Frete do café verde", "") | H16: =IF(H$12<>"", -1000,"") | K16: =IF(K$12<>"", "Frete do café verde", "") | L16: =IF(L$12<>"", -1000,"") | O16: =IF(O$12<>"", "Frete do café verde", "") -> Frete do café verde | P16: =IF(P$12<>"", -1000,"") -> -1000 | S16: =IF(S$12<>"", "Frete do café verde", "") | T16: =IF(T$12<>"", -1000,"") | W16: =IF(W$12<>"", "Frete do café verde", "") | X16: =IF(X$12<>"", -1000,"") | AA16: =IF(AA$12<>"", "Frete do café verde", "") -> Frete do café verde | AB16: =IF(AB$12<>"", -1000,"") -> -1000 | AE16: =IF(AE$12<>"", "Frete do café verde", "") | AF16: =IF(AF$12<>"", -1000,"") | AI16: =IF(AI$12<>"", "Frete do café verde", "") | AJ16: =IF(AJ$12<>"", -1000,"") | AM16: =IF(AM$12<>"", "Frete do café verde", "") -> Frete do café verde | AN16: =IF(AN$12<>"", -1000,"") -> -1000 | AQ16: =IF(AQ$12<>"", "Frete do café verde", "") | AR16: =IF(AR$12<>"", -1000,"") | AU16: =IF(AU$12<>"", "Frete do café verde", "") | AV16: =IF(AV$12<>"", -1000,"") | AY16: =IF(AY$12<>"", "Frete do café verde", "") -> Frete do café verde | AZ16: =IF(AZ$12<>"", -1000,"") -> -1000 | BC16: =IF(BC$12<>"", "Frete do café verde", "") | BD16: =IF(BD$12<>"", -1000,"") | BG16: =IF(BG$12<>"", "Frete do café verde", "") | BH16: =IF(BH$12<>"", -1000,"") | BK16: =IF(BK$12<>"", "Frete do café verde", "") -> Frete do café verde | BL16: =IF(BL$12<>"", -1000,"") -> -1000 | BO16: =IF(BO$12<>"", "Frete do café verde", "") | BP16: =IF(BP$12<>"", -1000,"") | BS16: =IF(BS$12<>"", "Frete do café verde", "") | BT16: =IF(BT$12<>"", -1000,"") | BW16: =IF(BW$12<>"", "Frete do café verde", "") -> Frete do café verde | BX16: =IF(BX$12<>"", -1000,"") -> -1000 | CA16: =IF(CA$12<>"", "Frete do café verde", "") | CB16: =IF(CB$12<>"", -1000,"") | CE16: =IF(CE$12<>"", "Frete do café verde", "") | CF16: =IF(CF$12<>"", -1000,"") | CI16: =IF(CI$12<>"", "Frete do café verde", "") -> Frete do café verde | CJ16: =IF(CJ$12<>"", -1000,"") -> -1000 | CM16: =IF(CM$12<>"", "Frete do café verde", "") | CN16: =IF(CN$12<>"", -1000,"") | CQ16: =IF(CQ$12<>"", "Frete do café verde", "") | CR16: =IF(CR$12<>"", -1000,"") | CU16: =IF(CU$12<>"", "Frete do café verde", "") -> Frete do café verde | CV16: =IF(CV$12<>"", -1000,"") -> -1000 | CY16: =IF(CY$12<>"", "Frete do café verde", "") | CZ16: =IF(CZ$12<>"", -1000,"") | DC16: =IF(DC$12<>"", "Frete do café verde", "") | DD16: =IF(DD$12<>"", -1000,"") | DG16: =IF(DG$12<>"", "Frete do café verde", "") -> Frete do café verde | DH16: =IF(DH$12<>"", -1000,"") -> -1000 | DK16: =IF(DK$12<>"", "Frete do café verde", "") | DL16: =IF(DL$12<>"", -1000,"") | DO16: =IF(DO$12<>"", "Frete do café verde", "") | DP16: =IF(DP$12<>"", -1000,"") | DS16: =IF(DS$12<>"", "Frete do café verde", "") -> Frete do café verde | DT16: =IF(DT$12<>"", -1000,"") -> -1000 | DW16: =IF(DW$12<>"", "Frete do café verde", "") | DX16: =IF(DX$12<>"", -1000,"") | EA16: =IF(EA$12<>"", "Frete do café verde", "") | EB16: =IF(EB$12<>"", -1000,"") | EE16: =IF(EE$12<>"", "Frete do café verde", "") -> Frete do café verde | EF16: =IF(EF$12<>"", -1000,"") -> -1000 | EI16: =IF(EI$12<>"", "Frete do café verde", "") | EJ16: =IF(EJ$12<>"", -1000,"") | EM16: =IF(EM$12<>"", "Frete do café verde", "") | EN16: =IF(EN$12<>"", -1000,"") | EQ16: =IF(EQ$12<>"", "Frete do café verde", "") -> Frete do café verde | ER16: =IF(ER$12<>"", -1000,"") -> -1000 | EU16: =IF(EU$12<>"", "Frete do café verde", "") | EV16: =IF(EV$12<>"", -1000,"") | EY16: =IF(EY$12<>"", "Frete do café verde", "") | EZ16: =IF(EZ$12<>"", -1000,"") | FC16: =IF(FC$12<>"", "Frete do café verde", "") -> Frete do café verde | FD16: =IF(FD$12<>"", -1000,"") -> -1000 | FG16: =IF(FG$12<>"", "Frete do café verde", "") | FH16: =IF(FH$12<>"", -1000,"") | FK16: =IF(FK$12<>"", "Frete do café verde", "") | FL16: =IF(FL$12<>"", -1000,"") | FO16: =IF(FO$12<>"", "Frete do café verde", "") -> Frete do café verde | FP16: =IF(FP$12<>"", -1000,"") -> -1000 | FS16: =IF(FS$12<>"", "Frete do café verde", "") | FT16: =IF(FT$12<>"", -1000,"") | FW16: =IF(FW$12<>"", "Frete do café verde", "") | FX16: =IF(FX$12<>"", -1000,"") | GA16: =IF(GA$12<>"", "Frete do café verde", "") -> Frete do café verde | GB16: =IF(GB$12<>"", -1000,"") -> -1000 | GE16: =IF(GE$12<>"", "Frete do café verde", "") | GF16: =IF(GF$12<>"", -1000,"") | GI16: =IF(GI$12<>"", "Frete do café verde", "") | GJ16: =IF(GJ$12<>"", -1000,"") | GM16: =IF(GM$12<>"", "Frete do café verde", "") -> Frete do café verde | GN16: =IF(GN$12<>"", -1000,"") -> -1000 | GQ16: =IF(GQ$12<>"", "Frete do café verde", "") | GR16: =IF(GR$12<>"", -1000,"") | GU16: =IF(GU$12<>"", "Frete do café verde", "") | GV16: =IF(GV$12<>"", -1000,"") | GY16: =IF(GY$12<>"", "Frete do café verde", "") -> Frete do café verde | GZ16: =IF(GZ$12<>"", -1000,"") -> -1000 | HC16: =IF(HC$12<>"", "Frete do café verde", "") | HD16: =IF(HD$12<>"", -1000,"") | HG16: =IF(HG$12<>"", "Frete do café verde", "") | HH16: =IF(HH$12<>"", -1000,"") | HK16: =IF(HK$12<>"", "Frete do café verde", "") -> Frete do café verde | HL16: =IF(HL$12<>"", -1000,"") -> -1000 | HO16: =IF(HO$12<>"", "Frete do café verde", "") | HP16: =IF(HP$12<>"", -1000,"") | HS16: =IF(HS$12<>"", "Frete do café verde", "") | HT16: =IF(HT$12<>"", -1000,"") | HW16: =IF(HW$12<>"", "Frete do café verde", "") -> Frete do café verde | HX16: =IF(HX$12<>"", -1000,"") -> -1000 | IA16: =IF(IA$12<>"", "Frete do café verde", "") | IB16: =IF(IB$12<>"", -1000,"") | IE16: =IF(IE$12<>"", "Frete do café verde", "") | IF16: =IF(IF$12<>"", -1000,"") | II16: =IF(II$12<>"", "Frete do café verde", "") -> Frete do café verde | IJ16: =IF(IJ$12<>"", -1000,"") -> -1000 | IM16: =IF(IM$12<>"", "Frete do café verde", "") | IN16: =IF(IN$12<>"", -1000,"") | IQ16: =IF(IQ$12<>"", "Frete do café verde", "") | IR16: =IF(IR$12<>"", -1000,"") | IU16: =IF(IU$12<>"", "Frete do café verde", "") -> Frete do café verde | IV16: =IF(IV$12<>"", -1000,"") -> -1000 | IY16: =IF(IY$12<>"", "Frete do café verde", "") | IZ16: =IF(IZ$12<>"", -1000,"") | JC16: =IF(JC$12<>"", "Frete do café verde", "") | JD16: =IF(JD$12<>"", -1000,"") | JG16: =IF(JG$12<>"", "Frete do café verde", "") -> Frete do café verde | JH16: =IF(JH$12<>"", -1000,"") -> -1000 | JK16: =IF(JK$12<>"", "Frete do café verde", "") | JL16: =IF(JL$12<>"", -1000,"") | JO16: =IF(JO$12<>"", "Frete do café verde", "") | JP16: =IF(JP$12<>"", -1000,"") | JS16: =IF(JS$12<>"", "Frete do café verde", "") -> Frete do café verde | JT16: =IF(JT$12<>"", -1000,"") -> -1000 | JW16: =IF(JW$12<>"", "Frete do café verde", "") | JX16: =IF(JX$12<>"", -1000,"") | KA16: =IF(KA$12<>"", "Frete do café verde", "") | KB16: =IF(KB$12<>"", -1000,"") | KE16: =IF(KE$12<>"", "Frete do café verde", "") -> Frete do café verde | KF16: =IF(KF$12<>"", -1000,"") -> -1000
C17: Marketing | D17: =-'Investimento Inicial'!$B$7 -> -3000 | G17: Marketing | H17: =-'Investimento Inicial'!$B$7 -> -3000 | K17: Marketing | L17: =-'Investimento Inicial'!$B$7 -> -3000 | O17: Marketing | P17: =-'Investimento Inicial'!$B$7 -> -3000 | S17: Marketing | T17: =-'Investimento Inicial'!$B$7 -> -3000 | W17: Marketing | X17: =-'Investimento Inicial'!$B$7 -> -3000 | AA17: Marketing | AB17: =-'Investimento Inicial'!$B$7 -> -3000 | AE17: Marketing | AF17: =-'Investimento Inicial'!$B$7 -> -3000 | AI17: Marketing | AJ17: =-'Investimento Inicial'!$B$7 -> -3000 | AM17: Marketing | AN17: =-'Investimento Inicial'!$B$7 -> -3000 | AQ17: Marketing | AR17: =-'Investimento Inicial'!$B$7 -> -3000 | AU17: Marketing | AV17: =-'Investimento Inicial'!$B$7 -> -3000 | AY17: Marketing | AZ17: =-'Investimento Inicial'!$B$7 -> -3000 | BC17: Marketing | BD17: =-'Investimento Inicial'!$B$7 -> -3000 | BG17: Marketing | BH17: =-'Investimento Inicial'!$B$7 -> -3000 | BK17: Marketing | BL17: =-'Investimento Inicial'!$B$7 -> -3000 | BO17: Marketing | BP17: =-'Investimento Inicial'!$B$7 -> -3000 | BS17: Marketing | BT17: =-'Investimento Inicial'!$B$7 -> -3000 | BW17: Marketing | BX17: =-'Investimento Inicial'!$B$7 -> -3000 | CA17: Marketing | CB17: =-'Investimento Inicial'!$B$7 -> -3000 | CE17: Marketing | CF17: =-'Investimento Inicial'!$B$7 -> -3000 | CI17: Marketing | CJ17: =-'Investimento Inicial'!$B$7 -> -3000 | CM17: Marketing | CN17: =-'Investimento Inicial'!$B$7 -> -3000 | CQ17: Marketing | CR17: =-'Investimento Inicial'!$B$7 -> -3000 | CU17: Marketing | CV17: =-'Investimento Inicial'!$B$7 -> -3000 | CY17: Marketing | CZ17: =-'Investimento Inicial'!$B$7 -> -3000 | DC17: Marketing | DD17: =-'Investimento Inicial'!$B$7 -> -3000 | DG17: Marketing | DH17: =-'Investimento Inicial'!$B$7 -> -3000 | DK17: Marketing | DL17: =-'Investimento Inicial'!$B$7 -> -3000 | DO17: Marketing | DP17: =-'Investimento Inicial'!$B$7 -> -3000 | DS17: Marketing | DT17: =-'Investimento Inicial'!$B$7 -> -3000 | DW17: Marketing | DX17: =-'Investimento Inicial'!$B$7 -> -3000 | EA17: Marketing | EB17: =-'Investimento Inicial'!$B$7 -> -3000 | EE17: Marketing | EF17: =-'Investimento Inicial'!$B$7 -> -3000 | EI17: Marketing | EJ17: =-'Investimento Inicial'!$B$7 -> -3000 | EM17: Marketing | EN17: =-'Investimento Inicial'!$B$7 -> -3000 | EQ17: Marketing | ER17: =-'Investimento Inicial'!$B$7 -> -3000 | EU17: Marketing | EV17: =-'Investimento Inicial'!$B$7 -> -3000 | EY17: Marketing | EZ17: =-'Investimento Inicial'!$B$7 -> -3000 | FC17: Marketing | FD17: =-'Investimento Inicial'!$B$7 -> -3000 | FG17: Marketing | FH17: =-'Investimento Inicial'!$B$7 -> -3000 | FK17: Marketing | FL17: =-'Investimento Inicial'!$B$7 -> -3000 | FO17: Marketing | FP17: =-'Investimento Inicial'!$B$7 -> -3000 | FS17: Marketing | FT17: =-'Investimento Inicial'!$B$7 -> -3000 | FW17: Marketing | FX17: =-'Investimento Inicial'!$B$7 -> -3000 | GA17: Marketing | GB17: =-'Investimento Inicial'!$B$7 -> -3000 | GE17: Marketing | GF17: =-'Investimento Inicial'!$B$7 -> -3000 | GI17: Marketing | GJ17: =-'Investimento Inicial'!$B$7 -> -3000 | GM17: Marketing | GN17: =-'Investimento Inicial'!$B$7 -> -3000 | GQ17: Marketing | GR17: =-'Investimento Inicial'!$B$7 -> -3000 | GU17: Marketing | GV17: =-'Investimento Inicial'!$B$7 -> -3000 | GY17: Marketing | GZ17: =-'Investimento Inicial'!$B$7 -> -3000 | HC17: Marketing | HD17: =-'Investimento Inicial'!$B$7 -> -3000 | HG17: Marketing | HH17: =-'Investimento Inicial'!$B$7 -> -3000 | HK17: Marketing | HL17: =-'Investimento Inicial'!$B$7 -> -3000 | HO17: Marketing | HP17: =-'Investimento Inicial'!$B$7 -> -3000 | HS17: Marketing | HT17: =-'Investimento Inicial'!$B$7 -> -3000 | HW17: Marketing | HX17: =-'Investimento Inicial'!$B$7 -> -3000 | IA17: Marketing | IB17: =-'Investimento Inicial'!$B$7 -> -3000 | IE17: Marketing | IF17: =-'Investimento Inicial'!$B$7 -> -3000 | II17: Marketing | IJ17: =-'Investimento Inicial'!$B$7 -> -3000 | IM17: Marketing | IN17: =-'Investimento Inicial'!$B$7 -> -3000 | IQ17: Marketing | IR17: =-'Investimento Inicial'!$B$7 -> -3000 | IU17: Marketing | IV17: =-'Investimento Inicial'!$B$7 -> -3000 | IY17: Marketing | IZ17: =-'Investimento Inicial'!$B$7 -> -3000 | JC17: Marketing | JD17: =-'Investimento Inicial'!$B$7 -> -3000 | JG17: Marketing | JH17: =-'Investimento Inicial'!$B$7 -> -3000 | JK17: Marketing | JL17: =-'Investimento Inicial'!$B$7 -> -3000 | JO17: Marketing | JP17: =-'Investimento Inicial'!$B$7 -> -3000 | JS17: Marketing | JT17: =-'Investimento Inicial'!$B$7 -> -3000 | JW17: Marketing | JX17: =-'Investimento Inicial'!$B$7 -> -3000 | KA17: Marketing | KB17: =-'Investimento Inicial'!$B$7 -> -3000 | KE17: Marketing | KF17: =-'Investimento Inicial'!$B$7 -> -3000
C18: 1 mês de aluguel | D18: =-'Investimento Inicial'!$C$4 -> -5000 | G18: 1 mês de aluguel | H18: =-'Investimento Inicial'!$C$4 -> -5000 | K18: 1 mês de aluguel | L18: =-'Investimento Inicial'!$C$4 -> -5000 | O18: 1 mês de aluguel | P18: =-'Investimento Inicial'!$C$4 -> -5000 | S18: 1 mês de aluguel | T18: =-'Investimento Inicial'!$C$4 -> -5000 | W18: 1 mês de aluguel | X18: =-'Investimento Inicial'!$C$4 -> -5000 | AA18: 1 mês de aluguel | AB18: =-'Investimento Inicial'!$C$4 -> -5000 | AE18: 1 mês de aluguel | AF18: =-'Investimento Inicial'!$C$4 -> -5000 | AI18: 1 mês de aluguel | AJ18: =-'Investimento Inicial'!$C$4 -> -5000 | AM18: 1 mês de aluguel | AN18: =-'Investimento Inicial'!$C$4 -> -5000 | AQ18: 1 mês de aluguel | AR18: =-'Investimento Inicial'!$C$4 -> -5000 | AU18: 1 mês de aluguel | AV18: =-'Investimento Inicial'!$C$4 -> -5000 | AY18: 1 mês de aluguel | AZ18: =-'Investimento Inicial'!$C$4 -> -5000 | BC18: 1 mês de aluguel | BD18: =-'Investimento Inicial'!$C$4 -> -5000 | BG18: 1 mês de aluguel | BH18: =-'Investimento Inicial'!$C$4 -> -5000 | BK18: 1 mês de aluguel | BL18: =-'Investimento Inicial'!$C$4 -> -5000 | BO18: 1 mês de aluguel | BP18: =-'Investimento Inicial'!$C$4 -> -5000 | BS18: 1 mês de aluguel | BT18: =-'Investimento Inicial'!$C$4 -> -5000 | BW18: 1 mês de aluguel | BX18: =-'Investimento Inicial'!$C$4 -> -5000 | CA18: 1 mês de aluguel | CB18: =-'Investimento Inicial'!$C$4 -> -5000 | CE18: 1 mês de aluguel | CF18: =-'Investimento Inicial'!$C$4 -> -5000 | CI18: 1 mês de aluguel | CJ18: =-'Investimento Inicial'!$C$4 -> -5000 | CM18: 1 mês de aluguel | CN18: =-'Investimento Inicial'!$C$4 -> -5000 | CQ18: 1 mês de aluguel | CR18: =-'Investimento Inicial'!$C$4 -> -5000 | CU18: 1 mês de aluguel | CV18: =-'Investimento Inicial'!$C$4 -> -5000 | CY18: 1 mês de aluguel | CZ18: =-'Investimento Inicial'!$C$4 -> -5000 | DC18: 1 mês de aluguel | DD18: =-'Investimento Inicial'!$C$4 -> -5000 | DG18: 1 mês de aluguel | DH18: =-'Investimento Inicial'!$C$4 -> -5000 | DK18: 1 mês de aluguel | DL18: =-'Investimento Inicial'!$C$4 -> -5000 | DO18: 1 mês de aluguel | DP18: =-'Investimento Inicial'!$C$4 -> -5000 | DS18: 1 mês de aluguel | DT18: =-'Investimento Inicial'!$C$4 -> -5000 | DW18: 1 mês de aluguel | DX18: =-'Investimento Inicial'!$C$4 -> -5000 | EA18: 1 mês de aluguel | EB18: =-'Investimento Inicial'!$C$4 -> -5000 | EE18: 1 mês de aluguel | EF18: =-'Investimento Inicial'!$C$4 -> -5000 | EI18: 1 mês de aluguel | EJ18: =-'Investimento Inicial'!$C$4 -> -5000 | EM18: 1 mês de aluguel | EN18: =-'Investimento Inicial'!$C$4 -> -5000 | EQ18: 1 mês de aluguel | ER18: =-'Investimento Inicial'!$C$4 -> -5000 | EU18: 1 mês de aluguel | EV18: =-'Investimento Inicial'!$C$4 -> -5000 | EY18: 1 mês de aluguel | EZ18: =-'Investimento Inicial'!$C$4 -> -5000 | FC18: 1 mês de aluguel | FD18: =-'Investimento Inicial'!$C$4 -> -5000 | FG18: 1 mês de aluguel | FH18: =-'Investimento Inicial'!$C$4 -> -5000 | FK18: 1 mês de aluguel | FL18: =-'Investimento Inicial'!$C$4 -> -5000 | FO18: 1 mês de aluguel | FP18: =-'Investimento Inicial'!$C$4 -> -5000 | FS18: 1 mês de aluguel | FT18: =-'Investimento Inicial'!$C$4 -> -5000 | FW18: 1 mês de aluguel | FX18: =-'Investimento Inicial'!$C$4 -> -5000 | GA18: 1 mês de aluguel | GB18: =-'Investimento Inicial'!$C$4 -> -5000 | GE18: 1 mês de aluguel | GF18: =-'Investimento Inicial'!$C$4 -> -5000 | GI18: 1 mês de aluguel | GJ18: =-'Investimento Inicial'!$C$4 -> -5000 | GM18: 1 mês de aluguel | GN18: =-'Investimento Inicial'!$C$4 -> -5000 | GQ18: 1 mês de aluguel | GR18: =-'Investimento Inicial'!$C$4 -> -5000 | GU18: 1 mês de aluguel | GV18: =-'Investimento Inicial'!$C$4 -> -5000 | GY18: 1 mês de aluguel | GZ18: =-'Investimento Inicial'!$C$4 -> -5000 | HC18: 1 mês de aluguel | HD18: =-'Investimento Inicial'!$C$4 -> -5000 | HG18: 1 mês de aluguel | HH18: =-'Investimento Inicial'!$C$4 -> -5000 | HK18: 1 mês de aluguel | HL18: =-'Investimento Inicial'!$C$4 -> -5000 | HO18: 1 mês de aluguel | HP18: =-'Investimento Inicial'!$C$4 -> -5000 | HS18: 1 mês de aluguel | HT18: =-'Investimento Inicial'!$C$4 -> -5000 | HW18: 1 mês de aluguel | HX18: =-'Investimento Inicial'!$C$4 -> -5000 | IA18: 1 mês de aluguel | IB18: =-'Investimento Inicial'!$C$4 -> -5000 | IE18: 1 mês de aluguel | IF18: =-'Investimento Inicial'!$C$4 -> -5000 | II18: 1 mês de aluguel | IJ18: =-'Investimento Inicial'!$C$4 -> -5000 | IM18: 1 mês de aluguel | IN18: =-'Investimento Inicial'!$C$4 -> -5000 | IQ18: 1 mês de aluguel | IR18: =-'Investimento Inicial'!$C$4 -> -5000 | IU18: 1 mês de aluguel | IV18: =-'Investimento Inicial'!$C$4 -> -5000 | IY18: 1 mês de aluguel | IZ18: =-'Investimento Inicial'!$C$4 -> -5000 | JC18: 1 mês de aluguel | JD18: =-'Investimento Inicial'!$C$4 -> -5000 | JG18: 1 mês de aluguel | JH18: =-'Investimento Inicial'!$C$4 -> -5000 | JK18: 1 mês de aluguel | JL18: =-'Investimento Inicial'!$C$4 -> -5000 | JO18: 1 mês de aluguel | JP18: =-'Investimento Inicial'!$C$4 -> -5000 | JS18: 1 mês de aluguel | JT18: =-'Investimento Inicial'!$C$4 -> -5000 | JW18: 1 mês de aluguel | JX18: =-'Investimento Inicial'!$C$4 -> -5000 | KA18: 1 mês de aluguel | KB18: =-'Investimento Inicial'!$C$4 -> -5000 | KE18: 1 mês de aluguel | KF18: =-'Investimento Inicial'!$C$4 -> -5000
C19: 1 mês de contabilidade | D19: =-'Investimento Inicial'!$C$10 -> -1000 | G19: 1 mês de contabilidade | H19: =-'Investimento Inicial'!$C$10 -> -1000 | K19: 1 mês de contabilidade | L19: =-'Investimento Inicial'!$C$10 -> -1000 | O19: 1 mês de contabilidade | P19: =-'Investimento Inicial'!$C$10 -> -1000 | S19: 1 mês de contabilidade | T19: =-'Investimento Inicial'!$C$10 -> -1000 | W19: 1 mês de contabilidade | X19: =-'Investimento Inicial'!$C$10 -> -1000 | AA19: 1 mês de contabilidade | AB19: =-'Investimento Inicial'!$C$10 -> -1000 | AE19: 1 mês de contabilidade | AF19: =-'Investimento Inicial'!$C$10 -> -1000 | AI19: 1 mês de contabilidade | AJ19: =-'Investimento Inicial'!$C$10 -> -1000 | AM19: 1 mês de contabilidade | AN19: =-'Investimento Inicial'!$C$10 -> -1000 | AQ19: 1 mês de contabilidade | AR19: =-'Investimento Inicial'!$C$10 -> -1000 | AU19: 1 mês de contabilidade | AV19: =-'Investimento Inicial'!$C$10 -> -1000 | AY19: 1 mês de contabilidade | AZ19: =-'Investimento Inicial'!$C$10 -> -1000 | BC19: 1 mês de contabilidade | BD19: =-'Investimento Inicial'!$C$10 -> -1000 | BG19: 1 mês de contabilidade | BH19: =-'Investimento Inicial'!$C$10 -> -1000 | BK19: 1 mês de contabilidade | BL19: =-'Investimento Inicial'!$C$10 -> -1000 | BO19: 1 mês de contabilidade | BP19: =-'Investimento Inicial'!$C$10 -> -1000 | BS19: 1 mês de contabilidade | BT19: =-'Investimento Inicial'!$C$10 -> -1000 | BW19: 1 mês de contabilidade | BX19: =-'Investimento Inicial'!$C$10 -> -1000 | CA19: 1 mês de contabilidade | CB19: =-'Investimento Inicial'!$C$10 -> -1000 | CE19: 1 mês de contabilidade | CF19: =-'Investimento Inicial'!$C$10 -> -1000 | CI19: 1 mês de contabilidade | CJ19: =-'Investimento Inicial'!$C$10 -> -1000 | CM19: 1 mês de contabilidade | CN19: =-'Investimento Inicial'!$C$10 -> -1000 | CQ19: 1 mês de contabilidade | CR19: =-'Investimento Inicial'!$C$10 -> -1000 | CU19: 1 mês de contabilidade | CV19: =-'Investimento Inicial'!$C$10 -> -1000 | CY19: 1 mês de contabilidade | CZ19: =-'Investimento Inicial'!$C$10 -> -1000 | DC19: 1 mês de contabilidade | DD19: =-'Investimento Inicial'!$C$10 -> -1000 | DG19: 1 mês de contabilidade | DH19: =-'Investimento Inicial'!$C$10 -> -1000 | DK19: 1 mês de contabilidade | DL19: =-'Investimento Inicial'!$C$10 -> -1000 | DO19: 1 mês de contabilidade | DP19: =-'Investimento Inicial'!$C$10 -> -1000 | DS19: 1 mês de contabilidade | DT19: =-'Investimento Inicial'!$C$10 -> -1000 | DW19: 1 mês de contabilidade | DX19: =-'Investimento Inicial'!$C$10 -> -1000 | EA19: 1 mês de contabilidade | EB19: =-'Investimento Inicial'!$C$10 -> -1000 | EE19: 1 mês de contabilidade | EF19: =-'Investimento Inicial'!$C$10 -> -1000 | EI19: 1 mês de contabilidade | EJ19: =-'Investimento Inicial'!$C$10 -> -1000 | EM19: 1 mês de contabilidade | EN19: =-'Investimento Inicial'!$C$10 -> -1000 | EQ19: 1 mês de contabilidade | ER19: =-'Investimento Inicial'!$C$10 -> -1000 | EU19: 1 mês de contabilidade | EV19: =-'Investimento Inicial'!$C$10 -> -1000 | EY19: 1 mês de contabilidade | EZ19: =-'Investimento Inicial'!$C$10 -> -1000 | FC19: 1 mês de contabilidade | FD19: =-'Investimento Inicial'!$C$10 -> -1000 | FG19: 1 mês de contabilidade | FH19: =-'Investimento Inicial'!$C$10 -> -1000 | FK19: 1 mês de contabilidade | FL19: =-'Investimento Inicial'!$C$10 -> -1000 | FO19: 1 mês de contabilidade | FP19: =-'Investimento Inicial'!$C$10 -> -1000 | FS19: 1 mês de contabilidade | FT19: =-'Investimento Inicial'!$C$10 -> -1000 | FW19: 1 mês de contabilidade | FX19: =-'Investimento Inicial'!$C$10 -> -1000 | GA19: 1 mês de contabilidade | GB19: =-'Investimento Inicial'!$C$10 -> -1000 | GE19: 1 mês de contabilidade | GF19: =-'Investimento Inicial'!$C$10 -> -1000 | GI19: 1 mês de contabilidade | GJ19: =-'Investimento Inicial'!$C$10 -> -1000 | GM19: 1 mês de contabilidade | GN19: =-'Investimento Inicial'!$C$10 -> -1000 | GQ19: 1 mês de contabilidade | GR19: =-'Investimento Inicial'!$C$10 -> -1000 | GU19: 1 mês de contabilidade | GV19: =-'Investimento Inicial'!$C$10 -> -1000 | GY19: 1 mês de contabilidade | GZ19: =-'Investimento Inicial'!$C$10 -> -1000 | HC19: 1 mês de contabilidade | HD19: =-'Investimento Inicial'!$C$10 -> -1000 | HG19: 1 mês de contabilidade | HH19: =-'Investimento Inicial'!$C$10 -> -1000 | HK19: 1 mês de contabilidade | HL19: =-'Investimento Inicial'!$C$10 -> -1000 | HO19: 1 mês de contabilidade | HP19: =-'Investimento Inicial'!$C$10 -> -1000 | HS19: 1 mês de contabilidade | HT19: =-'Investimento Inicial'!$C$10 -> -1000 | HW19: 1 mês de contabilidade | HX19: =-'Investimento Inicial'!$C$10 -> -1000 | IA19: 1 mês de contabilidade | IB19: =-'Investimento Inicial'!$C$10 -> -1000 | IE19: 1 mês de contabilidade | IF19: =-'Investimento Inicial'!$C$10 -> -1000 | II19: 1 mês de contabilidade | IJ19: =-'Investimento Inicial'!$C$10 -> -1000 | IM19: 1 mês de contabilidade | IN19: =-'Investimento Inicial'!$C$10 -> -1000 | IQ19: 1 mês de contabilidade | IR19: =-'Investimento Inicial'!$C$10 -> -1000 | IU19: 1 mês de contabilidade | IV19: =-'Investimento Inicial'!$C$10 -> -1000 | IY19: 1 mês de contabilidade | IZ19: =-'Investimento Inicial'!$C$10 -> -1000 | JC19: 1 mês de contabilidade | JD19: =-'Investimento Inicial'!$C$10 -> -1000 | JG19: 1 mês de contabilidade | JH19: =-'Investimento Inicial'!$C$10 -> -1000 | JK19: 1 mês de contabilidade | JL19: =-'Investimento Inicial'!$C$10 -> -1000 | JO19: 1 mês de contabilidade | JP19: =-'Investimento Inicial'!$C$10 -> -1000 | JS19: 1 mês de contabilidade | JT19: =-'Investimento Inicial'!$C$10 -> -1000 | JW19: 1 mês de contabilidade | JX19: =-'Investimento Inicial'!$C$10 -> -1000 | KA19: 1 mês de contabilidade | KB19: =-'Investimento Inicial'!$C$10 -> -1000 | KE19: 1 mês de contabilidade | KF19: =-'Investimento Inicial'!$C$10 -> -1000
C20: Água e luz | D20: -300 | G20: Água e luz | H20: -300 | K20: Água e luz | L20: -300 | O20: Água e luz | P20: -300 | S20: Água e luz | T20: -300 | W20: Água e luz | X20: -300 | AA20: Água e luz | AB20: -300 | AE20: Água e luz | AF20: -300 | AI20: Água e luz | AJ20: -300 | AM20: Água e luz | AN20: -300 | AQ20: Água e luz | AR20: -300 | AU20: Água e luz | AV20: -300 | AY20: Água e luz | AZ20: -300 | BC20: Água e luz | BD20: -300 | BG20: Água e luz | BH20: -300 | BK20: Água e luz | BL20: -300 | BO20: Água e luz | BP20: -300 | BS20: Água e luz | BT20: -300 | BW20: Água e luz | BX20: -300 | CA20: Água e luz | CB20: -300 | CE20: Água e luz | CF20: -300 | CI20: Água e luz | CJ20: -300 | CM20: Água e luz | CN20: -300 | CQ20: Água e luz | CR20: -300 | CU20: Água e luz | CV20: -300 | CY20: Água e luz | CZ20: -300 | DC20: Água e luz | DD20: -300 | DG20: Água e luz | DH20: -300 | DK20: Água e luz | DL20: -300 | DO20: Água e luz | DP20: -300 | DS20: Água e luz | DT20: -300 | DW20: Água e luz | DX20: -300 | EA20: Água e luz | EB20: -300 | EE20: Água e luz | EF20: -300 | EI20: Água e luz | EJ20: -300 | EM20: Água e luz | EN20: -300 | EQ20: Água e luz | ER20: -300 | EU20: Água e luz | EV20: -300 | EY20: Água e luz | EZ20: -300 | FC20: Água e luz | FD20: -300 | FG20: Água e luz | FH20: -300 | FK20: Água e luz | FL20: -300 | FO20: Água e luz | FP20: -300 | FS20: Água e luz | FT20: -300 | FW20: Água e luz | FX20: -300 | GA20: Água e luz | GB20: -300 | GE20: Água e luz | GF20: -300 | GI20: Água e luz | GJ20: -300 | GM20: Água e luz | GN20: -300 | GQ20: Água e luz | GR20: -300 | GU20: Água e luz | GV20: -300 | GY20: Água e luz | GZ20: -300 | HC20: Água e luz | HD20: -300 | HG20: Água e luz | HH20: -300 | HK20: Água e luz | HL20: -300 | HO20: Água e luz | HP20: -300 | HS20: Água e luz | HT20: -300 | HW20: Água e luz | HX20: -300 | IA20: Água e luz | IB20: -300 | IE20: Água e luz | IF20: -300 | II20: Água e luz | IJ20: -300 | IM20: Água e luz | IN20: -300 | IQ20: Água e luz | IR20: -300 | IU20: Água e luz | IV20: -300 | IY20: Água e luz | IZ20: -300 | JC20: Água e luz | JD20: -300 | JG20: Água e luz | JH20: -300 | JK20: Água e luz | JL20: -300 | JO20: Água e luz | JP20: -300 | JS20: Água e luz | JT20: -300 | JW20: Água e luz | JX20: -300 | KA20: Água e luz | KB20: -300 | KE20: Água e luz | KF20: -300
C21: Juros | D21: =-AVERAGE('Simulação Empréstimo'!$K$6:$K$11)/12 -> -1714.1957 | G21: Juros | H21: =-AVERAGE('Simulação Empréstimo'!$K$6:$K$11)/12 -> -1714.1957 | K21: Juros | L21: =-AVERAGE('Simulação Empréstimo'!$K$6:$K$11)/12 -> -1714.1957 | O21: Juros | P21: =-AVERAGE('Simulação Empréstimo'!$K$6:$K$11)/12 -> -1714.1957 | S21: Juros | T21: =-AVERAGE('Simulação Empréstimo'!$K$6:$K$11)/12 -> -1714.1957 | W21: Juros | X21: =-AVERAGE('Simulação Empréstimo'!$K$6:$K$11)/12 -> -1714.1957 | AA21: Juros | AB21: =-AVERAGE('Simulação Empréstimo'!$K$6:$K$11)/12 -> -1714.1957 | AE21: Juros | AF21: =-AVERAGE('Simulação Empréstimo'!$K$6:$K$11)/12 -> -1714.1957 | AI21: Juros | AJ21: =-AVERAGE('Simulação Empréstimo'!$K$6:$K$11)/12 -> -1714.1957 | AM21: Juros | AN21: =-AVERAGE('Simulação Empréstimo'!$K$6:$K$11)/12 -> -1714.1957 | AQ21: Juros | AR21: =-AVERAGE('Simulação Empréstimo'!$K$6:$K$11)/12 -> -1714.1957 | AU21: Juros | AV21: =-AVERAGE('Simulação Empréstimo'!$K$6:$K$11)/12 -> -1714.1957 | AY21: Juros | AZ21: =-AVERAGE('Simulação Empréstimo'!$K$6:$K$11)/12 -> -1714.1957 | BC21: Juros | BD21: =-AVERAGE('Simulação Empréstimo'!$K$6:$K$11)/12 -> -1714.1957 | BG21: Juros | BH21: =-AVERAGE('Simulação Empréstimo'!$K$6:$K$11)/12 -> -1714.1957 | BK21: Juros | BL21: =-AVERAGE('Simulação Empréstimo'!$K$6:$K$11)/12 -> -1714.1957 | BO21: Juros | BP21: =-AVERAGE('Simulação Empréstimo'!$K$6:$K$11)/12 -> -1714.1957 | BS21: Juros | BT21: =-AVERAGE('Simulação Empréstimo'!$K$6:$K$11)/12 -> -1714.1957 | BW21: Juros | BX21: =-AVERAGE('Simulação Empréstimo'!$K$6:$K$11)/12 -> -1714.1957 | CA21: Juros | CB21: =-AVERAGE('Simulação Empréstimo'!$K$6:$K$11)/12 -> -1714.1957 | CE21: Juros | CF21: =-AVERAGE('Simulação Empréstimo'!$K$6:$K$11)/12 -> -1714.1957 | CI21: Juros | CJ21: =-AVERAGE('Simulação Empréstimo'!$K$6:$K$11)/12 -> -1714.1957 | CM21: Juros | CN21: =-AVERAGE('Simulação Empréstimo'!$K$6:$K$11)/12 -> -1714.1957 | CQ21: Juros | CR21: =-AVERAGE('Simulação Empréstimo'!$K$6:$K$11)/12 -> -1714.1957 | CU21: Juros | CV21: =-AVERAGE('Simulação Empréstimo'!$K$6:$K$11)/12 -> -1714.1957 | CY21: Juros | CZ21: =-AVERAGE('Simulação Empréstimo'!$K$6:$K$11)/12 -> -1714.1957 | DC21: Juros | DD21: =-AVERAGE('Simulação Empréstimo'!$K$6:$K$11)/12 -> -1714.1957 | DG21: Juros | DH21: =-AVERAGE('Simulação Empréstimo'!$K$6:$K$11)/12 -> -1714.1957 | DK21: Juros | DL21: =-AVERAGE('Simulação Empréstimo'!$K$6:$K$11)/12 -> -1714.1957 | DO21: Juros | DP21: =-AVERAGE('Simulação Empréstimo'!$K$6:$K$11)/12 -> -1714.1957 | DS21: Juros | DT21: =-AVERAGE('Simulação Empréstimo'!$K$6:$K$11)/12 -> -1714.1957 | DW21: Juros | DX21: =-AVERAGE('Simulação Empréstimo'!$K$6:$K$11)/12 -> -1714.1957 | EA21: Juros | EB21: =-AVERAGE('Simulação Empréstimo'!$K$6:$K$11)/12 -> -1714.1957 | EE21: Juros | EF21: =-AVERAGE('Simulação Empréstimo'!$K$6:$K$11)/12 -> -1714.1957 | EI21: Juros | EJ21: =-AVERAGE('Simulação Empréstimo'!$K$6:$K$11)/12 -> -1714.1957 | EM21: Juros | EN21: =-AVERAGE('Simulação Empréstimo'!$K$6:$K$11)/12 -> -1714.1957 | EQ21: Juros | ER21: =-AVERAGE('Simulação Empréstimo'!$K$6:$K$11)/12 -> -1714.1957 | EU21: Juros | EV21: =-AVERAGE('Simulação Empréstimo'!$K$6:$K$11)/12 -> -1714.1957 | EY21: Juros | EZ21: =-AVERAGE('Simulação Empréstimo'!$K$6:$K$11)/12 -> -1714.1957 | FC21: Juros | FD21: =-AVERAGE('Simulação Empréstimo'!$K$6:$K$11)/12 -> -1714.1957 | FG21: Juros | FH21: =-AVERAGE('Simulação Empréstimo'!$K$6:$K$11)/12 -> -1714.1957 | FK21: Juros | FL21: =-AVERAGE('Simulação Empréstimo'!$K$6:$K$11)/12 -> -1714.1957 | FO21: Juros | FP21: =-AVERAGE('Simulação Empréstimo'!$K$6:$K$11)/12 -> -1714.1957 | FS21: Juros | FT21: =-AVERAGE('Simulação Empréstimo'!$K$6:$K$11)/12 -> -1714.1957 | FW21: Juros | FX21: =-AVERAGE('Simulação Empréstimo'!$K$6:$K$11)/12 -> -1714.1957 | GA21: Juros | GB21: =-AVERAGE('Simulação Empréstimo'!$K$6:$K$11)/12 -> -1714.1957 | GE21: Juros | GF21: =-AVERAGE('Simulação Empréstimo'!$K$6:$K$11)/12 -> -1714.1957 | GI21: Juros | GJ21: =-AVERAGE('Simulação Empréstimo'!$K$6:$K$11)/12 -> -1714.1957 | GM21: Juros | GN21: =-AVERAGE('Simulação Empréstimo'!$K$6:$K$11)/12 -> -1714.1957 | GQ21: Juros | GR21: =-AVERAGE('Simulação Empréstimo'!$K$6:$K$11)/12 -> -1714.1957 | GU21: Juros | GV21: =-AVERAGE('Simulação Empréstimo'!$K$6:$K$11)/12 -> -1714.1957 | GY21: Juros | GZ21: =-AVERAGE('Simulação Empréstimo'!$K$6:$K$11)/12 -> -1714.1957 | HC21: Juros | HD21: =-AVERAGE('Simulação Empréstimo'!$K$6:$K$11)/12 -> -1714.1957 | HG21: Juros | HH21: =-AVERAGE('Simulação Empréstimo'!$K$6:$K$11)/12 -> -1714.1957 | HK21: Juros | HL21: =-AVERAGE('Simulação Empréstimo'!$K$6:$K$11)/12 -> -1714.1957 | HO21: Juros | HP21: =-AVERAGE('Simulação Empréstimo'!$K$6:$K$11)/12 -> -1714.1957 | HS21: Juros | HT21: =-AVERAGE('Simulação Empréstimo'!$K$6:$K$11)/12 -> -1714.1957 | HW21: Juros | HX21: =-AVERAGE('Simulação Empréstimo'!$K$6:$K$11)/12 -> -1714.1957 | IA21: Juros | IB21: =-AVERAGE('Simulação Empréstimo'!$K$6:$K$11)/12 -> -1714.1957 | IE21: Juros | IF21: =-AVERAGE('Simulação Empréstimo'!$K$6:$K$11)/12 -> -1714.1957 | II21: Juros | IJ21: =-AVERAGE('Simulação Empréstimo'!$K$6:$K$11)/12 -> -1714.1957 | IM21: Juros | IN21: =-AVERAGE('Simulação Empréstimo'!$K$6:$K$11)/12 -> -1714.1957 | IQ21: Juros | IR21: =-AVERAGE('Simulação Empréstimo'!$K$6:$K$11)/12 -> -1714.1957 | IU21: Juros | IV21: =-AVERAGE('Simulação Empréstimo'!$K$6:$K$11)/12 -> -1714.1957 | IY21: Juros | IZ21: =-AVERAGE('Simulação Empréstimo'!$K$6:$K$11)/12 -> -1714.1957 | JC21: Juros | JD21: =-AVERAGE('Simulação Empréstimo'!$K$6:$K$11)/12 -> -1714.1957 | JG21: Juros | JH21: =-AVERAGE('Simulação Empréstimo'!$K$6:$K$11)/12 -> -1714.1957 | JK21: Juros | JL21: =-AVERAGE('Simulação Empréstimo'!$K$6:$K$11)/12 -> -1714.1957 | JO21: Juros | JP21: =-AVERAGE('Simulação Empréstimo'!$K$6:$K$11)/12 -> -1714.1957 | JS21: Juros | JT21: =-AVERAGE('Simulação Empréstimo'!$K$6:$K$11)/12 -> -1714.1957 | JW21: Juros | JX21: =-AVERAGE('Simulação Empréstimo'!$K$6:$K$11)/12 -> -1714.1957 | KA21: Juros | KB21: =-AVERAGE('Simulação Empréstimo'!$K$6:$K$11)/12 -> -1714.1957 | KE21: Juros | KF21: =-AVERAGE('Simulação Empréstimo'!$K$6:$K$11)/12 -> -1714.1957
C22: Impostos Simples | D22: =-E22*D$3 -> -1296 | E22: =VLOOKUP(SUM(OFFSET(D7, 0, -(MIN(12*4-1, COLUMN(D7)-1)), 1, MIN(12*4, COLUMN(D7)))), 'Tabela Simples'!$B$2:$C$7, 2, TRUE) -> 0.045 | G22: Impostos Simples | H22: =-I$22*H$3 -> -1296 | I22: =VLOOKUP(SUM(OFFSET(H7, 0, -(MIN(12*4-1, COLUMN(H7)-1)), 1, MIN(12*4, COLUMN(H7)))), 'Tabela Simples'!$B$2:$C$7, 2, TRUE) -> 0.045 | K22: Impostos Simples | L22: =-M$22*L$3 -> -1296 | M22: =VLOOKUP(SUM(OFFSET(L7, 0, -(MIN(12*4-1, COLUMN(L7)-1)), 1, MIN(12*4, COLUMN(L7)))), 'Tabela Simples'!$B$2:$C$7, 2, TRUE) -> 0.045 | O22: Impostos Simples | P22: =-Q$22*P$3 -> -1296 | Q22: =VLOOKUP(SUM(OFFSET(P7, 0, -(MIN(12*4-1, COLUMN(P7)-1)), 1, MIN(12*4, COLUMN(P7)))), 'Tabela Simples'!$B$2:$C$7, 2, TRUE) -> 0.045 | S22: Impostos Simples | T22: =-U$22*T$3 -> -1296 | U22: =VLOOKUP(SUM(OFFSET(T7, 0, -(MIN(12*4-1, COLUMN(T7)-1)), 1, MIN(12*4, COLUMN(T7)))), 'Tabela Simples'!$B$2:$C$7, 2, TRUE) -> 0.045 | W22: Impostos Simples | X22: =-Y$22*X$3 -> -1296 | Y22: =VLOOKUP(SUM(OFFSET(X7, 0, -(MIN(12*4-1, COLUMN(X7)-1)), 1, MIN(12*4, COLUMN(X7)))), 'Tabela Simples'!$B$2:$C$7, 2, TRUE) -> 0.045 | AA22: Impostos Simples | AB22: =-AC$22*AB$3 -> -2246.4 | AC22: =VLOOKUP(SUM(OFFSET(AB7, 0, -(MIN(12*4-1, COLUMN(AB7)-1)), 1, MIN(12*4, COLUMN(AB7)))), 'Tabela Simples'!$B$2:$C$7, 2, TRUE) -> 0.078 | AE22: Impostos Simples | AF22: =-AG$22*AF$3 -> -2995.2 | AG22: =VLOOKUP(SUM(OFFSET(AF7, 0, -(MIN(12*4-1, COLUMN(AF7)-1)), 1, MIN(12*4, COLUMN(AF7)))), 'Tabela Simples'!$B$2:$C$7, 2, TRUE) -> 0.078 | AI22: Impostos Simples | AJ22: =-AK$22*AJ$3 -> -2995.2 | AK22: =VLOOKUP(SUM(OFFSET(AJ7, 0, -(MIN(12*4-1, COLUMN(AJ7)-1)), 1, MIN(12*4, COLUMN(AJ7)))), 'Tabela Simples'!$B$2:$C$7, 2, TRUE) -> 0.078 | AM22: Impostos Simples | AN22: =-AO$22*AN$3 -> -2995.2 | AO22: =VLOOKUP(SUM(OFFSET(AN7, 0, -(MIN(12*4-1, COLUMN(AN7)-1)), 1, MIN(12*4, COLUMN(AN7)))), 'Tabela Simples'!$B$2:$C$7, 2, TRUE) -> 0.078 | AQ22: Impostos Simples | AR22: =-AS$22*AR$3 -> -2995.2 | AS22: =VLOOKUP(SUM(OFFSET(AR7, 0, -(MIN(12*4-1, COLUMN(AR7)-1)), 1, MIN(12*4, COLUMN(AR7)))), 'Tabela Simples'!$B$2:$C$7, 2, TRUE) -> 0.078 | AU22: Impostos Simples | AV22: =-AW$22*AV$3 -> -3840 | AW22: =VLOOKUP(SUM(OFFSET(AV7, 0, -(MIN(12*4-1, COLUMN(AV7)-1)), 1, MIN(12*4, COLUMN(AV7)))), 'Tabela Simples'!$B$2:$C$7, 2, TRUE) -> 0.1 | AY22: Impostos Simples | AZ22: =-BA$22*AZ$3 -> -3840 | BA22: =VLOOKUP(SUM(OFFSET(AZ7, 0, -(MIN(12*4-1, COLUMN(AZ7)-1)), 1, MIN(12*4, COLUMN(AZ7)))), 'Tabela Simples'!$B$2:$C$7, 2, TRUE) -> 0.1 | BC22: Impostos Simples | BD22: =-BE$22*BD$3 -> -3840 | BE22: =VLOOKUP(SUM(OFFSET(BD7, 0, -(MIN(12*4-1, COLUMN(BD7)-1)), 1, MIN(12*4, COLUMN(BD7)))), 'Tabela Simples'!$B$2:$C$7, 2, TRUE) -> 0.1 | BG22: Impostos Simples | BH22: =-BI$22*BH$3 -> -4800 | BI22: =VLOOKUP(SUM(OFFSET(BH7, 0, -(MIN(12*4-1, COLUMN(BH7)-1)), 1, MIN(12*4, COLUMN(BH7)))), 'Tabela Simples'!$B$2:$C$7, 2, TRUE) -> 0.1 | BK22: Impostos Simples | BL22: =-BM$22*BL$3 -> -4800 | BM22: =VLOOKUP(SUM(OFFSET(BL7, 0, -(MIN(12*4-1, COLUMN(BL7)-1)), 1, MIN(12*4, COLUMN(BL7)))), 'Tabela Simples'!$B$2:$C$7, 2, TRUE) -> 0.1 | BO22: Impostos Simples | BP22: =-BQ$22*BP$3 -> -4800 | BQ22: =VLOOKUP(SUM(OFFSET(BP7, 0, -(MIN(12*4-1, COLUMN(BP7)-1)), 1, MIN(12*4, COLUMN(BP7)))), 'Tabela Simples'!$B$2:$C$7, 2, TRUE) -> 0.1 | BS22: Impostos Simples | BT22: =-BU$22*BT$3 -> -4800 | BU22: =VLOOKUP(SUM(OFFSET(BT7, 0, -(MIN(12*4-1, COLUMN(BT7)-1)), 1, MIN(12*4, COLUMN(BT7)))), 'Tabela Simples'!$B$2:$C$7, 2, TRUE) -> 0.1 | BW22: Impostos Simples | BX22: =-BY$22*BX$3 -> -4800 | BY22: =VLOOKUP(SUM(OFFSET(BX7, 0, -(MIN(12*4-1, COLUMN(BX7)-1)), 1, MIN(12*4, COLUMN(BX7)))), 'Tabela Simples'!$B$2:$C$7, 2, TRUE) -> 0.1 | CA22: Impostos Simples | CB22: =-CC$22*CB$3 -> -4800 | CC22: =VLOOKUP(SUM(OFFSET(CB7, 0, -(MIN(12*4-1, COLUMN(CB7)-1)), 1, MIN(12*4, COLUMN(CB7)))), 'Tabela Simples'!$B$2:$C$7, 2, TRUE) -> 0.1 | CE22: Impostos Simples | CF22: =-CG$22*CF$3 -> -5760 | CG22: =VLOOKUP(SUM(OFFSET(CF7, 0, -(MIN(12*4-1, COLUMN(CF7)-1)), 1, MIN(12*4, COLUMN(CF7)))), 'Tabela Simples'!$B$2:$C$7, 2, TRUE) -> 0.1 | CI22: Impostos Simples | CJ22: =-CK$22*CJ$3 -> -5760 | CK22: =VLOOKUP(SUM(OFFSET(CJ7, 0, -(MIN(12*4-1, COLUMN(CJ7)-1)), 1, MIN(12*4, COLUMN(CJ7)))), 'Tabela Simples'!$B$2:$C$7, 2, TRUE) -> 0.1 | CM22: Impostos Simples | CN22: =-CO$22*CN$3 -> -5760 | CO22: =VLOOKUP(SUM(OFFSET(CN7, 0, -(MIN(12*4-1, COLUMN(CN7)-1)), 1, MIN(12*4, COLUMN(CN7)))), 'Tabela Simples'!$B$2:$C$7, 2, TRUE) -> 0.1 | CQ22: Impostos Simples | CR22: =-CS$22*CR$3 -> -5760 | CS22: =VLOOKUP(SUM(OFFSET(CR7, 0, -(MIN(12*4-1, COLUMN(CR7)-1)), 1, MIN(12*4, COLUMN(CR7)))), 'Tabela Simples'!$B$2:$C$7, 2, TRUE) -> 0.1 | CU22: Impostos Simples | CV22: =-CW$22*CV$3 -> -5760 | CW22: =VLOOKUP(SUM(OFFSET(CV7, 0, -(MIN(12*4-1, COLUMN(CV7)-1)), 1, MIN(12*4, COLUMN(CV7)))), 'Tabela Simples'!$B$2:$C$7, 2, TRUE) -> 0.1 | CY22: Impostos Simples | CZ22: =-DA$22*CZ$3 -> -5760 | DA22: =VLOOKUP(SUM(OFFSET(CZ7, 0, -(MIN(12*4-1, COLUMN(CZ7)-1)), 1, MIN(12*4, COLUMN(CZ7)))), 'Tabela Simples'!$B$2:$C$7, 2, TRUE) -> 0.1 | DC22: Impostos Simples | DD22: =-DE$22*DD$3 -> -5760 | DE22: =VLOOKUP(SUM(OFFSET(DD7, 0, -(MIN(12*4-1, COLUMN(DD7)-1)), 1, MIN(12*4, COLUMN(DD7)))), 'Tabela Simples'!$B$2:$C$7, 2, TRUE) -> 0.1 | DG22: Impostos Simples | DH22: =-DI$22*DH$3 -> -6720 | DI22: =VLOOKUP(SUM(OFFSET(DH7, 0, -(MIN(12*4-1, COLUMN(DH7)-1)), 1, MIN(12*4, COLUMN(DH7)))), 'Tabela Simples'!$B$2:$C$7, 2, TRUE) -> 0.1 | DK22: Impostos Simples | DL22: =-DM$22*DL$3 -> -6720 | DM22: =VLOOKUP(SUM(OFFSET(DL7, 0, -(MIN(12*4-1, COLUMN(DL7)-1)), 1, MIN(12*4, COLUMN(DL7)))), 'Tabela Simples'!$B$2:$C$7, 2, TRUE) -> 0.1 | DO22: Impostos Simples | DP22: =-DQ$22*DP$3 -> -6720 | DQ22: =VLOOKUP(SUM(OFFSET(DP7, 0, -(MIN(12*4-1, COLUMN(DP7)-1)), 1, MIN(12*4, COLUMN(DP7)))), 'Tabela Simples'!$B$2:$C$7, 2, TRUE) -> 0.1 | DS22: Impostos Simples | DT22: =-DU$22*DT$3 -> -6720 | DU22: =VLOOKUP(SUM(OFFSET(DT7, 0, -(MIN(12*4-1, COLUMN(DT7)-1)), 1, MIN(12*4, COLUMN(DT7)))), 'Tabela Simples'!$B$2:$C$7, 2, TRUE) -> 0.1 | DW22: Impostos Simples | DX22: =-DY$22*DX$3 -> -7526.4 | DY22: =VLOOKUP(SUM(OFFSET(DX7, 0, -(MIN(12*4-1, COLUMN(DX7)-1)), 1, MIN(12*4, COLUMN(DX7)))), 'Tabela Simples'!$B$2:$C$7, 2, TRUE) -> 0.112 | EA22: Impostos Simples | EB22: =-EC$22*EB$3 -> -7526.4 | EC22: =VLOOKUP(SUM(OFFSET(EB7, 0, -(MIN(12*4-1, COLUMN(EB7)-1)), 1, MIN(12*4, COLUMN(EB7)))), 'Tabela Simples'!$B$2:$C$7, 2, TRUE) -> 0.112 | EE22: Impostos Simples | EF22: =-EG$22*EF$3 -> -7526.4 | EG22: =VLOOKUP(SUM(OFFSET(EF7, 0, -(MIN(12*4-1, COLUMN(EF7)-1)), 1, MIN(12*4, COLUMN(EF7)))), 'Tabela Simples'!$B$2:$C$7, 2, TRUE) -> 0.112 | EI22: Impostos Simples | EJ22: =-EK$22*EJ$3 -> -8601.6 | EK22: =VLOOKUP(SUM(OFFSET(EJ7, 0, -(MIN(12*4-1, COLUMN(EJ7)-1)), 1, MIN(12*4, COLUMN(EJ7)))), 'Tabela Simples'!$B$2:$C$7, 2, TRUE) -> 0.112 | EM22: Impostos Simples | EN22: =-EO$22*EN$3 -> -8601.6 | EO22: =VLOOKUP(SUM(OFFSET(EN7, 0, -(MIN(12*4-1, COLUMN(EN7)-1)), 1, MIN(12*4, COLUMN(EN7)))), 'Tabela Simples'!$B$2:$C$7, 2, TRUE) -> 0.112 | EQ22: Impostos Simples | ER22: =-ES$22*ER$3 -> -8601.6 | ES22: =VLOOKUP(SUM(OFFSET(ER7, 0, -(MIN(12*4-1, COLUMN(ER7)-1)), 1, MIN(12*4, COLUMN(ER7)))), 'Tabela Simples'!$B$2:$C$7, 2, TRUE) -> 0.112 | EU22: Impostos Simples | EV22: =-EW$22*EV$3 -> -8601.6 | EW22: =VLOOKUP(SUM(OFFSET(EV7, 0, -(MIN(12*4-1, COLUMN(EV7)-1)), 1, MIN(12*4, COLUMN(EV7)))), 'Tabela Simples'!$B$2:$C$7, 2, TRUE) -> 0.112 | EY22: Impostos Simples | EZ22: =-FA$22*EZ$3 -> -8601.6 | FA22: =VLOOKUP(SUM(OFFSET(EZ7, 0, -(MIN(12*4-1, COLUMN(EZ7)-1)), 1, MIN(12*4, COLUMN(EZ7)))), 'Tabela Simples'!$B$2:$C$7, 2, TRUE) -> 0.112 | FC22: Impostos Simples | FD22: =-FE$22*FD$3 -> -8601.6 | FE22: =VLOOKUP(SUM(OFFSET(FD7, 0, -(MIN(12*4-1, COLUMN(FD7)-1)), 1, MIN(12*4, COLUMN(FD7)))), 'Tabela Simples'!$B$2:$C$7, 2, TRUE) -> 0.112 | FG22: Impostos Simples | FH22: =-FI$22*FH$3 -> -9676.8 | FI22: =VLOOKUP(SUM(OFFSET(FH7, 0, -(MIN(12*4-1, COLUMN(FH7)-1)), 1, MIN(12*4, COLUMN(FH7)))), 'Tabela Simples'!$B$2:$C$7, 2, TRUE) -> 0.112 | FK22: Impostos Simples | FL22: =-FM$22*FL$3 -> -9676.8 | FM22: =VLOOKUP(SUM(OFFSET(FL7, 0, -(MIN(12*4-1, COLUMN(FL7)-1)), 1, MIN(12*4, COLUMN(FL7)))), 'Tabela Simples'!$B$2:$C$7, 2, TRUE) -> 0.112 | FO22: Impostos Simples | FP22: =-FQ$22*FP$3 -> -9676.8 | FQ22: =VLOOKUP(SUM(OFFSET(FP7, 0, -(MIN(12*4-1, COLUMN(FP7)-1)), 1, MIN(12*4, COLUMN(FP7)))), 'Tabela Simples'!$B$2:$C$7, 2, TRUE) -> 0.112 | FS22: Impostos Simples | FT22: =-FU$22*FT$3 -> -9676.8 | FU22: =VLOOKUP(SUM(OFFSET(FT7, 0, -(MIN(12*4-1, COLUMN(FT7)-1)), 1, MIN(12*4, COLUMN(FT7)))), 'Tabela Simples'!$B$2:$C$7, 2, TRUE) -> 0.112 | FW22: Impostos Simples | FX22: =-FY$22*FX$3 -> -9676.8 | FY22: =VLOOKUP(SUM(OFFSET(FX7, 0, -(MIN(12*4-1, COLUMN(FX7)-1)), 1, MIN(12*4, COLUMN(FX7)))), 'Tabela Simples'!$B$2:$C$7, 2, TRUE) -> 0.112 | GA22: Impostos Simples | GB22: =-GC$22*GB$3 -> -9676.8 | GC22: =VLOOKUP(SUM(OFFSET(GB7, 0, -(MIN(12*4-1, COLUMN(GB7)-1)), 1, MIN(12*4, COLUMN(GB7)))), 'Tabela Simples'!$B$2:$C$7, 2, TRUE) -> 0.112 | GE22: Impostos Simples | GF22: =-GG$22*GF$3 -> -9676.8 | GG22: =VLOOKUP(SUM(OFFSET(GF7, 0, -(MIN(12*4-1, COLUMN(GF7)-1)), 1, MIN(12*4, COLUMN(GF7)))), 'Tabela Simples'!$B$2:$C$7, 2, TRUE) -> 0.112 | GI22: Impostos Simples | GJ22: =-GK$22*GJ$3 -> -10752 | GK22: =VLOOKUP(SUM(OFFSET(GJ7, 0, -(MIN(12*4-1, COLUMN(GJ7)-1)), 1, MIN(12*4, COLUMN(GJ7)))), 'Tabela Simples'!$B$2:$C$7, 2, TRUE) -> 0.112 | GM22: Impostos Simples | GN22: =-GO$22*GN$3 -> -10752 | GO22: =VLOOKUP(SUM(OFFSET(GN7, 0, -(MIN(12*4-1, COLUMN(GN7)-1)), 1, MIN(12*4, COLUMN(GN7)))), 'Tabela Simples'!$B$2:$C$7, 2, TRUE) -> 0.112 | GQ22: Impostos Simples | GR22: =-GS$22*GR$3 -> -10752 | GS22: =VLOOKUP(SUM(OFFSET(GR7, 0, -(MIN(12*4-1, COLUMN(GR7)-1)), 1, MIN(12*4, COLUMN(GR7)))), 'Tabela Simples'!$B$2:$C$7, 2, TRUE) -> 0.112 | GU22: Impostos Simples | GV22: =-GW$22*GV$3 -> -10752 | GW22: =VLOOKUP(SUM(OFFSET(GV7, 0, -(MIN(12*4-1, COLUMN(GV7)-1)), 1, MIN(12*4, COLUMN(GV7)))), 'Tabela Simples'!$B$2:$C$7, 2, TRUE) -> 0.112 | GY22: Impostos Simples | GZ22: =-HA$22*GZ$3 -> -10752 | HA22: =VLOOKUP(SUM(OFFSET(GZ7, 0, -(MIN(12*4-1, COLUMN(GZ7)-1)), 1, MIN(12*4, COLUMN(GZ7)))), 'Tabela Simples'!$B$2:$C$7, 2, TRUE) -> 0.112 | HC22: Impostos Simples | HD22: =-HE$22*HD$3 -> -10752 | HE22: =VLOOKUP(SUM(OFFSET(HD7, 0, -(MIN(12*4-1, COLUMN(HD7)-1)), 1, MIN(12*4, COLUMN(HD7)))), 'Tabela Simples'!$B$2:$C$7, 2, TRUE) -> 0.112 | HG22: Impostos Simples | HH22: =-HI$22*HH$3 -> -10752 | HI22: =VLOOKUP(SUM(OFFSET(HH7, 0, -(MIN(12*4-1, COLUMN(HH7)-1)), 1, MIN(12*4, COLUMN(HH7)))), 'Tabela Simples'!$B$2:$C$7, 2, TRUE) -> 0.112 | HK22: Impostos Simples | HL22: =-HM$22*HL$3 -> -11827.2 | HM22: =VLOOKUP(SUM(OFFSET(HL7, 0, -(MIN(12*4-1, COLUMN(HL7)-1)), 1, MIN(12*4, COLUMN(HL7)))), 'Tabela Simples'!$B$2:$C$7, 2, TRUE) -> 0.112 | HO22: Impostos Simples | HP22: =-HQ$22*HP$3 -> -11827.2 | HQ22: =VLOOKUP(SUM(OFFSET(HP7, 0, -(MIN(12*4-1, COLUMN(HP7)-1)), 1, MIN(12*4, COLUMN(HP7)))), 'Tabela Simples'!$B$2:$C$7, 2, TRUE) -> 0.112 | HS22: Impostos Simples | HT22: =-HU$22*HT$3 -> -11827.2 | HU22: =VLOOKUP(SUM(OFFSET(HT7, 0, -(MIN(12*4-1, COLUMN(HT7)-1)), 1, MIN(12*4, COLUMN(HT7)))), 'Tabela Simples'!$B$2:$C$7, 2, TRUE) -> 0.112 | HW22: Impostos Simples | HX22: =-HY$22*HX$3 -> -11827.2 | HY22: =VLOOKUP(SUM(OFFSET(HX7, 0, -(MIN(12*4-1, COLUMN(HX7)-1)), 1, MIN(12*4, COLUMN(HX7)))), 'Tabela Simples'!$B$2:$C$7, 2, TRUE) -> 0.112 | IA22: Impostos Simples | IB22: =-IC$22*IB$3 -> -11827.2 | IC22: =VLOOKUP(SUM(OFFSET(IB7, 0, -(MIN(12*4-1, COLUMN(IB7)-1)), 1, MIN(12*4, COLUMN(IB7)))), 'Tabela Simples'!$B$2:$C$7, 2, TRUE) -> 0.112 | IE22: Impostos Simples | IF22: =-IG$22*IF$3 -> -11827.2 | IG22: =VLOOKUP(SUM(OFFSET(IF7, 0, -(MIN(12*4-1, COLUMN(IF7)-1)), 1, MIN(12*4, COLUMN(IF7)))), 'Tabela Simples'!$B$2:$C$7, 2, TRUE) -> 0.112 | II22: Impostos Simples | IJ22: =-IK$22*IJ$3 -> -12902.4 | IK22: =VLOOKUP(SUM(OFFSET(IJ7, 0, -(MIN(12*4-1, COLUMN(IJ7)-1)), 1, MIN(12*4, COLUMN(IJ7)))), 'Tabela Simples'!$B$2:$C$7, 2, TRUE) -> 0.112 | IM22: Impostos Simples | IN22: =-IO$22*IN$3 -> -12902.4 | IO22: =VLOOKUP(SUM(OFFSET(IN7, 0, -(MIN(12*4-1, COLUMN(IN7)-1)), 1, MIN(12*4, COLUMN(IN7)))), 'Tabela Simples'!$B$2:$C$7, 2, TRUE) -> 0.112 | IQ22: Impostos Simples | IR22: =-IS$22*IR$3 -> -12902.4 | IS22: =VLOOKUP(SUM(OFFSET(IR7, 0, -(MIN(12*4-1, COLUMN(IR7)-1)), 1, MIN(12*4, COLUMN(IR7)))), 'Tabela Simples'!$B$2:$C$7, 2, TRUE) -> 0.112 | IU22: Impostos Simples | IV22: =-IW$22*IV$3 -> -12902.4 | IW22: =VLOOKUP(SUM(OFFSET(IV7, 0, -(MIN(12*4-1, COLUMN(IV7)-1)), 1, MIN(12*4, COLUMN(IV7)))), 'Tabela Simples'!$B$2:$C$7, 2, TRUE) -> 0.112 | IY22: Impostos Simples | IZ22: =-JA$22*IZ$3 -> -12902.4 | JA22: =VLOOKUP(SUM(OFFSET(IZ7, 0, -(MIN(12*4-1, COLUMN(IZ7)-1)), 1, MIN(12*4, COLUMN(IZ7)))), 'Tabela Simples'!$B$2:$C$7, 2, TRUE) -> 0.112 | JC22: Impostos Simples | JD22: =-JE$22*JD$3 -> -12902.4 | JE22: =VLOOKUP(SUM(OFFSET(JD7, 0, -(MIN(12*4-1, COLUMN(JD7)-1)), 1, MIN(12*4, COLUMN(JD7)))), 'Tabela Simples'!$B$2:$C$7, 2, TRUE) -> 0.112 | JG22: Impostos Simples | JH22: =-JI$22*JH$3 -> -12902.4 | JI22: =VLOOKUP(SUM(OFFSET(JH7, 0, -(MIN(12*4-1, COLUMN(JH7)-1)), 1, MIN(12*4, COLUMN(JH7)))), 'Tabela Simples'!$B$2:$C$7, 2, TRUE) -> 0.112 | JK22: Impostos Simples | JL22: =-JM$22*JL$3 -> -13977.6 | JM22: =VLOOKUP(SUM(OFFSET(JL7, 0, -(MIN(12*4-1, COLUMN(JL7)-1)), 1, MIN(12*4, COLUMN(JL7)))), 'Tabela Simples'!$B$2:$C$7, 2, TRUE) -> 0.112 | JO22: Impostos Simples | JP22: =-JQ$22*JP$3 -> -13977.6 | JQ22: =VLOOKUP(SUM(OFFSET(JP7, 0, -(MIN(12*4-1, COLUMN(JP7)-1)), 1, MIN(12*4, COLUMN(JP7)))), 'Tabela Simples'!$B$2:$C$7, 2, TRUE) -> 0.112 | JS22: Impostos Simples | JT22: =-JU$22*JT$3 -> -13977.6 | JU22: =VLOOKUP(SUM(OFFSET(JT7, 0, -(MIN(12*4-1, COLUMN(JT7)-1)), 1, MIN(12*4, COLUMN(JT7)))), 'Tabela Simples'!$B$2:$C$7, 2, TRUE) -> 0.112 | JW22: Impostos Simples | JX22: =-JY$22*JX$3 -> -13977.6 | JY22: =VLOOKUP(SUM(OFFSET(JX7, 0, -(MIN(12*4-1, COLUMN(JX7)-1)), 1, MIN(12*4, COLUMN(JX7)))), 'Tabela Simples'!$B$2:$C$7, 2, TRUE) -> 0.112 | KA22: Impostos Simples | KB22: =-KC$22*KB$3 -> -13977.6 | KC22: =VLOOKUP(SUM(OFFSET(KB7, 0, -(MIN(12*4-1, COLUMN(KB7)-1)), 1, MIN(12*4, COLUMN(KB7)))), 'Tabela Simples'!$B$2:$C$7, 2, TRUE) -> 0.112 | KE22: Impostos Simples | KF22: =-KG$22*KF$3 -> -13977.6 | KG22: =VLOOKUP(SUM(OFFSET(KF7, 0, -(MIN(12*4-1, COLUMN(KF7)-1)), 1, MIN(12*4, COLUMN(KF7)))), 'Tabela Simples'!$B$2:$C$7, 2, TRUE) -> 0.112
C23: Pacotes | D23: =-E$23*(D$4*60)/0.25 -> -2880 | E23: 4 | G23: Pacotes | H23: =-I$23*(H$4*60)/0.25 -> -2880 | I23: 4 | K23: Pacotes | L23: =-M$23*(L$4*60)/0.25 -> -2880 | M23: 4 | O23: Pacotes | P23: =-Q$23*(P$4*60)/0.25 -> -2880 | Q23: 4 | S23: Pacotes | T23: =-U$23*(T$4*60)/0.25 -> -2880 | U23: 4 | W23: Pacotes | X23: =-Y$23*(X$4*60)/0.25 -> -2880 | Y23: 4 | AA23: Pacotes | AB23: =-AC$23*(AB$4*60)/0.25 -> -2880 | AC23: 4 | AE23: Pacotes | AF23: =-AG$23*(AF$4*60)/0.25 -> -3840 | AG23: 4 | AI23: Pacotes | AJ23: =-AK$23*(AJ$4*60)/0.25 -> -3840 | AK23: 4 | AM23: Pacotes | AN23: =-AO$23*(AN$4*60)/0.25 -> -3840 | AO23: 4 | AQ23: Pacotes | AR23: =-AS$23*(AR$4*60)/0.25 -> -3840 | AS23: 4 | AU23: Pacotes | AV23: =-AW$23*(AV$4*60)/0.25 -> -3840 | AW23: 4 | AY23: Pacotes | AZ23: =-BA$23*(AZ$4*60)/0.25 -> -3840 | BA23: 4 | BC23: Pacotes | BD23: =-BE$23*(BD$4*60)/0.25 -> -3840 | BE23: 4 | BG23: Pacotes | BH23: =-BI$23*(BH$4*60)/0.25 -> -4800 | BI23: 4 | BK23: Pacotes | BL23: =-BM$23*(BL$4*60)/0.25 -> -4800 | BM23: 4 | BO23: Pacotes | BP23: =-BQ$23*(BP$4*60)/0.25 -> -4800 | BQ23: 4 | BS23: Pacotes | BT23: =-BU$23*(BT$4*60)/0.25 -> -4800 | BU23: 4 | BW23: Pacotes | BX23: =-BY$23*(BX$4*60)/0.25 -> -4800 | BY23: 4 | CA23: Pacotes | CB23: =-CC$23*(CB$4*60)/0.25 -> -4800 | CC23: 4 | CE23: Pacotes | CF23: =-CG$23*(CF$4*60)/0.25 -> -5760 | CG23: 4 | CI23: Pacotes | CJ23: =-CK$23*(CJ$4*60)/0.25 -> -5760 | CK23: 4 | CM23: Pacotes | CN23: =-CO$23*(CN$4*60)/0.25 -> -5760 | CO23: 4 | CQ23: Pacotes | CR23: =-CS$23*(CR$4*60)/0.25 -> -5760 | CS23: 4 | CU23: Pacotes | CV23: =-CW$23*(CV$4*60)/0.25 -> -5760 | CW23: 4 | CY23: Pacotes | CZ23: =-DA$23*(CZ$4*60)/0.25 -> -5760 | DA23: 4 | DC23: Pacotes | DD23: =-DE$23*(DD$4*60)/0.25 -> -5760 | DE23: 4 | DG23: Pacotes | DH23: =-DI$23*(DH$4*60)/0.25 -> -6720 | DI23: 4 | DK23: Pacotes | DL23: =-DM$23*(DL$4*60)/0.25 -> -6720 | DM23: 4 | DO23: Pacotes | DP23: =-DQ$23*(DP$4*60)/0.25 -> -6720 | DQ23: 4 | DS23: Pacotes | DT23: =-DU$23*(DT$4*60)/0.25 -> -6720 | DU23: 4 | DW23: Pacotes | DX23: =-DY$23*(DX$4*60)/0.25 -> -6720 | DY23: 4 | EA23: Pacotes | EB23: =-EC$23*(EB$4*60)/0.25 -> -6720 | EC23: 4 | EE23: Pacotes | EF23: =-EG$23*(EF$4*60)/0.25 -> -6720 | EG23: 4 | EI23: Pacotes | EJ23: =-EK$23*(EJ$4*60)/0.25 -> -7680 | EK23: 4 | EM23: Pacotes | EN23: =-EO$23*(EN$4*60)/0.25 -> -7680 | EO23: 4 | EQ23: Pacotes | ER23: =-ES$23*(ER$4*60)/0.25 -> -7680 | ES23: 4 | EU23: Pacotes | EV23: =-EW$23*(EV$4*60)/0.25 -> -7680 | EW23: 4 | EY23: Pacotes | EZ23: =-FA$23*(EZ$4*60)/0.25 -> -7680 | FA23: 4 | FC23: Pacotes | FD23: =-FE$23*(FD$4*60)/0.25 -> -7680 | FE23: 4 | FG23: Pacotes | FH23: =-FI$23*(FH$4*60)/0.25 -> -8640 | FI23: 4 | FK23: Pacotes | FL23: =-FM$23*(FL$4*60)/0.25 -> -8640 | FM23: 4 | FO23: Pacotes | FP23: =-FQ$23*(FP$4*60)/0.25 -> -8640 | FQ23: 4 | FS23: Pacotes | FT23: =-FU$23*(FT$4*60)/0.25 -> -8640 | FU23: 4 | FW23: Pacotes | FX23: =-FY$23*(FX$4*60)/0.25 -> -8640 | FY23: 4 | GA23: Pacotes | GB23: =-GC$23*(GB$4*60)/0.25 -> -8640 | GC23: 4 | GE23: Pacotes | GF23: =-GG$23*(GF$4*60)/0.25 -> -8640 | GG23: 4 | GI23: Pacotes | GJ23: =-GK$23*(GJ$4*60)/0.25 -> -9600 | GK23: 4 | GM23: Pacotes | GN23: =-GO$23*(GN$4*60)/0.25 -> -9600 | GO23: 4 | GQ23: Pacotes | GR23: =-GS$23*(GR$4*60)/0.25 -> -9600 | GS23: 4 | GU23: Pacotes | GV23: =-GW$23*(GV$4*60)/0.25 -> -9600 | GW23: 4 | GY23: Pacotes | GZ23: =-HA$23*(GZ$4*60)/0.25 -> -9600 | HA23: 4 | HC23: Pacotes | HD23: =-HE$23*(HD$4*60)/0.25 -> -9600 | HE23: 4 | HG23: Pacotes | HH23: =-HI$23*(HH$4*60)/0.25 -> -9600 | HI23: 4 | HK23: Pacotes | HL23: =-HM$23*(HL$4*60)/0.25 -> -10560 | HM23: 4 | HO23: Pacotes | HP23: =-HQ$23*(HP$4*60)/0.25 -> -10560 | HQ23: 4 | HS23: Pacotes | HT23: =-HU$23*(HT$4*60)/0.25 -> -10560 | HU23: 4 | HW23: Pacotes | HX23: =-HY$23*(HX$4*60)/0.25 -> -10560 | HY23: 4 | IA23: Pacotes | IB23: =-IC$23*(IB$4*60)/0.25 -> -10560 | IC23: 4 | IE23: Pacotes | IF23: =-IG$23*(IF$4*60)/0.25 -> -10560 | IG23: 4 | II23: Pacotes | IJ23: =-IK$23*(IJ$4*60)/0.25 -> -11520 | IK23: 4 | IM23: Pacotes | IN23: =-IO$23*(IN$4*60)/0.25 -> -11520 | IO23: 4 | IQ23: Pacotes | IR23: =-IS$23*(IR$4*60)/0.25 -> -11520 | IS23: 4 | IU23: Pacotes | IV23: =-IW$23*(IV$4*60)/0.25 -> -11520 | IW23: 4 | IY23: Pacotes | IZ23: =-JA$23*(IZ$4*60)/0.25 -> -11520 | JA23: 4 | JC23: Pacotes | JD23: =-JE$23*(JD$4*60)/0.25 -> -11520 | JE23: 4 | JG23: Pacotes | JH23: =-JI$23*(JH$4*60)/0.25 -> -11520 | JI23: 4 | JK23: Pacotes | JL23: =-JM$23*(JL$4*60)/0.25 -> -12480 | JM23: 4 | JO23: Pacotes | JP23: =-JQ$23*(JP$4*60)/0.25 -> -12480 | JQ23: 4 | JS23: Pacotes | JT23: =-JU$23*(JT$4*60)/0.25 -> -12480 | JU23: 4 | JW23: Pacotes | JX23: =-JY$23*(JX$4*60)/0.25 -> -12480 | JY23: 4 | KA23: Pacotes | KB23: =-KC$23*(KB$4*60)/0.25 -> -12480 | KC23: 4 | KE23: Pacotes | KF23: =-KG$23*(KF$4*60)/0.25 -> -12480 | KG23: 4
C24: Outros materiais | D24: =-E$24*D$4*$A$2 -> -465 | E24: 0.05 | G24: Outros materiais | H24: =-I$24*H$4*$A$2 -> -465 | I24: 0.05 | K24: Outros materiais | L24: =-M$24*L$4*$A$2 -> -465 | M24: 0.05 | O24: Outros materiais | P24: =-Q$24*P$4*$A$2 -> -465 | Q24: 0.05 | S24: Outros materiais | T24: =-U$24*T$4*$A$2 -> -465 | U24: 0.05 | W24: Outros materiais | X24: =-Y$24*X$4*$A$2 -> -465 | Y24: 0.05 | AA24: Outros materiais | AB24: =-AC$24*AB$4*$A$2 -> -465 | AC24: 0.05 | AE24: Outros materiais | AF24: =-AG$24*AF$4*$A$2 -> -620 | AG24: 0.05 | AI24: Outros materiais | AJ24: =-AK$24*AJ$4*$A$2 -> -620 | AK24: 0.05 | AM24: Outros materiais | AN24: =-AO$24*AN$4*$A$2 -> -620 | AO24: 0.05 | AQ24: Outros materiais | AR24: =-AS$24*AR$4*$A$2 -> -620 | AS24: 0.05 | AU24: Outros materiais | AV24: =-AW$24*AV$4*$A$2 -> -620 | AW24: 0.05 | AY24: Outros materiais | AZ24: =-BA$24*AZ$4*$A$2 -> -620 | BA24: 0.05 | BC24: Outros materiais | BD24: =-BE$24*BD$4*$A$2 -> -620 | BE24: 0.05 | BG24: Outros materiais | BH24: =-BI$24*BH$4*$A$2 -> -775 | BI24: 0.05 | BK24: Outros materiais | BL24: =-BM$24*BL$4*$A$2 -> -775 | BM24: 0.05 | BO24: Outros materiais | BP24: =-BQ$24*BP$4*$A$2 -> -775 | BQ24: 0.05 | BS24: Outros materiais | BT24: =-BU$24*BT$4*$A$2 -> -775 | BU24: 0.05 | BW24: Outros materiais | BX24: =-BY$24*BX$4*$A$2 -> -775 | BY24: 0.05 | CA24: Outros materiais | CB24: =-CC$24*CB$4*$A$2 -> -775 | CC24: 0.05 | CE24: Outros materiais | CF24: =-CG$24*CF$4*$A$2 -> -930 | CG24: 0.05 | CI24: Outros materiais | CJ24: =-CK$24*CJ$4*$A$2 -> -930 | CK24: 0.05 | CM24: Outros materiais | CN24: =-CO$24*CN$4*$A$2 -> -930 | CO24: 0.05 | CQ24: Outros materiais | CR24: =-CS$24*CR$4*$A$2 -> -930 | CS24: 0.05 | CU24: Outros materiais | CV24: =-CW$24*CV$4*$A$2 -> -930 | CW24: 0.05 | CY24: Outros materiais | CZ24: =-DA$24*CZ$4*$A$2 -> -930 | DA24: 0.05 | DC24: Outros materiais | DD24: =-DE$24*DD$4*$A$2 -> -930 | DE24: 0.05 | DG24: Outros materiais | DH24: =-DI$24*DH$4*$A$2 -> -1085 | DI24: 0.05 | DK24: Outros materiais | DL24: =-DM$24*DL$4*$A$2 -> -1085 | DM24: 0.05 | DO24: Outros materiais | DP24: =-DQ$24*DP$4*$A$2 -> -1085 | DQ24: 0.05 | DS24: Outros materiais | DT24: =-DU$24*DT$4*$A$2 -> -1085 | DU24: 0.05 | DW24: Outros materiais | DX24: =-DY$24*DX$4*$A$2 -> -1085 | DY24: 0.05 | EA24: Outros materiais | EB24: =-EC$24*EB$4*$A$2 -> -1085 | EC24: 0.05 | EE24: Outros materiais | EF24: =-EG$24*EF$4*$A$2 -> -1085 | EG24: 0.05 | EI24: Outros materiais | EJ24: =-EK$24*EJ$4*$A$2 -> -1240 | EK24: 0.05 | EM24: Outros materiais | EN24: =-EO$24*EN$4*$A$2 -> -1240 | EO24: 0.05 | EQ24: Outros materiais | ER24: =-ES$24*ER$4*$A$2 -> -1240 | ES24: 0.05 | EU24: Outros materiais | EV24: =-EW$24*EV$4*$A$2 -> -1240 | EW24: 0.05 | EY24: Outros materiais | EZ24: =-FA$24*EZ$4*$A$2 -> -1240 | FA24: 0.05 | FC24: Outros materiais | FD24: =-FE$24*FD$4*$A$2 -> -1240 | FE24: 0.05 | FG24: Outros materiais | FH24: =-FI$24*FH$4*$A$2 -> -1395 | FI24: 0.05 | FK24: Outros materiais | FL24: =-FM$24*FL$4*$A$2 -> -1395 | FM24: 0.05 | FO24: Outros materiais | FP24: =-FQ$24*FP$4*$A$2 -> -1395 | FQ24: 0.05 | FS24: Outros materiais | FT24: =-FU$24*FT$4*$A$2 -> -1395 | FU24: 0.05 | FW24: Outros materiais | FX24: =-FY$24*FX$4*$A$2 -> -1395 | FY24: 0.05 | GA24: Outros materiais | GB24: =-GC$24*GB$4*$A$2 -> -1395 | GC24: 0.05 | GE24: Outros materiais | GF24: =-GG$24*GF$4*$A$2 -> -1395 | GG24: 0.05 | GI24: Outros materiais | GJ24: =-GK$24*GJ$4*$A$2 -> -1550 | GK24: 0.05 | GM24: Outros materiais | GN24: =-GO$24*GN$4*$A$2 -> -1550 | GO24: 0.05 | GQ24: Outros materiais | GR24: =-GS$24*GR$4*$A$2 -> -1550 | GS24: 0.05 | GU24: Outros materiais | GV24: =-GW$24*GV$4*$A$2 -> -1550 | GW24: 0.05 | GY24: Outros materiais | GZ24: =-HA$24*GZ$4*$A$2 -> -1550 | HA24: 0.05 | HC24: Outros materiais | HD24: =-HE$24*HD$4*$A$2 -> -1550 | HE24: 0.05 | HG24: Outros materiais | HH24: =-HI$24*HH$4*$A$2 -> -1550 | HI24: 0.05 | HK24: Outros materiais | HL24: =-HM$24*HL$4*$A$2 -> -1705 | HM24: 0.05 | HO24: Outros materiais | HP24: =-HQ$24*HP$4*$A$2 -> -1705 | HQ24: 0.05 | HS24: Outros materiais | HT24: =-HU$24*HT$4*$A$2 -> -1705 | HU24: 0.05 | HW24: Outros materiais | HX24: =-HY$24*HX$4*$A$2 -> -1705 | HY24: 0.05 | IA24: Outros materiais | IB24: =-IC$24*IB$4*$A$2 -> -1705 | IC24: 0.05 | IE24: Outros materiais | IF24: =-IG$24*IF$4*$A$2 -> -1705 | IG24: 0.05 | II24: Outros materiais | IJ24: =-IK$24*IJ$4*$A$2 -> -1860 | IK24: 0.05 | IM24: Outros materiais | IN24: =-IO$24*IN$4*$A$2 -> -1860 | IO24: 0.05 | IQ24: Outros materiais | IR24: =-IS$24*IR$4*$A$2 -> -1860 | IS24: 0.05 | IU24: Outros materiais | IV24: =-IW$24*IV$4*$A$2 -> -1860 | IW24: 0.05 | IY24: Outros materiais | IZ24: =-JA$24*IZ$4*$A$2 -> -1860 | JA24: 0.05 | JC24: Outros materiais | JD24: =-JE$24*JD$4*$A$2 -> -1860 | JE24: 0.05 | JG24: Outros materiais | JH24: =-JI$24*JH$4*$A$2 -> -1860 | JI24: 0.05 | JK24: Outros materiais | JL24: =-JM$24*JL$4*$A$2 -> -2015 | JM24: 0.05 | JO24: Outros materiais | JP24: =-JQ$24*JP$4*$A$2 -> -2015 | JQ24: 0.05 | JS24: Outros materiais | JT24: =-JU$24*JT$4*$A$2 -> -2015 | JU24: 0.05 | JW24: Outros materiais | JX24: =-JY$24*JX$4*$A$2 -> -2015 | JY24: 0.05 | KA24: Outros materiais | KB24: =-KC$24*KB$4*$A$2 -> -2015 | KC24: 0.05 | KE24: Outros materiais | KF24: =-KG$24*KF$4*$A$2 -> -2015 | KG24: 0.05
C25: Perdas operacionais | D25: =-E$25*D$4*$A$2 -> -186 | E25: 0.02 | G25: Perdas operacionais | H25: =-I$25*H$4*$A$2 -> -186 | I25: 0.02 | K25: Perdas operacionais | L25: =-M$25*L$4*$A$2 -> -186 | M25: 0.02 | O25: Perdas operacionais | P25: =-Q$25*P$4*$A$2 -> -186 | Q25: 0.02 | S25: Perdas operacionais | T25: =-U$25*T$4*$A$2 -> -186 | U25: 0.02 | W25: Perdas operacionais | X25: =-Y$25*X$4*$A$2 -> -186 | Y25: 0.02 | AA25: Perdas operacionais | AB25: =-AC$25*AB$4*$A$2 -> -186 | AC25: 0.02 | AE25: Perdas operacionais | AF25: =-AG$25*AF$4*$A$2 -> -248 | AG25: 0.02 | AI25: Perdas operacionais | AJ25: =-AK$25*AJ$4*$A$2 -> -248 | AK25: 0.02 | AM25: Perdas operacionais | AN25: =-AO$25*AN$4*$A$2 -> -248 | AO25: 0.02 | AQ25: Perdas operacionais | AR25: =-AS$25*AR$4*$A$2 -> -248 | AS25: 0.02 | AU25: Perdas operacionais | AV25: =-AW$25*AV$4*$A$2 -> -248 | AW25: 0.02 | AY25: Perdas operacionais | AZ25: =-BA$25*AZ$4*$A$2 -> -248 | BA25: 0.02 | BC25: Perdas operacionais | BD25: =-BE$25*BD$4*$A$2 -> -248 | BE25: 0.02 | BG25: Perdas operacionais | BH25: =-BI$25*BH$4*$A$2 -> -310 | BI25: 0.02 | BK25: Perdas operacionais | BL25: =-BM$25*BL$4*$A$2 -> -310 | BM25: 0.02 | BO25: Perdas operacionais | BP25: =-BQ$25*BP$4*$A$2 -> -310 | BQ25: 0.02 | BS25: Perdas operacionais | BT25: =-BU$25*BT$4*$A$2 -> -310 | BU25: 0.02 | BW25: Perdas operacionais | BX25: =-BY$25*BX$4*$A$2 -> -310 | BY25: 0.02 | CA25: Perdas operacionais | CB25: =-CC$25*CB$4*$A$2 -> -310 | CC25: 0.02 | CE25: Perdas operacionais | CF25: =-CG$25*CF$4*$A$2 -> -372 | CG25: 0.02 | CI25: Perdas operacionais | CJ25: =-CK$25*CJ$4*$A$2 -> -372 | CK25: 0.02 | CM25: Perdas operacionais | CN25: =-CO$25*CN$4*$A$2 -> -372 | CO25: 0.02 | CQ25: Perdas operacionais | CR25: =-CS$25*CR$4*$A$2 -> -372 | CS25: 0.02 | CU25: Perdas operacionais | CV25: =-CW$25*CV$4*$A$2 -> -372 | CW25: 0.02 | CY25: Perdas operacionais | CZ25: =-DA$25*CZ$4*$A$2 -> -372 | DA25: 0.02 | DC25: Perdas operacionais | DD25: =-DE$25*DD$4*$A$2 -> -372 | DE25: 0.02 | DG25: Perdas operacionais | DH25: =-DI$25*DH$4*$A$2 -> -434 | DI25: 0.02 | DK25: Perdas operacionais | DL25: =-DM$25*DL$4*$A$2 -> -434 | DM25: 0.02 | DO25: Perdas operacionais | DP25: =-DQ$25*DP$4*$A$2 -> -434 | DQ25: 0.02 | DS25: Perdas operacionais | DT25: =-DU$25*DT$4*$A$2 -> -434 | DU25: 0.02 | DW25: Perdas operacionais | DX25: =-DY$25*DX$4*$A$2 -> -434 | DY25: 0.02 | EA25: Perdas operacionais | EB25: =-EC$25*EB$4*$A$2 -> -434 | EC25: 0.02 | EE25: Perdas operacionais | EF25: =-EG$25*EF$4*$A$2 -> -434 | EG25: 0.02 | EI25: Perdas operacionais | EJ25: =-EK$25*EJ$4*$A$2 -> -496 | EK25: 0.02 | EM25: Perdas operacionais | EN25: =-EO$25*EN$4*$A$2 -> -496 | EO25: 0.02 | EQ25: Perdas operacionais | ER25: =-ES$25*ER$4*$A$2 -> -496 | ES25: 0.02 | EU25: Perdas operacionais | EV25: =-EW$25*EV$4*$A$2 -> -496 | EW25: 0.02 | EY25: Perdas operacionais | EZ25: =-FA$25*EZ$4*$A$2 -> -496 | FA25: 0.02 | FC25: Perdas operacionais | FD25: =-FE$25*FD$4*$A$2 -> -496 | FE25: 0.02 | FG25: Perdas operacionais | FH25: =-FI$25*FH$4*$A$2 -> -558 | FI25: 0.02 | FK25: Perdas operacionais | FL25: =-FM$25*FL$4*$A$2 -> -558 | FM25: 0.02 | FO25: Perdas operacionais | FP25: =-FQ$25*FP$4*$A$2 -> -558 | FQ25: 0.02 | FS25: Perdas operacionais | FT25: =-FU$25*FT$4*$A$2 -> -558 | FU25: 0.02 | FW25: Perdas operacionais | FX25: =-FY$25*FX$4*$A$2 -> -558 | FY25: 0.02 | GA25: Perdas operacionais | GB25: =-GC$25*GB$4*$A$2 -> -558 | GC25: 0.02 | GE25: Perdas operacionais | GF25: =-GG$25*GF$4*$A$2 -> -558 | GG25: 0.02 | GI25: Perdas operacionais | GJ25: =-GK$25*GJ$4*$A$2 -> -620 | GK25: 0.02 | GM25: Perdas operacionais | GN25: =-GO$25*GN$4*$A$2 -> -620 | GO25: 0.02 | GQ25: Perdas operacionais | GR25: =-GS$25*GR$4*$A$2 -> -620 | GS25: 0.02 | GU25: Perdas operacionais | GV25: =-GW$25*GV$4*$A$2 -> -620 | GW25: 0.02 | GY25: Perdas operacionais | GZ25: =-HA$25*GZ$4*$A$2 -> -620 | HA25: 0.02 | HC25: Perdas operacionais | HD25: =-HE$25*HD$4*$A$2 -> -620 | HE25: 0.02 | HG25: Perdas operacionais | HH25: =-HI$25*HH$4*$A$2 -> -620 | HI25: 0.02 | HK25: Perdas operacionais | HL25: =-HM$25*HL$4*$A$2 -> -682 | HM25: 0.02 | HO25: Perdas operacionais | HP25: =-HQ$25*HP$4*$A$2 -> -682 | HQ25: 0.02 | HS25: Perdas operacionais | HT25: =-HU$25*HT$4*$A$2 -> -682 | HU25: 0.02 | HW25: Perdas operacionais | HX25: =-HY$25*HX$4*$A$2 -> -682 | HY25: 0.02 | IA25: Perdas operacionais | IB25: =-IC$25*IB$4*$A$2 -> -682 | IC25: 0.02 | IE25: Perdas operacionais | IF25: =-IG$25*IF$4*$A$2 -> -682 | IG25: 0.02 | II25: Perdas operacionais | IJ25: =-IK$25*IJ$4*$A$2 -> -744 | IK25: 0.02 | IM25: Perdas operacionais | IN25: =-IO$25*IN$4*$A$2 -> -744 | IO25: 0.02 | IQ25: Perdas operacionais | IR25: =-IS$25*IR$4*$A$2 -> -744 | IS25: 0.02 | IU25: Perdas operacionais | IV25: =-IW$25*IV$4*$A$2 -> -744 | IW25: 0.02 | IY25: Perdas operacionais | IZ25: =-JA$25*IZ$4*$A$2 -> -744 | JA25: 0.02 | JC25: Perdas operacionais | JD25: =-JE$25*JD$4*$A$2 -> -744 | JE25: 0.02 | JG25: Perdas operacionais | JH25: =-JI$25*JH$4*$A$2 -> -744 | JI25: 0.02 | JK25: Perdas operacionais | JL25: =-JM$25*JL$4*$A$2 -> -806 | JM25: 0.02 | JO25: Perdas operacionais | JP25: =-JQ$25*JP$4*$A$2 -> -806 | JQ25: 0.02 | JS25: Perdas operacionais | JT25: =-JU$25*JT$4*$A$2 -> -806 | JU25: 0.02 | JW25: Perdas operacionais | JX25: =-JY$25*JX$4*$A$2 -> -806 | JY25: 0.02 | KA25: Perdas operacionais | KB25: =-KC$25*KB$4*$A$2 -> -806 | KC25: 0.02 | KE25: Perdas operacionais | KF25: =-KG$25*KF$4*$A$2 -> -806 | KG25: 0.02
C26: Perda de peso na torra | D26: =-E$26*D$4*$A$2 -> -1674 | E26: 0.18 | G26: Perda de peso na torra | H26: =-I$26*H$4*$A$2 -> -1674 | I26: 0.18 | K26: Perda de peso na torra | L26: =-M$26*L$4*$A$2 -> -1674 | M26: 0.18 | O26: Perda de peso na torra | P26: =-Q$26*P$4*$A$2 -> -1674 | Q26: 0.18 | S26: Perda de peso na torra | T26: =-U$26*T$4*$A$2 -> -1674 | U26: 0.18 | W26: Perda de peso na torra | X26: =-Y$26*X$4*$A$2 -> -1674 | Y26: 0.18 | AA26: Perda de peso na torra | AB26: =-AC$26*AB$4*$A$2 -> -1674 | AC26: 0.18 | AE26: Perda de peso na torra | AF26: =-AG$26*AF$4*$A$2 -> -2232 | AG26: 0.18 | AI26: Perda de peso na torra | AJ26: =-AK$26*AJ$4*$A$2 -> -2232 | AK26: 0.18 | AM26: Perda de peso na torra | AN26: =-AO$26*AN$4*$A$2 -> -2232 | AO26: 0.18 | AQ26: Perda de peso na torra | AR26: =-AS$26*AR$4*$A$2 -> -2232 | AS26: 0.18 | AU26: Perda de peso na torra | AV26: =-AW$26*AV$4*$A$2 -> -2232 | AW26: 0.18 | AY26: Perda de peso na torra | AZ26: =-BA$26*AZ$4*$A$2 -> -2232 | BA26: 0.18 | BC26: Perda de peso na torra | BD26: =-BE$26*BD$4*$A$2 -> -2232 | BE26: 0.18 | BG26: Perda de peso na torra | BH26: =-BI$26*BH$4*$A$2 -> -2790 | BI26: 0.18 | BK26: Perda de peso na torra | BL26: =-BM$26*BL$4*$A$2 -> -2790 | BM26: 0.18 | BO26: Perda de peso na torra | BP26: =-BQ$26*BP$4*$A$2 -> -2790 | BQ26: 0.18 | BS26: Perda de peso na torra | BT26: =-BU$26*BT$4*$A$2 -> -2790 | BU26: 0.18 | BW26: Perda de peso na torra | BX26: =-BY$26*BX$4*$A$2 -> -2790 | BY26: 0.18 | CA26: Perda de peso na torra | CB26: =-CC$26*CB$4*$A$2 -> -2790 | CC26: 0.18 | CE26: Perda de peso na torra | CF26: =-CG$26*CF$4*$A$2 -> -3348 | CG26: 0.18 | CI26: Perda de peso na torra | CJ26: =-CK$26*CJ$4*$A$2 -> -3348 | CK26: 0.18 | CM26: Perda de peso na torra | CN26: =-CO$26*CN$4*$A$2 -> -3348 | CO26: 0.18 | CQ26: Perda de peso na torra | CR26: =-CS$26*CR$4*$A$2 -> -3348 | CS26: 0.18 | CU26: Perda de peso na torra | CV26: =-CW$26*CV$4*$A$2 -> -3348 | CW26: 0.18 | CY26: Perda de peso na torra | CZ26: =-DA$26*CZ$4*$A$2 -> -3348 | DA26: 0.18 | DC26: Perda de peso na torra | DD26: =-DE$26*DD$4*$A$2 -> -3348 | DE26: 0.18 | DG26: Perda de peso na torra | DH26: =-DI$26*DH$4*$A$2 -> -3906 | DI26: 0.18 | DK26: Perda de peso na torra | DL26: =-DM$26*DL$4*$A$2 -> -3906 | DM26: 0.18 | DO26: Perda de peso na torra | DP26: =-DQ$26*DP$4*$A$2 -> -3906 | DQ26: 0.18 | DS26: Perda de peso na torra | DT26: =-DU$26*DT$4*$A$2 -> -3906 | DU26: 0.18 | DW26: Perda de peso na torra | DX26: =-DY$26*DX$4*$A$2 -> -3906 | DY26: 0.18 | EA26: Perda de peso na torra | EB26: =-EC$26*EB$4*$A$2 -> -3906 | EC26: 0.18 | EE26: Perda de peso na torra | EF26: =-EG$26*EF$4*$A$2 -> -3906 | EG26: 0.18 | EI26: Perda de peso na torra | EJ26: =-EK$26*EJ$4*$A$2 -> -4464 | EK26: 0.18 | EM26: Perda de peso na torra | EN26: =-EO$26*EN$4*$A$2 -> -4464 | EO26: 0.18 | EQ26: Perda de peso na torra | ER26: =-ES$26*ER$4*$A$2 -> -4464 | ES26: 0.18 | EU26: Perda de peso na torra | EV26: =-EW$26*EV$4*$A$2 -> -4464 | EW26: 0.18 | EY26: Perda de peso na torra | EZ26: =-FA$26*EZ$4*$A$2 -> -4464 | FA26: 0.18 | FC26: Perda de peso na torra | FD26: =-FE$26*FD$4*$A$2 -> -4464 | FE26: 0.18 | FG26: Perda de peso na torra | FH26: =-FI$26*FH$4*$A$2 -> -5022 | FI26: 0.18 | FK26: Perda de peso na torra | FL26: =-FM$26*FL$4*$A$2 -> -5022 | FM26: 0.18 | FO26: Perda de peso na torra | FP26: =-FQ$26*FP$4*$A$2 -> -5022 | FQ26: 0.18 | FS26: Perda de peso na torra | FT26: =-FU$26*FT$4*$A$2 -> -5022 | FU26: 0.18 | FW26: Perda de peso na torra | FX26: =-FY$26*FX$4*$A$2 -> -5022 | FY26: 0.18 | GA26: Perda de peso na torra | GB26: =-GC$26*GB$4*$A$2 -> -5022 | GC26: 0.18 | GE26: Perda de peso na torra | GF26: =-GG$26*GF$4*$A$2 -> -5022 | GG26: 0.18 | GI26: Perda de peso na torra | GJ26: =-GK$26*GJ$4*$A$2 -> -5580 | GK26: 0.18 | GM26: Perda de peso na torra | GN26: =-GO$26*GN$4*$A$2 -> -5580 | GO26: 0.18 | GQ26: Perda de peso na torra | GR26: =-GS$26*GR$4*$A$2 -> -5580 | GS26: 0.18 | GU26: Perda de peso na torra | GV26: =-GW$26*GV$4*$A$2 -> -5580 | GW26: 0.18 | GY26: Perda de peso na torra | GZ26: =-HA$26*GZ$4*$A$2 -> -5580 | HA26: 0.18 | HC26: Perda de peso na torra | HD26: =-HE$26*HD$4*$A$2 -> -5580 | HE26: 0.18 | HG26: Perda de peso na torra | HH26: =-HI$26*HH$4*$A$2 -> -5580 | HI26: 0.18 | HK26: Perda de peso na torra | HL26: =-HM$26*HL$4*$A$2 -> -6138 | HM26: 0.18 | HO26: Perda de peso na torra | HP26: =-HQ$26*HP$4*$A$2 -> -6138 | HQ26: 0.18 | HS26: Perda de peso na torra | HT26: =-HU$26*HT$4*$A$2 -> -6138 | HU26: 0.18 | HW26: Perda de peso na torra | HX26: =-HY$26*HX$4*$A$2 -> -6138 | HY26: 0.18 | IA26: Perda de peso na torra | IB26: =-IC$26*IB$4*$A$2 -> -6138 | IC26: 0.18 | IE26: Perda de peso na torra | IF26: =-IG$26*IF$4*$A$2 -> -6138 | IG26: 0.18 | II26: Perda de peso na torra | IJ26: =-IK$26*IJ$4*$A$2 -> -6696 | IK26: 0.18 | IM26: Perda de peso na torra | IN26: =-IO$26*IN$4*$A$2 -> -6696 | IO26: 0.18 | IQ26: Perda de peso na torra | IR26: =-IS$26*IR$4*$A$2 -> -6696 | IS26: 0.18 | IU26: Perda de peso na torra | IV26: =-IW$26*IV$4*$A$2 -> -6696 | IW26: 0.18 | IY26: Perda de peso na torra | IZ26: =-JA$26*IZ$4*$A$2 -> -6696 | JA26: 0.18 | JC26: Perda de peso na torra | JD26: =-JE$26*JD$4*$A$2 -> -6696 | JE26: 0.18 | JG26: Perda de peso na torra | JH26: =-JI$26*JH$4*$A$2 -> -6696 | JI26: 0.18 | JK26: Perda de peso na torra | JL26: =-JM$26*JL$4*$A$2 -> -7254 | JM26: 0.18 | JO26: Perda de peso na torra | JP26: =-JQ$26*JP$4*$A$2 -> -7254 | JQ26: 0.18 | JS26: Perda de peso na torra | JT26: =-JU$26*JT$4*$A$2 -> -7254 | JU26: 0.18 | JW26: Perda de peso na torra | JX26: =-JY$26*JX$4*$A$2 -> -7254 | JY26: 0.18 | KA26: Perda de peso na torra | KB26: =-KC$26*KB$4*$A$2 -> -7254 | KC26: 0.18 | KE26: Perda de peso na torra | KF26: =-KG$26*KF$4*$A$2 -> -7254 | KG26: 0.18
C27: GLP | D27: =-E$27*60*D$4 -> -154.8 | E27: 0.86 | G27: GLP | H27: =-I$27*60*H$4 -> -154.8 | I27: 0.86 | K27: GLP | L27: =-M$27*60*L$4 -> -154.8 | M27: 0.86 | O27: GLP | P27: =-Q$27*60*P$4 -> -154.8 | Q27: 0.86 | S27: GLP | T27: =-U$27*60*T$4 -> -154.8 | U27: 0.86 | W27: GLP | X27: =-Y$27*60*X$4 -> -154.8 | Y27: 0.86 | AA27: GLP | AB27: =-AC$27*60*AB$4 -> -154.8 | AC27: 0.86 | AE27: GLP | AF27: =-AG$27*60*AF$4 -> -206.4 | AG27: 0.86 | AI27: GLP | AJ27: =-AK$27*60*AJ$4 -> -206.4 | AK27: 0.86 | AM27: GLP | AN27: =-AO$27*60*AN$4 -> -206.4 | AO27: 0.86 | AQ27: GLP | AR27: =-AS$27*60*AR$4 -> -206.4 | AS27: 0.86 | AU27: GLP | AV27: =-AW$27*60*AV$4 -> -206.4 | AW27: 0.86 | AY27: GLP | AZ27: =-BA$27*60*AZ$4 -> -206.4 | BA27: 0.86 | BC27: GLP | BD27: =-BE$27*60*BD$4 -> -206.4 | BE27: 0.86 | BG27: GLP | BH27: =-BI$27*60*BH$4 -> -258 | BI27: 0.86 | BK27: GLP | BL27: =-BM$27*60*BL$4 -> -258 | BM27: 0.86 | BO27: GLP | BP27: =-BQ$27*60*BP$4 -> -258 | BQ27: 0.86 | BS27: GLP | BT27: =-BU$27*60*BT$4 -> -258 | BU27: 0.86 | BW27: GLP | BX27: =-BY$27*60*BX$4 -> -258 | BY27: 0.86 | CA27: GLP | CB27: =-CC$27*60*CB$4 -> -258 | CC27: 0.86 | CE27: GLP | CF27: =-CG$27*60*CF$4 -> -309.6 | CG27: 0.86 | CI27: GLP | CJ27: =-CK$27*60*CJ$4 -> -309.6 | CK27: 0.86 | CM27: GLP | CN27: =-CO$27*60*CN$4 -> -309.6 | CO27: 0.86 | CQ27: GLP | CR27: =-CS$27*60*CR$4 -> -309.6 | CS27: 0.86 | CU27: GLP | CV27: =-CW$27*60*CV$4 -> -309.6 | CW27: 0.86 | CY27: GLP | CZ27: =-DA$27*60*CZ$4 -> -309.6 | DA27: 0.86 | DC27: GLP | DD27: =-DE$27*60*DD$4 -> -309.6 | DE27: 0.86 | DG27: GLP | DH27: =-DI$27*60*DH$4 -> -361.2 | DI27: 0.86 | DK27: GLP | DL27: =-DM$27*60*DL$4 -> -361.2 | DM27: 0.86 | DO27: GLP | DP27: =-DQ$27*60*DP$4 -> -361.2 | DQ27: 0.86 | DS27: GLP | DT27: =-DU$27*60*DT$4 -> -361.2 | DU27: 0.86 | DW27: GLP | DX27: =-DY$27*60*DX$4 -> -361.2 | DY27: 0.86 | EA27: GLP | EB27: =-EC$27*60*EB$4 -> -361.2 | EC27: 0.86 | EE27: GLP | EF27: =-EG$27*60*EF$4 -> -361.2 | EG27: 0.86 | EI27: GLP | EJ27: =-EK$27*60*EJ$4 -> -412.8 | EK27: 0.86 | EM27: GLP | EN27: =-EO$27*60*EN$4 -> -412.8 | EO27: 0.86 | EQ27: GLP | ER27: =-ES$27*60*ER$4 -> -412.8 | ES27: 0.86 | EU27: GLP | EV27: =-EW$27*60*EV$4 -> -412.8 | EW27: 0.86 | EY27: GLP | EZ27: =-FA$27*60*EZ$4 -> -412.8 | FA27: 0.86 | FC27: GLP | FD27: =-FE$27*60*FD$4 -> -412.8 | FE27: 0.86 | FG27: GLP | FH27: =-FI$27*60*FH$4 -> -464.4 | FI27: 0.86 | FK27: GLP | FL27: =-FM$27*60*FL$4 -> -464.4 | FM27: 0.86 | FO27: GLP | FP27: =-FQ$27*60*FP$4 -> -464.4 | FQ27: 0.86 | FS27: GLP | FT27: =-FU$27*60*FT$4 -> -464.4 | FU27: 0.86 | FW27: GLP | FX27: =-FY$27*60*FX$4 -> -464.4 | FY27: 0.86 | GA27: GLP | GB27: =-GC$27*60*GB$4 -> -464.4 | GC27: 0.86 | GE27: GLP | GF27: =-GG$27*60*GF$4 -> -464.4 | GG27: 0.86 | GI27: GLP | GJ27: =-GK$27*60*GJ$4 -> -516 | GK27: 0.86 | GM27: GLP | GN27: =-GO$27*60*GN$4 -> -516 | GO27: 0.86 | GQ27: GLP | GR27: =-GS$27*60*GR$4 -> -516 | GS27: 0.86 | GU27: GLP | GV27: =-GW$27*60*GV$4 -> -516 | GW27: 0.86 | GY27: GLP | GZ27: =-HA$27*60*GZ$4 -> -516 | HA27: 0.86 | HC27: GLP | HD27: =-HE$27*60*HD$4 -> -516 | HE27: 0.86 | HG27: GLP | HH27: =-HI$27*60*HH$4 -> -516 | HI27: 0.86 | HK27: GLP | HL27: =-HM$27*60*HL$4 -> -567.6 | HM27: 0.86 | HO27: GLP | HP27: =-HQ$27*60*HP$4 -> -567.6 | HQ27: 0.86 | HS27: GLP | HT27: =-HU$27*60*HT$4 -> -567.6 | HU27: 0.86 | HW27: GLP | HX27: =-HY$27*60*HX$4 -> -567.6 | HY27: 0.86 | IA27: GLP | IB27: =-IC$27*60*IB$4 -> -567.6 | IC27: 0.86 | IE27: GLP | IF27: =-IG$27*60*IF$4 -> -567.6 | IG27: 0.86 | II27: GLP | IJ27: =-IK$27*60*IJ$4 -> -619.2 | IK27: 0.86 | IM27: GLP | IN27: =-IO$27*60*IN$4 -> -619.2 | IO27: 0.86 | IQ27: GLP | IR27: =-IS$27*60*IR$4 -> -619.2 | IS27: 0.86 | IU27: GLP | IV27: =-IW$27*60*IV$4 -> -619.2 | IW27: 0.86 | IY27: GLP | IZ27: =-JA$27*60*IZ$4 -> -619.2 | JA27: 0.86 | JC27: GLP | JD27: =-JE$27*60*JD$4 -> -619.2 | JE27: 0.86 | JG27: GLP | JH27: =-JI$27*60*JH$4 -> -619.2 | JI27: 0.86 | JK27: GLP | JL27: =-JM$27*60*JL$4 -> -670.8 | JM27: 0.86 | JO27: GLP | JP27: =-JQ$27*60*JP$4 -> -670.8 | JQ27: 0.86 | JS27: GLP | JT27: =-JU$27*60*JT$4 -> -670.8 | JU27: 0.86 | JW27: GLP | JX27: =-JY$27*60*JX$4 -> -670.8 | JY27: 0.86 | KA27: GLP | KB27: =-KC$27*60*KB$4 -> -670.8 | KC27: 0.86 | KE27: GLP | KF27: =-KG$27*60*KF$4 -> -670.8 | KG27: 0.86
C28: Pró-labore | D28: =-E$28*D$3 -> -4032 | E28: 0.14 | G28: Pró-labore | H28: =-I$28*H$3 -> -4032 | I28: 0.14 | K28: Pró-labore | L28: =-M$28*L$3 -> -4032 | M28: 0.14 | O28: Pró-labore | P28: =-Q$28*P$3 -> -4032 | Q28: 0.14 | S28: Pró-labore | T28: =-U$28*T$3 -> -4032 | U28: 0.14 | W28: Pró-labore | X28: =-Y$28*X$3 -> -4032 | Y28: 0.14 | AA28: Pró-labore | AB28: =-AC$28*AB$3 -> -4032 | AC28: 0.14 | AE28: Pró-labore | AF28: =-AG$28*AF$3 -> -5376 | AG28: 0.14 | AI28: Pró-labore | AJ28: =-AK$28*AJ$3 -> -5376 | AK28: 0.14 | AM28: Pró-labore | AN28: =-AO$28*AN$3 -> -5376 | AO28: 0.14 | AQ28: Pró-labore | AR28: =-AS$28*AR$3 -> -5376 | AS28: 0.14 | AU28: Pró-labore | AV28: =-AW$28*AV$3 -> -5376 | AW28: 0.14 | AY28: Pró-labore | AZ28: =-BA$28*AZ$3 -> -5376 | BA28: 0.14 | BC28: Pró-labore | BD28: =-BE$28*BD$3 -> -5376 | BE28: 0.14 | BG28: Pró-labore | BH28: =-BI$28*BH$3 -> -6720 | BI28: 0.14 | BK28: Pró-labore | BL28: =-BM$28*BL$3 -> -6720 | BM28: 0.14 | BO28: Pró-labore | BP28: =-BQ$28*BP$3 -> -6720 | BQ28: 0.14 | BS28: Pró-labore | BT28: =-BU$28*BT$3 -> -6720 | BU28: 0.14 | BW28: Pró-labore | BX28: =-BY$28*BX$3 -> -6720 | BY28: 0.14 | CA28: Pró-labore | CB28: =-CC$28*CB$3 -> -6720 | CC28: 0.14 | CE28: Pró-labore | CF28: =-CG$28*CF$3 -> -8064 | CG28: 0.14 | CI28: Pró-labore | CJ28: =-CK$28*CJ$3 -> -8064 | CK28: 0.14 | CM28: Pró-labore | CN28: =-CO$28*CN$3 -> -8064 | CO28: 0.14 | CQ28: Pró-labore | CR28: =-CS$28*CR$3 -> -8064 | CS28: 0.14 | CU28: Pró-labore | CV28: =-CW$28*CV$3 -> -8064 | CW28: 0.14 | CY28: Pró-labore | CZ28: =-DA$28*CZ$3 -> -8064 | DA28: 0.14 | DC28: Pró-labore | DD28: =-DE$28*DD$3 -> -8064 | DE28: 0.14 | DG28: Pró-labore | DH28: =-DI$28*DH$3 -> -9408 | DI28: 0.14 | DK28: Pró-labore | DL28: =-DM$28*DL$3 -> -9408 | DM28: 0.14 | DO28: Pró-labore | DP28: =-DQ$28*DP$3 -> -9408 | DQ28: 0.14 | DS28: Pró-labore | DT28: =-DU$28*DT$3 -> -9408 | DU28: 0.14 | DW28: Pró-labore | DX28: =-DY$28*DX$3 -> -9408 | DY28: 0.14 | EA28: Pró-labore | EB28: =-EC$28*EB$3 -> -9408 | EC28: 0.14 | EE28: Pró-labore | EF28: =-EG$28*EF$3 -> -9408 | EG28: 0.14 | EI28: Pró-labore | EJ28: =-EK$28*EJ$3 -> -10752 | EK28: 0.14 | EM28: Pró-labore | EN28: =-EO$28*EN$3 -> -10752 | EO28: 0.14 | EQ28: Pró-labore | ER28: =-ES$28*ER$3 -> -10752 | ES28: 0.14 | EU28: Pró-labore | EV28: =-EW$28*EV$3 -> -10752 | EW28: 0.14 | EY28: Pró-labore | EZ28: =-FA$28*EZ$3 -> -10752 | FA28: 0.14 | FC28: Pró-labore | FD28: =-FE$28*FD$3 -> -10752 | FE28: 0.14 | FG28: Pró-labore | FH28: =-FI$28*FH$3 -> -12096 | FI28: 0.14 | FK28: Pró-labore | FL28: =-FM$28*FL$3 -> -12096 | FM28: 0.14 | FO28: Pró-labore | FP28: =-FQ$28*FP$3 -> -12096 | FQ28: 0.14 | FS28: Pró-labore | FT28: =-FU$28*FT$3 -> -12096 | FU28: 0.14 | FW28: Pró-labore | FX28: =-FY$28*FX$3 -> -12096 | FY28: 0.14 | GA28: Pró-labore | GB28: =-GC$28*GB$3 -> -12096 | GC28: 0.14 | GE28: Pró-labore | GF28: =-GG$28*GF$3 -> -12096 | GG28: 0.14 | GI28: Pró-labore | GJ28: =-GK$28*GJ$3 -> -13440 | GK28: 0.14 | GM28: Pró-labore | GN28: =-GO$28*GN$3 -> -13440 | GO28: 0.14 | GQ28: Pró-labore | GR28: =-GS$28*GR$3 -> -13440 | GS28: 0.14 | GU28: Pró-labore | GV28: =-GW$28*GV$3 -> -13440 | GW28: 0.14 | GY28: Pró-labore | GZ28: =-HA$28*GZ$3 -> -13440 | HA28: 0.14 | HC28: Pró-labore | HD28: =-HE$28*HD$3 -> -13440 | HE28: 0.14 | HG28: Pró-labore | HH28: =-HI$28*HH$3 -> -13440 | HI28: 0.14 | HK28: Pró-labore | HL28: =-HM$28*HL$3 -> -14784 | HM28: 0.14 | HO28: Pró-labore | HP28: =-HQ$28*HP$3 -> -14784 | HQ28: 0.14 | HS28: Pró-labore | HT28: =-HU$28*HT$3 -> -14784 | HU28: 0.14 | HW28: Pró-labore | HX28: =-HY$28*HX$3 -> -14784 | HY28: 0.14 | IA28: Pró-labore | IB28: =-IC$28*IB$3 -> -14784 | IC28: 0.14 | IE28: Pró-labore | IF28: =-IG$28*IF$3 -> -14784 | IG28: 0.14 | II28: Pró-labore | IJ28: =-IK$28*IJ$3 -> -16128 | IK28: 0.14 | IM28: Pró-labore | IN28: =-IO$28*IN$3 -> -16128 | IO28: 0.14 | IQ28: Pró-labore | IR28: =-IS$28*IR$3 -> -16128 | IS28: 0.14 | IU28: Pró-labore | IV28: =-IW$28*IV$3 -> -16128 | IW28: 0.14 | IY28: Pró-labore | IZ28: =-JA$28*IZ$3 -> -16128 | JA28: 0.14 | JC28: Pró-labore | JD28: =-JE$28*JD$3 -> -16128 | JE28: 0.14 | JG28: Pró-labore | JH28: =-JI$28*JH$3 -> -16128 | JI28: 0.14 | JK28: Pró-labore | JL28: =-JM$28*JL$3 -> -17472 | JM28: 0.14 | JO28: Pró-labore | JP28: =-JQ$28*JP$3 -> -17472 | JQ28: 0.14 | JS28: Pró-labore | JT28: =-JU$28*JT$3 -> -17472 | JU28: 0.14 | JW28: Pró-labore | JX28: =-JY$28*JX$3 -> -17472 | JY28: 0.14 | KA28: Pró-labore | KB28: =-KC$28*KB$3 -> -17472 | KC28: 0.14 | KE28: Pró-labore | KF28: =-KG$28*KF$3 -> -17472 | KG28: 0.14
C30: Custos totais | D30: =SUM(D$10:D$28) -> -133102 | G30: Custos totais | H30: =SUM(H$10:H$28) -> -21701.996 | K30: Custos totais | L30: =SUM(L$10:L$28) -> -21701.996 | O30: Custos totais | P30: =SUM(P$10:P$28) -> -50601.996 | S30: Custos totais | T30: =SUM(T$10:T$28) -> -21701.996 | W30: Custos totais | X30: =SUM(X$10:X$28) -> -21701.996 | AA30: Custos totais | AB30: =SUM(AB$10:AB$28) -> -57752.396 | AE30: Custos totais | AF30: =SUM(AF$10:AF$28) -> -26531.796 | AI30: Custos totais | AJ30: =SUM(AJ$10:AJ$28) -> -26531.796 | AM30: Custos totais | AN30: =SUM(AN$10:AN$28) -> -64731.796 | AQ30: Custos totais | AR30: =SUM(AR$10:AR$28) -> -26531.796 | AU30: Custos totais | AV30: =SUM(AV$10:AV$28) -> -27376.596 | AY30: Custos totais | AZ30: =SUM(AZ$10:AZ$28) -> -68676.596 | BC30: Custos totais | BD30: =SUM(BD$10:BD$28) -> -27376.596 | BG30: Custos totais | BH30: =SUM(BH$10:BH$28) -> -31467.196 | BK30: Custos totais | BL30: =SUM(BL$10:BL$28) -> -78967.196 | BO30: Custos totais | BP30: =SUM(BP$10:BP$28) -> -31467.196 | BS30: Custos totais | BT30: =SUM(BT$10:BT$28) -> -31467.196 | BW30: Custos totais | BX30: =SUM(BX$10:BX$28) -> -82067.196 | CA30: Custos totais | CB30: =SUM(CB$10:CB$28) -> -31467.196 | CE30: Custos totais | CF30: =SUM(CF$10:CF$28) -> -35557.796 | CI30: Custos totais | CJ30: =SUM(CJ$10:CJ$28) -> -92357.796 | CM30: Custos totais | CN30: =SUM(CN$10:CN$28) -> -35557.796 | CQ30: Custos totais | CR30: =SUM(CR$10:CR$28) -> -35557.796 | CU30: Custos totais | CV30: =SUM(CV$10:CV$28) -> -92357.796 | CY30: Custos totais | CZ30: =SUM(CZ$10:CZ$28) -> -35557.796 | DC30: Custos totais | DD30: =SUM(DD$10:DD$28) -> -35557.796 | DG30: Custos totais | DH30: =SUM(DH$10:DH$28) -> -105748.4 | DK30: Custos totais | DL30: =SUM(DL$10:DL$28) -> -39648.396 | DO30: Custos totais | DP30: =SUM(DP$10:DP$28) -> -39648.396 | DS30: Custos totais | DT30: =SUM(DT$10:DT$28) -> -105748.4 | DW30: Custos totais | DX30: =SUM(DX$10:DX$28) -> -40454.796 | EA30: Custos totais | EB30: =SUM(EB$10:EB$28) -> -40454.796 | EE30: Custos totais | EF30: =SUM(EF$10:EF$28) -> -112754.8 | EI30: Custos totais | EJ30: =SUM(EJ$10:EJ$28) -> -44660.596 | EM30: Custos totais | EN30: =SUM(EN$10:EN$28) -> -44660.596 | EQ30: Custos totais | ER30: =SUM(ER$10:ER$28) -> -120060.6 | EU30: Custos totais | EV30: =SUM(EV$10:EV$28) -> -44660.596 | EY30: Custos totais | EZ30: =SUM(EZ$10:EZ$28) -> -44660.596 | FC30: Custos totais | FD30: =SUM(FD$10:FD$28) -> -126260.6 | FG30: Custos totais | FH30: =SUM(FH$10:FH$28) -> -48866.396 | FK30: Custos totais | FL30: =SUM(FL$10:FL$28) -> -48866.396 | FO30: Custos totais | FP30: =SUM(FP$10:FP$28) -> -133566.4 | FS30: Custos totais | FT30: =SUM(FT$10:FT$28) -> -48866.396 | FW30: Custos totais | FX30: =SUM(FX$10:FX$28) -> -48866.396 | GA30: Custos totais | GB30: =SUM(GB$10:GB$28) -> -136666.4 | GE30: Custos totais | GF30: =SUM(GF$10:GF$28) -> -48866.396 | GI30: Custos totais | GJ30: =SUM(GJ$10:GJ$28) -> -53072.196 | GM30: Custos totais | GN30: =SUM(GN$10:GN$28) -> -147072.2 | GQ30: Custos totais | GR30: =SUM(GR$10:GR$28) -> -53072.196 | GU30: Custos totais | GV30: =SUM(GV$10:GV$28) -> -53072.196 | GY30: Custos totais | GZ30: =SUM(GZ$10:GZ$28) -> -147072.2 | HC30: Custos totais | HD30: =SUM(HD$10:HD$28) -> -53072.196 | HG30: Custos totais | HH30: =SUM(HH$10:HH$28) -> -53072.196 | HK30: Custos totais | HL30: =SUM(HL$10:HL$28) -> -160578 | HO30: Custos totais | HP30: =SUM(HP$10:HP$28) -> -57277.996 | HS30: Custos totais | HT30: =SUM(HT$10:HT$28) -> -57277.996 | HW30: Custos totais | HX30: =SUM(HX$10:HX$28) -> -160578 | IA30: Custos totais | IB30: =SUM(IB$10:IB$28) -> -57277.996 | IE30: Custos totais | IF30: =SUM(IF$10:IF$28) -> -57277.996 | II30: Custos totais | IJ30: =SUM(IJ$10:IJ$28) -> -174083.8 | IM30: Custos totais | IN30: =SUM(IN$10:IN$28) -> -61483.796 | IQ30: Custos totais | IR30: =SUM(IR$10:IR$28) -> -61483.796 | IU30: Custos totais | IV30: =SUM(IV$10:IV$28) -> -174083.8 | IY30: Custos totais | IZ30: =SUM(IZ$10:IZ$28) -> -61483.796 | JC30: Custos totais | JD30: =SUM(JD$10:JD$28) -> -61483.796 | JG30: Custos totais | JH30: =SUM(JH$10:JH$28) -> -180283.8 | JK30: Custos totais | JL30: =SUM(JL$10:JL$28) -> -65689.596 | JO30: Custos totais | JP30: =SUM(JP$10:JP$28) -> -65689.596 | JS30: Custos totais | JT30: =SUM(JT$10:JT$28) -> -187589.6 | JW30: Custos totais | JX30: =SUM(JX$10:JX$28) -> -65689.596 | KA30: Custos totais | KB30: =SUM(KB$10:KB$28) -> -65689.596 | KE30: Custos totais | KF30: =SUM(KF$10:KF$28) -> -106989.6
C31: Lucro mês | D31: =D$7+D$30 -> -104302 | G31: Lucro mês | H31: =H$7+H$30 -> 7098.0043 | K31: Lucro mês | L31: =L$7+L$30 -> 7098.0043 | O31: Lucro mês | P31: =P$7+P$30 -> -21801.996 | S31: Lucro mês | T31: =T$7+T$30 -> 7098.0043 | W31: Lucro mês | X31: =X$7+X$30 -> 7098.0043 | AA31: Lucro mês | AB31: =AB$7+AB$30 -> -28952.396 | AE31: Lucro mês | AF31: =AF$7+AF$30 -> 11868.204 | AI31: Lucro mês | AJ31: =AJ$7+AJ$30 -> 11868.204 | AM31: Lucro mês | AN31: =AN$7+AN$30 -> -26331.796 | AQ31: Lucro mês | AR31: =AR$7+AR$30 -> 11868.204 | AU31: Lucro mês | AV31: =AV$7+AV$30 -> 11023.404 | AY31: Lucro mês | AZ31: =AZ$7+AZ$30 -> -30276.596 | BC31: Lucro mês | BD31: =BD$7+BD$30 -> 11023.404 | BG31: Lucro mês | BH31: =BH$7+BH$30 -> 16532.804 | BK31: Lucro mês | BL31: =BL$7+BL$30 -> -30967.196 | BO31: Lucro mês | BP31: =BP$7+BP$30 -> 16532.804 | BS31: Lucro mês | BT31: =BT$7+BT$30 -> 16532.804 | BW31: Lucro mês | BX31: =BX$7+BX$30 -> -34067.196 | CA31: Lucro mês | CB31: =CB$7+CB$30 -> 16532.804 | CE31: Lucro mês | CF31: =CF$7+CF$30 -> 22042.204 | CI31: Lucro mês | CJ31: =CJ$7+CJ$30 -> -34757.796 | CM31: Lucro mês | CN31: =CN$7+CN$30 -> 22042.204 | CQ31: Lucro mês | CR31: =CR$7+CR$30 -> 22042.204 | CU31: Lucro mês | CV31: =CV$7+CV$30 -> -34757.796 | CY31: Lucro mês | CZ31: =CZ$7+CZ$30 -> 22042.204 | DC31: Lucro mês | DD31: =DD$7+DD$30 -> 22042.204 | DG31: Lucro mês | DH31: =DH$7+DH$30 -> -38548.396 | DK31: Lucro mês | DL31: =DL$7+DL$30 -> 27551.604 | DO31: Lucro mês | DP31: =DP$7+DP$30 -> 27551.604 | DS31: Lucro mês | DT31: =DT$7+DT$30 -> -38548.396 | DW31: Lucro mês | DX31: =DX$7+DX$30 -> 26745.204 | EA31: Lucro mês | EB31: =EB$7+EB$30 -> 26745.204 | EE31: Lucro mês | EF31: =EF$7+EF$30 -> -45554.796 | EI31: Lucro mês | EJ31: =EJ$7+EJ$30 -> 32139.404 | EM31: Lucro mês | EN31: =EN$7+EN$30 -> 32139.404 | EQ31: Lucro mês | ER31: =ER$7+ER$30 -> -43260.596 | EU31: Lucro mês | EV31: =EV$7+EV$30 -> 32139.404 | EY31: Lucro mês | EZ31: =EZ$7+EZ$30 -> 32139.404 | FC31: Lucro mês | FD31: =FD$7+FD$30 -> -49460.596 | FG31: Lucro mês | FH31: =FH$7+FH$30 -> 37533.604 | FK31: Lucro mês | FL31: =FL$7+FL$30 -> 37533.604 | FO31: Lucro mês | FP31: =FP$7+FP$30 -> -47166.396 | FS31: Lucro mês | FT31: =FT$7+FT$30 -> 37533.604 | FW31: Lucro mês | FX31: =FX$7+FX$30 -> 37533.604 | GA31: Lucro mês | GB31: =GB$7+GB$30 -> -50266.396 | GE31: Lucro mês | GF31: =GF$7+GF$30 -> 37533.604 | GI31: Lucro mês | GJ31: =GJ$7+GJ$30 -> 42927.804 | GM31: Lucro mês | GN31: =GN$7+GN$30 -> -51072.196 | GQ31: Lucro mês | GR31: =GR$7+GR$30 -> 42927.804 | GU31: Lucro mês | GV31: =GV$7+GV$30 -> 42927.804 | GY31: Lucro mês | GZ31: =GZ$7+GZ$30 -> -51072.196 | HC31: Lucro mês | HD31: =HD$7+HD$30 -> 42927.804 | HG31: Lucro mês | HH31: =HH$7+HH$30 -> 42927.804 | HK31: Lucro mês | HL31: =HL$7+HL$30 -> -54977.996 | HO31: Lucro mês | HP31: =HP$7+HP$30 -> 48322.004 | HS31: Lucro mês | HT31: =HT$7+HT$30 -> 48322.004 | HW31: Lucro mês | HX31: =HX$7+HX$30 -> -54977.996 | IA31: Lucro mês | IB31: =IB$7+IB$30 -> 48322.004 | IE31: Lucro mês | IF31: =IF$7+IF$30 -> 48322.004 | II31: Lucro mês | IJ31: =IJ$7+IJ$30 -> -58883.796 | IM31: Lucro mês | IN31: =IN$7+IN$30 -> 53716.204 | IQ31: Lucro mês | IR31: =IR$7+IR$30 -> 53716.204 | IU31: Lucro mês | IV31: =IV$7+IV$30 -> -58883.796 | IY31: Lucro mês | IZ31: =IZ$7+IZ$30 -> 53716.204 | JC31: Lucro mês | JD31: =JD$7+JD$30 -> 53716.204 | JG31: Lucro mês | JH31: =JH$7+JH$30 -> -65083.796 | JK31: Lucro mês | JL31: =JL$7+JL$30 -> 59110.404 | JO31: Lucro mês | JP31: =JP$7+JP$30 -> 59110.404 | JS31: Lucro mês | JT31: =JT$7+JT$30 -> -62789.596 | JW31: Lucro mês | JX31: =JX$7+JX$30 -> 59110.404 | KA31: Lucro mês | KB31: =KB$7+KB$30 -> 59110.404 | KE31: Lucro mês | KF31: =KF$7+KF$30 -> 17810.404
C33: Acumulado | D33: =D$31 -> -104302 | G33: Acumulado | H33: =D$33+H31 -> -97203.991 | K33: Acumulado | L33: =H$33+L31 -> -90105.987 | O33: Acumulado | P33: =L$33+P31 -> -111907.98 | S33: Acumulado | T33: =P$33+T31 -> -104809.98 | W33: Acumulado | X33: =T$33+X31 -> -97711.974 | AA33: Acumulado | AB33: =X$33+AB31 -> -126664.37 | AE33: Acumulado | AF33: =AB$33+AF31 -> -114796.17 | AI33: Acumulado | AJ33: =AF$33+AJ31 -> -102927.96 | AM33: Acumulado | AN33: =AJ$33+AN31 -> -129259.76 | AQ33: Acumulado | AR33: =AN$33+AR31 -> -117391.55 | AU33: Acumulado | AV33: =AR$33+AV31 -> -106368.15 | AY33: Acumulado | AZ33: =AV$33+AZ31 -> -136644.74 | BC33: Acumulado | BD33: =AZ$33+BD31 -> -125621.34 | BG33: Acumulado | BH33: =BD$33+BH31 -> -109088.54 | BK33: Acumulado | BL33: =BH$33+BL31 -> -140055.73 | BO33: Acumulado | BP33: =BL$33+BP31 -> -123522.93 | BS33: Acumulado | BT33: =BP$33+BT31 -> -106990.12 | BW33: Acumulado | BX33: =BT$33+BX31 -> -141057.32 | CA33: Acumulado | CB33: =BX$33+CB31 -> -124524.51 | CE33: Acumulado | CF33: =CB$33+CF31 -> -102482.31 | CI33: Acumulado | CJ33: =CF$33+CJ31 -> -137240.11 | CM33: Acumulado | CN33: =CJ$33+CN31 -> -115197.9 | CQ33: Acumulado | CR33: =CN$33+CR31 -> -93155.698 | CU33: Acumulado | CV33: =CR$33+CV31 -> -127913.49 | CY33: Acumulado | CZ33: =CV$33+CZ31 -> -105871.29 | DC33: Acumulado | DD33: =CZ$33+DD31 -> -83829.085 | DG33: Acumulado | DH33: =DD$33+DH31 -> -122377.48 | DK33: Acumulado | DL33: =DH$33+DL31 -> -94825.876 | DO33: Acumulado | DP33: =DL$33+DP31 -> -67274.272 | DS33: Acumulado | DT33: =DP$33+DT31 -> -105822.67 | DW33: Acumulado | DX33: =DT$33+DX31 -> -79077.464 | EA33: Acumulado | EB33: =DX$33+EB31 -> -52332.259 | EE33: Acumulado | EF33: =EB$33+EF31 -> -97887.055 | EI33: Acumulado | EJ33: =EF$33+EJ31 -> -65747.651 | EM33: Acumulado | EN33: =EJ$33+EN31 -> -33608.247 | EQ33: Acumulado | ER33: =EN$33+ER31 -> -76868.842 | EU33: Acumulado | EV33: =ER$33+EV31 -> -44729.438 | EY33: Acumulado | EZ33: =EV$33+EZ31 -> -12590.034 | FC33: Acumulado | FD33: =EZ$33+FD31 -> -62050.629 | FG33: Acumulado | FH33: =FD$33+FH31 -> -24517.025 | FK33: Acumulado | FL33: =FH$33+FL31 -> 13016.579 | FO33: Acumulado | FP33: =FL$33+FP31 -> -34149.817 | FS33: Acumulado | FT33: =FP$33+FT31 -> 3383.7876 | FW33: Acumulado | FX33: =FT$33+FX31 -> 40917.392 | GA33: Acumulado | GB33: =FX$33+GB31 -> -9349.0039 | GE33: Acumulado | GF33: =GB$33+GF31 -> 28184.6 | GI33: Acumulado | GJ33: =GF$33+GJ31 -> 71112.405 | GM33: Acumulado | GN33: =GJ$33+GN31 -> 20040.209 | GQ33: Acumulado | GR33: =GN$33+GR31 -> 62968.013 | GU33: Acumulado | GV33: =GR$33+GV31 -> 105895.82 | GY33: Acumulado | GZ33: =GV$33+GZ31 -> 54823.622 | HC33: Acumulado | HD33: =GZ$33+HD31 -> 97751.426 | HG33: Acumulado | HH33: =HD$33+HH31 -> 140679.23 | HK33: Acumulado | HL33: =HH$33+HL31 -> 85701.234 | HO33: Acumulado | HP33: =HL$33+HP31 -> 134023.24 | HS33: Acumulado | HT33: =HP$33+HT31 -> 182345.24 | HW33: Acumulado | HX33: =HT$33+HX31 -> 127367.25 | IA33: Acumulado | IB33: =HX$33+IB31 -> 175689.25 | IE33: Acumulado | IF33: =IB$33+IF31 -> 224011.26 | II33: Acumulado | IJ33: =IF$33+IJ31 -> 165127.46 | IM33: Acumulado | IN33: =IJ$33+IN31 -> 218843.66 | IQ33: Acumulado | IR33: =IN$33+IR31 -> 272559.87 | IU33: Acumulado | IV33: =IR$33+IV31 -> 213676.07 | IY33: Acumulado | IZ33: =IV$33+IZ31 -> 267392.28 | JC33: Acumulado | JD33: =IZ$33+JD31 -> 321108.48 | JG33: Acumulado | JH33: =JD$33+JH31 -> 256024.69 | JK33: Acumulado | JL33: =JH$33+JL31 -> 315135.09 | JO33: Acumulado | JP33: =JL$33+JP31 -> 374245.49 | JS33: Acumulado | JT33: =JP$33+JT31 -> 311455.9 | JW33: Acumulado | JX33: =JT$33+JX31 -> 370566.3 | KA33: Acumulado | KB33: =JX$33+KB31 -> 429676.71 | KE33: Acumulado | KF33: =KB$33+KF31 -> 447487.11
A35: X | B35: X | C35: X | G35: X | H35: X | I35: X | J35: X | K35: X | L35: X | M35: X | N35: X | O35: X | P35: X | Q35: X | R35: X | S35: X | T35: X | U35: X | V35: X | W35: X | X35: X | Y35: X | Z35: X | AA35: X | AB35: X | AC35: X | AD35: X | AE35: X | AF35: X | AG35: X | AH35: X | AI35: X | AJ35: X | AK35: X | AL35: X | AM35: X | AN35: X | AO35: X | AP35: X | AQ35: X | AR35: X | AS35: X | AT35: X | AU35: X | AV35: X | AW35: X | AX35: X | AY35: X | AZ35: X | BA35: X | BB35: X | BC35: X | BD35: X | BE35: X | BF35: X | BG35: X | BH35: X | BI35: X | BJ35: X | BK35: X | BL35: X | BM35: X | BN35: X | BO35: X | BP35: X | BQ35: X | BR35: X | BS35: X | BT35: X | BU35: X | BV35: X | BW35: X | BX35: X | BY35: X | BZ35: X | CA35: X | CB35: X | CC35: X | CD35: X | CE35: X | CF35: X | CG35: X | CH35: X | CI35: X | CJ35: X | CK35: X | CL35: X | CM35: X | CN35: X | CO35: X | CP35: X | CQ35: X | CR35: X | CS35: X | CT35: X | CU35: X | CV35: X | CW35: X
C36: VPL | G36: PRÓXIMO PASSO: CONSERTAR OS JUROS E IMPOSTOS
C37: 0.01
C38: =NPV($C$37,H31:KF31)+D31 -> 211843.52

Sheet Tabela Simples
A1: Faixa | B1: Limite inferior últimos 12 meses | C1: Alíquota
A2: 1ª Faixa | B2: 0 | C2: 0.045
A3: 2ª Faixa | B3: 180000.01 | C3: 0.078
A4: 3ª Faixa | B4: 360000.01 | C4: 0.1
A5: 4ª Faixa | B5: 720000.01 | C5: 0.112
A6: 5ª Faixa | B6: 1800000 | C6: 0.147
A7: 6ª Faixa | B7: 3600000 | C7: 0.3

Sheet Ponto de Equilíbrio
A2: Quantidade | B2: Receita | C2: Custo fixo | D2: Custo variável | E2: Custo total | F2: Lucro | G2: Preço de venda | H2: Custo variável por unidade
A3: 0 | B3: =A3*G3 -> 0 | C3: 2000 | D3: =A3*H3 -> 0 | E3: =SUM(D3+C3) -> 2000 | F3: =B3-E3 -> -2000 | G3: ='Fluxo de Caixa'!$A$3 -> 40 | H3: 31
A4: 50 | B4: =A4*G4 -> 2000 | C4: 2000 | D4: =A4*H4 -> 1550 | E4: =SUM(D4+C4) -> 3550 | F4: =B4-E4 -> -1550 | G4: ='Fluxo de Caixa'!$A$3 -> 40 | H4: 31
A5: 100 | B5: =A5*G5 -> 4000 | C5: 2000 | D5: =A5*H5 -> 3100 | E5: =SUM(D5+C5) -> 5100 | F5: =B5-E5 -> -1100 | G5: ='Fluxo de Caixa'!$A$3 -> 40 | H5: 31
A6: 150 | B6: =A6*G6 -> 6000 | C6: 2000 | D6: =A6*H6 -> 4650 | E6: =SUM(D6+C6) -> 6650 | F6: =B6-E6 -> -650 | G6: ='Fluxo de Caixa'!$A$3 -> 40 | H6: 31
A7: 200 | B7: =A7*G7 -> 8000 | C7: 2000 | D7: =A7*H7 -> 6200 | E7: =SUM(D7+C7) -> 8200 | F7: =B7-E7 -> -200 | G7: ='Fluxo de Caixa'!$A$3 -> 40 | H7: 31
A8: 250 | B8: =A8*G8 -> 10000 | C8: 2000 | D8: =A8*H8 -> 7750 | E8: =SUM(D8+C8) -> 9750 | F8: =B8-E8 -> 250 | G8: ='Fluxo de Caixa'!$A$3 -> 40 | H8: 31
A9: 300 | B9: =A9*G9 -> 12000 | C9: 2000 | D9: =A9*H9 -> 9300 | E9: =SUM(D9+C9) -> 11300 | F9: =B9-E9 -> 700 | G9: ='Fluxo de Caixa'!$A$3 -> 40 | H9: 31

Sheet Distribuições
A1: Preço Saca de Café | C1: 0 | G1: =C$1+1 -> 1 | K1: =G$1+1 -> 2 | O1: =K$1+1 -> 3 | S1: =O$1+1 -> 4 | W1: =S$1+1 -> 5 | AA1: =W$1+1 -> 6 | AE1: =AA$1+1 -> 7 | AI1: =AE$1+1 -> 8 | AM1: =AI$1+1 -> 9 | AQ1: =AM$1+1 -> 10 | AU1: =AQ$1+1 -> 11 | AY1: =AU$1+1 -> 12 | BC1: =AY$1+1 -> 13 | BG1: =BC$1+1 -> 14 | BK1: =BG$1+1 -> 15 | BO1: =BK$1+1 -> 16 | BS1: =BO$1+1 -> 17 | BW1: =BS$1+1 -> 18 | CA1: =BW$1+1 -> 19 | CE1: =CA$1+1 -> 20 | CI1: =CE$1+1 -> 21 | CM1: =CI$1+1 -> 22 | CQ1: =CM$1+1 -> 23 | CU1: =CQ$1+1 -> 24 | CY1: =CU$1+1 -> 25 | DC1: =CY$1+1 -> 26 | DG1: =DC$1+1 -> 27 | DK1: =DG$1+1 -> 28 | DO1: =DK$1+1 -> 29 | DS1: =DO$1+1 -> 30 | DW1: =DS$1+1 -> 31 | EA1: =DW$1+1 -> 32 | EE1: =EA$1+1 -> 33 | EI1: =EE$1+1 -> 34 | EM1: =EI$1+1 -> 35 | EQ1: =EM$1+1 -> 36 | EU1: =EQ$1+1 -> 37 | EY1: =EU$1+1 -> 38 | FC1: =EY$1+1 -> 39 | FG1: =FC$1+1 -> 40 | FK1: =FG$1+1 -> 41 | FO1: =FK$1+1 -> 42 | FS1: =FO$1+1 -> 43 | FW1: =FS$1+1 -> 44 | GA1: =FW$1+1 -> 45 | GE1: =GA$1+1 -> 46 | GI1: =GE$1+1 -> 47 | GM1: =GI$1+1 -> 48 | GQ1: =GM$1+1 -> 49 | GU1: =GQ$1+1 -> 50 | GY1: =GU$1+1 -> 51 | HC1: =GY$1+1 -> 52 | HG1: =HC$1+1 -> 53 | HK1: =HG$1+1 -> 54 | HO1: =HK$1+1 -> 55 | HS1: =HO$1+1 -> 56 | HW1: =HS$1+1 -> 57 | IA1: =HW$1+1 -> 58 | IE1: =IA$1+1 -> 59 | II1: =IE$1+1 -> 60 | IM1: =II$1+1 -> 61 | IQ1: =IM$1+1 -> 62 | IU1: =IQ$1+1 -> 63 | IY1: =IU$1+1 -> 64 | JC1: =IY$1+1 -> 65 | JG1: =JC$1+1 -> 66 | JK1: =JG$1+1 -> 67 | JO1: =JK$1+1 -> 68 | JS1: =JO$1+1 -> 69 | JW1: =JS$1+1 -> 70 | KA1: =JW$1+1 -> 71
D2: =OFFSET($D$50, 0, (COLUMN()-4)/4) -> 2948.2548 | H2: =OFFSET($D$50, 0, (COLUMN()-4)/4) -> 2758.8365 | L2: =OFFSET($D$50, 0, (COLUMN()-4)/4) -> 2558.0313 | P2: =OFFSET($D$50, 0, (COLUMN()-4)/4) -> 2542.5918 | T2: =OFFSET($D$50, 0, (COLUMN()-4)/4) -> 2566.0521 | X2: =OFFSET($D$50, 0, (COLUMN()-4)/4) -> 2470.1988 | AB2: =OFFSET($D$50, 0, (COLUMN()-4)/4) -> 2533.7599 | AF2: =OFFSET($D$50, 0, (COLUMN()-4)/4) -> 2293.7568 | AJ2: =OFFSET($D$50, 0, (COLUMN()-4)/4) -> 2130.166 | AN2: =OFFSET($D$50, 0, (COLUMN()-4)/4) -> 1982.7191 | AR2: =OFFSET($D$50, 0, (COLUMN()-4)/4) -> 2024.217 | AV2: =OFFSET($D$50, 0, (COLUMN()-4)/4) -> 2126.1502 | AZ2: =OFFSET($D$50, 0, (COLUMN()-4)/4) -> 2056.6112 | BD2: =OFFSET($D$50, 0, (COLUMN()-4)/4) -> 2068.328 | BH2: =OFFSET($D$50, 0, (COLUMN()-4)/4) -> 2007.0713 | BL2: =OFFSET($D$50, 0, (COLUMN()-4)/4) -> 2077.3381 | BP2: =OFFSET($D$50, 0, (COLUMN()-4)/4) -> 2179.4349 | BT2: =OFFSET($D$50, 0, (COLUMN()-4)/4) -> 2445.3624 | BX2: =OFFSET($D$50, 0, (COLUMN()-4)/4) -> 2146.1979 | CB2: =OFFSET($D$50, 0, (COLUMN()-4)/4) -> 2072.3816 | CF2: =OFFSET($D$50, 0, (COLUMN()-4)/4) -> 1797.8712 | CJ2: =OFFSET($D$50, 0, (COLUMN()-4)/4) -> 1667.148 | CN2: =OFFSET($D$50, 0, (COLUMN()-4)/4) -> 1451.9897 | CR2: =OFFSET($D$50, 0, (COLUMN()-4)/4) -> 1470.9776 | CV2: =OFFSET($D$50, 0, (COLUMN()-4)/4) -> 1557.109 | CZ2: =OFFSET($D$50, 0, (COLUMN()-4)/4) -> 1528.8384 | DD2: =OFFSET($D$50, 0, (COLUMN()-4)/4) -> 1553.041 | DH2: =OFFSET($D$50, 0, (COLUMN()-4)/4) -> 1536.9611 | DL2: =OFFSET($D$50, 0, (COLUMN()-4)/4) -> 1648.4137 | DP2: =OFFSET($D$50, 0, (COLUMN()-4)/4) -> 1876.7369 | DT2: =OFFSET($D$50, 0, (COLUMN()-4)/4) -> 2060.937 | DX2: =OFFSET($D$50, 0, (COLUMN()-4)/4) -> 2235.7915 | EB2: =OFFSET($D$50, 0, (COLUMN()-4)/4) -> 2483.0852 | EF2: =OFFSET($D$50, 0, (COLUMN()-4)/4) -> 2778.3823 | EJ2: =OFFSET($D$50, 0, (COLUMN()-4)/4) -> 3404.3581 | EN2: =OFFSET($D$50, 0, (COLUMN()-4)/4) -> 3610.5319 | ER2: =OFFSET($D$50, 0, (COLUMN()-4)/4) -> 3504.9888 | EV2: =OFFSET($D$50, 0, (COLUMN()-4)/4) -> 3544.5378 | EZ2: =OFFSET($D$50, 0, (COLUMN()-4)/4) -> 3628.9021 | FD2: =OFFSET($D$50, 0, (COLUMN()-4)/4) -> 3637.4596 | FH2: =OFFSET($D$50, 0, (COLUMN()-4)/4) -> 3834.0552 | FL2: =OFFSET($D$50, 0, (COLUMN()-4)/4) -> 4246.4585 | FP2: =OFFSET($D$50, 0, (COLUMN()-4)/4) -> 4191.7558 | FT2: =OFFSET($D$50, 0, (COLUMN()-4)/4) -> 4572.4318 | FX2: =OFFSET($D$50, 0, (COLUMN()-4)/4) -> 4530.707 | GB2: =OFFSET($D$50, 0, (COLUMN()-4)/4) -> 4971.134 | GF2: =OFFSET($D$50, 0, (COLUMN()-4)/4) -> 5596.095 | GJ2: =OFFSET($D$50, 0, (COLUMN()-4)/4) -> 5172.1128 | GN2: =OFFSET($D$50, 0, (COLUMN()-4)/4) -> 4501.1537 | GR2: =OFFSET($D$50, 0, (COLUMN()-4)/4) -> 4246.8071 | GV2: =OFFSET($D$50, 0, (COLUMN()-4)/4) -> 4370.1737 | GZ2: =OFFSET($D$50, 0, (COLUMN()-4)/4) -> 4212.4521 | HD2: =OFFSET($D$50, 0, (COLUMN()-4)/4) -> 3997.4657 | HH2: =OFFSET($D$50, 0, (COLUMN()-4)/4) -> 3961.9596 | HL2: =OFFSET($D$50, 0, (COLUMN()-4)/4) -> 4006.0996 | HP2: =OFFSET($D$50, 0, (COLUMN()-4)/4) -> 4118.2314 | HT2: =OFFSET($D$50, 0, (COLUMN()-4)/4) -> 3799.3918 | HX2: =OFFSET($D$50, 0, (COLUMN()-4)/4) -> 3682.6672 | IB2: =OFFSET($D$50, 0, (COLUMN()-4)/4) -> 3753.5525 | IF2: =OFFSET($D$50, 0, (COLUMN()-4)/4) -> 3696.1525 | IJ2: =OFFSET($D$50, 0, (COLUMN()-4)/4) -> 3632.6843 | IN2: =OFFSET($D$50, 0, (COLUMN()-4)/4) -> 3921.0826 | IR2: =OFFSET($D$50, 0, (COLUMN()-4)/4) -> 4121.8134 | IV2: =OFFSET($D$50, 0, (COLUMN()-4)/4) -> 3977.2237 | IZ2: =OFFSET($D$50, 0, (COLUMN()-4)/4) -> 4023.8916 | JD2: =OFFSET($D$50, 0, (COLUMN()-4)/4) -> 4199.443 | JH2: =OFFSET($D$50, 0, (COLUMN()-4)/4) -> 4157.1863 | JL2: =OFFSET($D$50, 0, (COLUMN()-4)/4) -> 4635.9894 | JP2: =OFFSET($D$50, 0, (COLUMN()-4)/4) -> 4802.8104 | JT2: =OFFSET($D$50, 0, (COLUMN()-4)/4) -> 4728.0134 | JX2: =OFFSET($D$50, 0, (COLUMN()-4)/4) -> 4878.0359 | KB2: =OFFSET($D$50, 0, (COLUMN()-4)/4) -> 4776.6712
A3: 2900 | C3: Receitas | D3: R$ | G3: Receitas | H3: R$ | K3: Receitas | L3: R$ | O3: Receitas | P3: R$ | S3: Receitas | T3: R$ | W3: Receitas | X3: R$ | AA3: Receitas | AB3: R$ | AE3: Receitas | AF3: R$ | AI3: Receitas | AJ3: R$ | AM3: Receitas | AN3: R$ | AQ3: Receitas | AR3: R$ | AU3: Receitas | AV3: R$ | AY3: Receitas | AZ3: R$ | BC3: Receitas | BD3: R$ | BG3: Receitas | BH3: R$ | BK3: Receitas | BL3: R$ | BO3: Receitas | BP3: R$ | BS3: Receitas | BT3: R$ | BW3: Receitas | BX3: R$ | CA3: Receitas | CB3: R$ | CE3: Receitas | CF3: R$ | CI3: Receitas | CJ3: R$ | CM3: Receitas | CN3: R$ | CQ3: Receitas | CR3: R$ | CU3: Receitas | CV3: R$ | CY3: Receitas | CZ3: R$ | DC3: Receitas | DD3: R$ | DG3: Receitas | DH3: R$ | DK3: Receitas | DL3: R$ | DO3: Receitas | DP3: R$ | DS3: Receitas | DT3: R$ | DW3: Receitas | DX3: R$ | EA3: Receitas | EB3: R$ | EE3: Receitas | EF3: R$ | EI3: Receitas | EJ3: R$ | EM3: Receitas | EN3: R$ | EQ3: Receitas | ER3: R$ | EU3: Receitas | EV3: R$ | EY3: Receitas | EZ3: R$ | FC3: Receitas | FD3: R$ | FG3: Receitas | FH3: R$ | FK3: Receitas | FL3: R$ | FO3: Receitas | FP3: R$ | FS3: Receitas | FT3: R$ | FW3: Receitas | FX3: R$ | GA3: Receitas | GB3: R$ | GE3: Receitas | GF3: R$ | GI3: Receitas | GJ3: R$ | GM3: Receitas | GN3: R$ | GQ3: Receitas | GR3: R$ | GU3: Receitas | GV3: R$ | GY3: Receitas | GZ3: R$ | HC3: Receitas | HD3: R$ | HG3: Receitas | HH3: R$ | HK3: Receitas | HL3: R$ | HO3: Receitas | HP3: R$ | HS3: Receitas | HT3: R$ | HW3: Receitas | HX3: R$ | IA3: Receitas | IB3: R$ | IE3: Receitas | IF3: R$ | II3: Receitas | IJ3: R$ | IM3: Receitas | IN3: R$ | IQ3: Receitas | IR3: R$ | IU3: Receitas | IV3: R$ | IY3: Receitas | IZ3: R$ | JC3: Receitas | JD3: R$ | JG3: Receitas | JH3: R$ | JK3: Receitas | JL3: R$ | JO3: Receitas | JP3: R$ | JS3: Receitas | JT3: R$ | JW3: Receitas | JX3: R$ | KA3: Receitas | KB3: R$
A4: 40 | C4: Venda de café | D4: =((D$5*60)/0.25)*D$6 -> 29661.515 | E4: =-(D$4+D$26)/D$26 -> -0.84782869 | G4: Venda de café | H4: =((H$5*60)/0.25)*H$6 -> 31296.373 | I4: =-(H$4+H$26)/H$26 -> 0.43707351 | K4: Venda de café | L4: =((L$5*60)/0.25)*L$6 -> 30043.169 | M4: =-(L$4+L$26)/L$26 -> 0.42872092 | O4: Venda de café | P4: =((P$5*60)/0.25)*P$6 -> 32802.401 | Q4: =-(P$4+P$26)/P$26 -> -0.32980964 | S4: Venda de café | T4: =((T$5*60)/0.25)*T$6 -> 37032.099 | U4: =-(T$4+T$26)/T$26 -> 0.56972461 | W4: Venda de café | X4: =((X$5*60)/0.25)*X$6 -> 33254.992 | Y4: =-(X$4+X$26)/X$26 -> 0.41879709 | AA4: Venda de café | AB4: =((AB$5*60)/0.25)*AB$6 -> 36566.243 | AC4: =-(AB$4+AB$26)/AB$26 -> -0.33007799 | AE4: Venda de café | AF4: =((AF$5*60)/0.25)*AF$6 -> 40073.896 | AG4: =-(AF$4+AF$26)/AF$26 -> 0.56495748 | AI4: Venda de café | AJ4: =((AJ$5*60)/0.25)*AJ$6 -> 36474.938 | AK4: =-(AJ$4+AJ$26)/AJ$26 -> 0.49680081 | AM4: Venda de café | AN4: =((AN$5*60)/0.25)*AN$6 -> 38122.205 | AO4: =-(AN$4+AN$26)/AN$26 -> -0.28859806 | AQ4: Venda de café | AR4: =((AR$5*60)/0.25)*AR$6 -> 48380.712 | AS4: =-(AR$4+AR$26)/AR$26 -> 0.63581673 | AU4: Venda de café | AV4: =((AV$5*60)/0.25)*AV$6 -> 49916.11 | AW4: =-(AV$4+AV$26)/AV$26 -> 0.64230199 | AY4: Venda de café | AZ4: =((AZ$5*60)/0.25)*AZ$6 -> 49433.993 | BA4: =-(AZ$4+AZ$26)/AZ$26 -> -0.15184221 | BC4: Venda de café | BD4: =((BD$5*60)/0.25)*BD$6 -> 42020.638 | BE4: =-(BD$4+BD$26)/BD$26 -> 0.54937642 | BG4: Venda de café | BH4: =((BH$5*60)/0.25)*BH$6 -> 43598.813 | BI4: =-(BH$4+BH$26)/BH$26 -> 0.58276662 | BK4: Venda de café | BL4: =((BL$5*60)/0.25)*BL$6 -> 43913.663 | BM4: =-(BL$4+BL$26)/BL$26 -> -0.24004383 | BO4: Venda de café | BP4: =((BP$5*60)/0.25)*BP$6 -> 49432.18 | BQ4: =-(BP$4+BP$26)/BP$26 -> 0.6363685 | BS4: Venda de café | BT4: =((BT$5*60)/0.25)*BT$6 -> 44015.831 | BU4: =-(BT$4+BT$26)/BT$26 -> 0.54979046 | BW4: Venda de café | BX4: =((BX$5*60)/0.25)*BX$6 -> 53020.167 | BY4: =-(BX$4+BX$26)/BX$26 -> -0.24151917 | CA4: Venda de café | CB4: =((CB$5*60)/0.25)*CB$6 -> 56382.16 | CC4: =-(CB$4+CB$26)/CB$26 -> 0.72451739 | CE4: Venda de café | CF4: =((CF$5*60)/0.25)*CF$6 -> 64357.704 | CG4: =-(CF$4+CF$26)/CF$26 -> 0.82928539 | CI4: Venda de café | CJ4: =((CJ$5*60)/0.25)*CJ$6 -> 50982.114 | CK4: =-(CJ$4+CJ$26)/CJ$26 -> -0.12684857 | CM4: Venda de café | CN4: =((CN$5*60)/0.25)*CN$6 -> 52590.279 | CO4: =-(CN$4+CN$26)/CN$26 -> 0.75826113 | CQ4: Venda de café | CR4: =((CR$5*60)/0.25)*CR$6 -> 63151.192 | CS4: =-(CR$4+CR$26)/CR$26 -> 0.87451909 | CU4: Venda de café | CV4: =((CV$5*60)/0.25)*CV$6 -> 58531.79 | CW4: =-(CV$4+CV$26)/CV$26 -> -0.050460845 | CY4: Venda de café | CZ4: =((CZ$5*60)/0.25)*CZ$6 -> 53190.028 | DA4: =-(CZ$4+CZ$26)/CZ$26 -> 0.73838839 | DC4: Venda de café | DD4: =((DD$5*60)/0.25)*DD$6 -> 62409.733 | DE4: =-(DD$4+DD$26)/DD$26 -> 0.82932682 | DG4: Venda de café | DH4: =((DH$5*60)/0.25)*DH$6 -> 60915.943 | DI4: =-(DH$4+DH$26)/DH$26 -> -0.062330421 | DK4: Venda de café | DL4: =((DL$5*60)/0.25)*DL$6 -> 66000.733 | DM4: =-(DL$4+DL$26)/DL$26 -> 0.85715393 | DO4: Venda de café | DP4: =((DP$5*60)/0.25)*DP$6 -> 66452.203 | DQ4: =-(DP$4+DP$26)/DP$26 -> 0.83239089 | DS4: Venda de café | DT4: =((DT$5*60)/0.25)*DT$6 -> 70221.547 | DU4: =-(DT$4+DT$26)/DT$26 -> -0.16547306 | DW4: Venda de café | DX4: =((DX$5*60)/0.25)*DX$6 -> 68023.912 | DY4: =-(DX$4+DX$26)/DX$26 -> 0.76628946 | EA4: Venda de café | EB4: =((EB$5*60)/0.25)*EB$6 -> 71176.226 | EC4: =-(EB$4+EB$26)/EB$26 -> 0.76631318 | EE4: Venda de café | EF4: =((EF$5*60)/0.25)*EF$6 -> 72515.529 | EG4: =-(EF$4+EF$26)/EF$26 -> -0.34669872 | EI4: Venda de café | EJ4: =((EJ$5*60)/0.25)*EJ$6 -> 83085.462 | EK4: =-(EJ$4+EJ$26)/EJ$26 -> 0.75514851 | EM4: Venda de café | EN4: =((EN$5*60)/0.25)*EN$6 -> 84779.316 | EO4: =-(EN$4+EN$26)/EN$26 -> 0.76416564 | EQ4: Venda de café | ER4: =((ER$5*60)/0.25)*ER$6 -> 69834.484 | ES4: =-(ER$4+ER$26)/ER$26 -> -0.44728296 | EU4: Venda de café | EV4: =((EV$5*60)/0.25)*EV$6 -> 87311.336 | EW4: =-(EV$4+EV$26)/EV$26 -> 0.77122176 | EY4: Venda de café | EZ4: =((EZ$5*60)/0.25)*EZ$6 -> 76325.538 | FA4: =-(EZ$4+EZ$26)/EZ$26 -> 0.69996538 | FC4: Venda de café | FD4: =((FD$5*60)/0.25)*FD$6 -> 87632.583 | FE4: =-(FD$4+FD$26)/FD$26 -> -0.40594527 | FG4: Venda de café | FH4: =((FH$5*60)/0.25)*FH$6 -> 85443.375 | FI4: =-(FH$4+FH$26)/FH$26 -> 0.72146667 | FK4: Venda de café | FL4: =((FL$5*60)/0.25)*FL$6 -> 85912.485 | FM4: =-(FL$4+FL$26)/FL$26 -> 0.69726427 | FO4: Venda de café | FP4: =((FP$5*60)/0.25)*FP$6 -> 76264.937 | FQ4: =-(FP$4+FP$26)/FP$26 -> -0.50594569 | FS4: Venda de café | FT4: =((FT$5*60)/0.25)*FT$6 -> 77997.78 | FU4: =-(FT$4+FT$26)/FT$26 -> 0.61723368 | FW4: Venda de café | FX4: =((FX$5*60)/0.25)*FX$6 -> 94571.342 | FY4: =-(FX$4+FX$26)/FX$26 -> 0.70440656 | GA4: Venda de café | GB4: =((GB$5*60)/0.25)*GB$6 -> 79531.433 | GC4: =-(GB$4+GB$26)/GB$26 -> -0.59051634 | GE4: Venda de café | GF4: =((GF$5*60)/0.25)*GF$6 -> 100760.29 | GG4: =-(GF$4+GF$26)/GF$26 -> 0.63518313 | GI4: Venda de café | GJ4: =((GJ$5*60)/0.25)*GJ$6 -> 99221.445 | GK4: =-(GJ$4+GJ$26)/GJ$26 -> 0.6549852 | GM4: Venda de café | GN4: =((GN$5*60)/0.25)*GN$6 -> 81740.568 | GO4: =-(GN$4+GN$26)/GN$26 -> -0.56375826 | GQ4: Venda de café | GR4: =((GR$5*60)/0.25)*GR$6 -> 102213.65 | GS4: =-(GR$4+GR$26)/GR$26 -> 0.74154738 | GU4: Venda de café | GV4: =((GV$5*60)/0.25)*GV$6 -> 106031.52 | GW4: =-(GV$4+GV$26)/GV$26 -> 0.74133156 | GY4: Venda de café | GZ4: =((GZ$5*60)/0.25)*GZ$6 -> 86352.37 | HA4: =-(GZ$4+GZ$26)/GZ$26 -> -0.5208126 | HC4: Venda de café | HD4: =((HD$5*60)/0.25)*HD$6 -> 95308.379 | HE4: =-(HD$4+HD$26)/HD$26 -> 0.73354367 | HG4: Venda de café | HH4: =((HH$5*60)/0.25)*HH$6 -> 109306.35 | HI4: =-(HH$4+HH$26)/HH$26 -> 0.79357627 | HK4: Venda de café | HL4: =((HL$5*60)/0.25)*HL$6 -> 99947.324 | HM4: =-(HL$4+HL$26)/HL$26 -> -0.46134983 | HO4: Venda de café | HP4: =((HP$5*60)/0.25)*HP$6 -> 117268.67 | HQ4: =-(HP$4+HP$26)/HP$26 -> 0.81996187 | HS4: Venda de café | HT4: =((HT$5*60)/0.25)*HT$6 -> 95758.079 | HU4: =-(HT$4+HT$26)/HT$26 -> 0.78541307 | HW4: Venda de café | HX4: =((HX$5*60)/0.25)*HX$6 -> 119087.13 | HY4: =-(HX$4+HX$26)/HX$26 -> -0.36861075 | IA4: Venda de café | IB4: =((IB$5*60)/0.25)*IB$6 -> 96990.945 | IC4: =-(IB$4+IB$26)/IB$26 -> 0.77540796 | IE4: Venda de café | IF4: =((IF$5*60)/0.25)*IF$6 -> 105708.51 | IG4: =-(IF$4+IF$26)/IF$26 -> 0.78563232 | II4: Venda de café | IJ4: =((IJ$5*60)/0.25)*IJ$6 -> 96018.833 | IK4: =-(IJ$4+IJ$26)/IJ$26 -> -0.44740913 | IM4: Venda de café | IN4: =((IN$5*60)/0.25)*IN$6 -> 112079.75 | IO4: =-(IN$4+IN$26)/IN$26 -> 0.8240107 | IQ4: Venda de café | IR4: =((IR$5*60)/0.25)*IR$6 -> 104242.45 | IS4: =-(IR$4+IR$26)/IR$26 -> 0.73468364 | IU4: Venda de café | IV4: =((IV$5*60)/0.25)*IV$6 -> 125752.05 | IW4: =-(IV$4+IV$26)/IV$26 -> -0.42898185 | IY4: Venda de café | IZ4: =((IZ$5*60)/0.25)*IZ$6 -> 117784.41 | JA4: =-(IZ$4+IZ$26)/IZ$26 -> 0.82171519 | JC4: Venda de café | JD4: =((JD$5*60)/0.25)*JD$6 -> 125024.84 | JE4: =-(JD$4+JD$26)/JD$26 -> 0.80628298 | JG4: Venda de café | JH4: =((JH$5*60)/0.25)*JH$6 -> 130350.32 | JI4: =-(JH$4+JH$26)/JH$26 -> -0.43211589 | JK4: Venda de café | JL4: =((JL$5*60)/0.25)*JL$6 -> 112830.42 | JM4: =-(JL$4+JL$26)/JL$26 -> 0.72911159 | JO4: Venda de café | JP4: =((JP$5*60)/0.25)*JP$6 -> 128765.9 | JQ4: =-(JP$4+JP$26)/JP$26 -> 0.78313234 | JS4: Venda de café | JT4: =((JT$5*60)/0.25)*JT$6 -> 123173.66 | JU4: =-(JT$4+JT$26)/JT$26 -> -0.52794473 | JW4: Venda de café | JX4: =((JX$5*60)/0.25)*JX$6 -> 117956.78 | JY4: =-(JX$4+JX$26)/JX$26 -> 0.7029841 | KA4: Venda de café | KB4: =((KB$5*60)/0.25)*KB$6 -> 140249.02 | KC4: =-(KB$4+KB$26)/KB$26 -> 0.7944006
A5: 0.15 | C5: Sacas vendidas | D5: =OFFSET($D$51, 0, (COLUMN()-4)/4) -> 3.1 | G5: Sacas vendidas | H5: =OFFSET($D$51, 0, (COLUMN()-4)/4) -> 3.2 | K5: Sacas vendidas | L5: =OFFSET($D$51, 0, (COLUMN()-4)/4) -> 3 | O5: Sacas vendidas | P5: =OFFSET($D$51, 0, (COLUMN()-4)/4) -> 3.3 | S5: Sacas vendidas | T5: =OFFSET($D$51, 0, (COLUMN()-4)/4) -> 3.8 | W5: Sacas vendidas | X5: =OFFSET($D$51, 0, (COLUMN()-4)/4) -> 3.5 | AA5: Sacas vendidas | AB5: =OFFSET($D$51, 0, (COLUMN()-4)/4) -> 3.8 | AE5: Sacas vendidas | AF5: =OFFSET($D$51, 0, (COLUMN()-4)/4) -> 4.1 | AI5: Sacas vendidas | AJ5: =OFFSET($D$51, 0, (COLUMN()-4)/4) -> 3.9 | AM5: Sacas vendidas | AN5: =OFFSET($D$51, 0, (COLUMN()-4)/4) -> 4.1 | AQ5: Sacas vendidas | AR5: =OFFSET($D$51, 0, (COLUMN()-4)/4) -> 5.1 | AU5: Sacas vendidas | AV5: =OFFSET($D$51, 0, (COLUMN()-4)/4) -> 5.3 | AY5: Sacas vendidas | AZ5: =OFFSET($D$51, 0, (COLUMN()-4)/4) -> 5 | BC5: Sacas vendidas | BD5: =OFFSET($D$51, 0, (COLUMN()-4)/4) -> 4.4 | BG5: Sacas vendidas | BH5: =OFFSET($D$51, 0, (COLUMN()-4)/4) -> 4.5 | BK5: Sacas vendidas | BL5: =OFFSET($D$51, 0, (COLUMN()-4)/4) -> 4.6 | BO5: Sacas vendidas | BP5: =OFFSET($D$51, 0, (COLUMN()-4)/4) -> 5.2 | BS5: Sacas vendidas | BT5: =OFFSET($D$51, 0, (COLUMN()-4)/4) -> 4.6 | BW5: Sacas vendidas | BX5: =OFFSET($D$51, 0, (COLUMN()-4)/4) -> 5.4 | CA5: Sacas vendidas | CB5: =OFFSET($D$51, 0, (COLUMN()-4)/4) -> 5.9 | CE5: Sacas vendidas | CF5: =OFFSET($D$51, 0, (COLUMN()-4)/4) -> 6.7 | CI5: Sacas vendidas | CJ5: =OFFSET($D$51, 0, (COLUMN()-4)/4) -> 5.4 | CM5: Sacas vendidas | CN5: =OFFSET($D$51, 0, (COLUMN()-4)/4) -> 5.3 | CQ5: Sacas vendidas | CR5: =OFFSET($D$51, 0, (COLUMN()-4)/4) -> 6.3 | CU5: Sacas vendidas | CV5: =OFFSET($D$51, 0, (COLUMN()-4)/4) -> 6.3 | CY5: Sacas vendidas | CZ5: =OFFSET($D$51, 0, (COLUMN()-4)/4) -> 5.6 | DC5: Sacas vendidas | DD5: =OFFSET($D$51, 0, (COLUMN()-4)/4) -> 6.6 | DG5: Sacas vendidas | DH5: =OFFSET($D$51, 0, (COLUMN()-4)/4) -> 6.5 | DK5: Sacas vendidas | DL5: =OFFSET($D$51, 0, (COLUMN()-4)/4) -> 6.9 | DO5: Sacas vendidas | DP5: =OFFSET($D$51, 0, (COLUMN()-4)/4) -> 7 | DS5: Sacas vendidas | DT5: =OFFSET($D$51, 0, (COLUMN()-4)/4) -> 7.3 | DW5: Sacas vendidas | DX5: =OFFSET($D$51, 0, (COLUMN()-4)/4) -> 7.2 | EA5: Sacas vendidas | EB5: =OFFSET($D$51, 0, (COLUMN()-4)/4) -> 7.5 | EE5: Sacas vendidas | EF5: =OFFSET($D$51, 0, (COLUMN()-4)/4) -> 7.8 | EI5: Sacas vendidas | EJ5: =OFFSET($D$51, 0, (COLUMN()-4)/4) -> 8.6 | EM5: Sacas vendidas | EN5: =OFFSET($D$51, 0, (COLUMN()-4)/4) -> 8.5 | EQ5: Sacas vendidas | ER5: =OFFSET($D$51, 0, (COLUMN()-4)/4) -> 7.3 | EU5: Sacas vendidas | EV5: =OFFSET($D$51, 0, (COLUMN()-4)/4) -> 8.9 | EY5: Sacas vendidas | EZ5: =OFFSET($D$51, 0, (COLUMN()-4)/4) -> 7.9 | FC5: Sacas vendidas | FD5: =OFFSET($D$51, 0, (COLUMN()-4)/4) -> 9.1 | FG5: Sacas vendidas | FH5: =OFFSET($D$51, 0, (COLUMN()-4)/4) -> 8.9 | FK5: Sacas vendidas | FL5: =OFFSET($D$51, 0, (COLUMN()-4)/4) -> 8.8 | FO5: Sacas vendidas | FP5: =OFFSET($D$51, 0, (COLUMN()-4)/4) -> 7.9 | FS5: Sacas vendidas | FT5: =OFFSET($D$51, 0, (COLUMN()-4)/4) -> 8.2 | FW5: Sacas vendidas | FX5: =OFFSET($D$51, 0, (COLUMN()-4)/4) -> 9.7 | GA5: Sacas vendidas | GB5: =OFFSET($D$51, 0, (COLUMN()-4)/4) -> 8.4 | GE5: Sacas vendidas | GF5: =OFFSET($D$51, 0, (COLUMN()-4)/4) -> 10.3 | GI5: Sacas vendidas | GJ5: =OFFSET($D$51, 0, (COLUMN()-4)/4) -> 10.3 | GM5: Sacas vendidas | GN5: =OFFSET($D$51, 0, (COLUMN()-4)/4) -> 8.7 | GQ5: Sacas vendidas | GR5: =OFFSET($D$51, 0, (COLUMN()-4)/4) -> 10.7 | GU5: Sacas vendidas | GV5: =OFFSET($D$51, 0, (COLUMN()-4)/4) -> 11.1 | GY5: Sacas vendidas | GZ5: =OFFSET($D$51, 0, (COLUMN()-4)/4) -> 9.1 | HC5: Sacas vendidas | HD5: =OFFSET($D$51, 0, (COLUMN()-4)/4) -> 10.1 | HG5: Sacas vendidas | HH5: =OFFSET($D$51, 0, (COLUMN()-4)/4) -> 11.4 | HK5: Sacas vendidas | HL5: =OFFSET($D$51, 0, (COLUMN()-4)/4) -> 10.5 | HO5: Sacas vendidas | HP5: =OFFSET($D$51, 0, (COLUMN()-4)/4) -> 11.9 | HS5: Sacas vendidas | HT5: =OFFSET($D$51, 0, (COLUMN()-4)/4) -> 9.7 | HW5: Sacas vendidas | HX5: =OFFSET($D$51, 0, (COLUMN()-4)/4) -> 12.3 | IA5: Sacas vendidas | IB5: =OFFSET($D$51, 0, (COLUMN()-4)/4) -> 10.1 | IE5: Sacas vendidas | IF5: =OFFSET($D$51, 0, (COLUMN()-4)/4) -> 11.4 | II5: Sacas vendidas | IJ5: =OFFSET($D$51, 0, (COLUMN()-4)/4) -> 10.2 | IM5: Sacas vendidas | IN5: =OFFSET($D$51, 0, (COLUMN()-4)/4) -> 11.4 | IQ5: Sacas vendidas | IR5: =OFFSET($D$51, 0, (COLUMN()-4)/4) -> 11.3 | IU5: Sacas vendidas | IV5: =OFFSET($D$51, 0, (COLUMN()-4)/4) -> 13 | IY5: Sacas vendidas | IZ5: =OFFSET($D$51, 0, (COLUMN()-4)/4) -> 12.1 | JC5: Sacas vendidas | JD5: =OFFSET($D$51, 0, (COLUMN()-4)/4) -> 13.1 | JG5: Sacas vendidas | JH5: =OFFSET($D$51, 0, (COLUMN()-4)/4) -> 13.3 | JK5: Sacas vendidas | JL5: =OFFSET($D$51, 0, (COLUMN()-4)/4) -> 11.9 | JO5: Sacas vendidas | JP5: =OFFSET($D$51, 0, (COLUMN()-4)/4) -> 13 | JS5: Sacas vendidas | JT5: =OFFSET($D$51, 0, (COLUMN()-4)/4) -> 13.1 | JW5: Sacas vendidas | JX5: =OFFSET($D$51, 0, (COLUMN()-4)/4) -> 12.7 | KA5: Sacas vendidas | KB5: =OFFSET($D$51, 0, (COLUMN()-4)/4) -> 14.4
C6: Preço por pacotinho | D6: =OFFSET($D$52, 0, (COLUMN()-4)/4) -> 39.867628 | G6: Preço por pacotinho | H6: =OFFSET($D$52, 0, (COLUMN()-4)/4) -> 40.750486 | K6: Preço por pacotinho | L6: =OFFSET($D$52, 0, (COLUMN()-4)/4) -> 41.726623 | O6: Preço por pacotinho | P6: =OFFSET($D$52, 0, (COLUMN()-4)/4) -> 41.417173 | S6: Preço por pacotinho | T6: =OFFSET($D$52, 0, (COLUMN()-4)/4) -> 40.605372 | W6: Preço por pacotinho | X6: =OFFSET($D$52, 0, (COLUMN()-4)/4) -> 39.589276 | AA6: Preço por pacotinho | AB6: =OFFSET($D$52, 0, (COLUMN()-4)/4) -> 40.094565 | AE6: Preço por pacotinho | AF6: =OFFSET($D$52, 0, (COLUMN()-4)/4) -> 40.725504 | AI6: Preço por pacotinho | AJ6: =OFFSET($D$52, 0, (COLUMN()-4)/4) -> 38.968951 | AM6: Preço por pacotinho | AN6: =OFFSET($D$52, 0, (COLUMN()-4)/4) -> 38.742078 | AQ6: Preço por pacotinho | AR6: =OFFSET($D$52, 0, (COLUMN()-4)/4) -> 39.526725 | AU6: Preço por pacotinho | AV6: =OFFSET($D$52, 0, (COLUMN()-4)/4) -> 39.242224 | AY6: Preço por pacotinho | AZ6: =OFFSET($D$52, 0, (COLUMN()-4)/4) -> 41.194994 | BC6: Preço por pacotinho | BD6: =OFFSET($D$52, 0, (COLUMN()-4)/4) -> 39.792271 | BG6: Preço por pacotinho | BH6: =OFFSET($D$52, 0, (COLUMN()-4)/4) -> 40.369271 | BK6: Preço por pacotinho | BL6: =OFFSET($D$52, 0, (COLUMN()-4)/4) -> 39.776868 | BO6: Preço por pacotinho | BP6: =OFFSET($D$52, 0, (COLUMN()-4)/4) -> 39.609119 | BS6: Preço por pacotinho | BT6: =OFFSET($D$52, 0, (COLUMN()-4)/4) -> 39.869412 | BW6: Preço por pacotinho | BX6: =OFFSET($D$52, 0, (COLUMN()-4)/4) -> 40.910622 | CA6: Preço por pacotinho | CB6: =OFFSET($D$52, 0, (COLUMN()-4)/4) -> 39.81791 | CE6: Preço por pacotinho | CF6: =OFFSET($D$52, 0, (COLUMN()-4)/4) -> 40.023448 | CI6: Preço por pacotinho | CJ6: =OFFSET($D$52, 0, (COLUMN()-4)/4) -> 39.338051 | CM6: Preço por pacotinho | CN6: =OFFSET($D$52, 0, (COLUMN()-4)/4) -> 41.344559 | CQ6: Preço por pacotinho | CR6: =OFFSET($D$52, 0, (COLUMN()-4)/4) -> 41.766662 | CU6: Preço por pacotinho | CV6: =OFFSET($D$52, 0, (COLUMN()-4)/4) -> 38.711502 | CY6: Preço por pacotinho | CZ6: =OFFSET($D$52, 0, (COLUMN()-4)/4) -> 39.575914 | DC6: Preço por pacotinho | DD6: =OFFSET($D$52, 0, (COLUMN()-4)/4) -> 39.400084 | DG6: Preço por pacotinho | DH6: =OFFSET($D$52, 0, (COLUMN()-4)/4) -> 39.048681 | DK6: Preço por pacotinho | DL6: =OFFSET($D$52, 0, (COLUMN()-4)/4) -> 39.855515 | DO6: Preço por pacotinho | DP6: =OFFSET($D$52, 0, (COLUMN()-4)/4) -> 39.554883 | DS6: Preço por pacotinho | DT6: =OFFSET($D$52, 0, (COLUMN()-4)/4) -> 40.080791 | DW6: Preço por pacotinho | DX6: =OFFSET($D$52, 0, (COLUMN()-4)/4) -> 39.36569 | EA6: Preço por pacotinho | EB6: =OFFSET($D$52, 0, (COLUMN()-4)/4) -> 39.542348 | EE6: Preço por pacotinho | EF6: =OFFSET($D$52, 0, (COLUMN()-4)/4) -> 38.736928 | EI6: Preço por pacotinho | EJ6: =OFFSET($D$52, 0, (COLUMN()-4)/4) -> 40.254585 | EM6: Preço por pacotinho | EN6: =OFFSET($D$52, 0, (COLUMN()-4)/4) -> 41.558488 | EQ6: Preço por pacotinho | ER6: =OFFSET($D$52, 0, (COLUMN()-4)/4) -> 39.859865 | EU6: Preço por pacotinho | EV6: =OFFSET($D$52, 0, (COLUMN()-4)/4) -> 40.876094 | EY6: Preço por pacotinho | EZ6: =OFFSET($D$52, 0, (COLUMN()-4)/4) -> 40.256085 | FC6: Preço por pacotinho | FD6: =OFFSET($D$52, 0, (COLUMN()-4)/4) -> 40.124809 | FG6: Preço por pacotinho | FH6: =OFFSET($D$52, 0, (COLUMN()-4)/4) -> 40.00158 | FK6: Preço por pacotinho | FL6: =OFFSET($D$52, 0, (COLUMN()-4)/4) -> 40.67826 | FO6: Preço por pacotinho | FP6: =OFFSET($D$52, 0, (COLUMN()-4)/4) -> 40.224123 | FS6: Preço por pacotinho | FT6: =OFFSET($D$52, 0, (COLUMN()-4)/4) -> 39.633018 | FW6: Preço por pacotinho | FX6: =OFFSET($D$52, 0, (COLUMN()-4)/4) -> 40.623429 | GA6: Preço por pacotinho | GB6: =OFFSET($D$52, 0, (COLUMN()-4)/4) -> 39.450116 | GE6: Preço por pacotinho | GF6: =OFFSET($D$52, 0, (COLUMN()-4)/4) -> 40.760636 | GI6: Preço por pacotinho | GJ6: =OFFSET($D$52, 0, (COLUMN()-4)/4) -> 40.138125 | GM6: Preço por pacotinho | GN6: =OFFSET($D$52, 0, (COLUMN()-4)/4) -> 39.147782 | GQ6: Preço por pacotinho | GR6: =OFFSET($D$52, 0, (COLUMN()-4)/4) -> 39.802824 | GU6: Preço por pacotinho | GV6: =OFFSET($D$52, 0, (COLUMN()-4)/4) -> 39.801622 | GY6: Preço por pacotinho | GZ6: =OFFSET($D$52, 0, (COLUMN()-4)/4) -> 39.538631 | HC6: Preço por pacotinho | HD6: =OFFSET($D$52, 0, (COLUMN()-4)/4) -> 39.318638 | HG6: Preço por pacotinho | HH6: =OFFSET($D$52, 0, (COLUMN()-4)/4) -> 39.951153 | HK6: Preço por pacotinho | HL6: =OFFSET($D$52, 0, (COLUMN()-4)/4) -> 39.661636 | HO6: Preço por pacotinho | HP6: =OFFSET($D$52, 0, (COLUMN()-4)/4) -> 41.060457 | HS6: Preço por pacotinho | HT6: =OFFSET($D$52, 0, (COLUMN()-4)/4) -> 41.133195 | HW6: Preço por pacotinho | HX6: =OFFSET($D$52, 0, (COLUMN()-4)/4) -> 40.341169 | IA6: Preço por pacotinho | IB6: =OFFSET($D$52, 0, (COLUMN()-4)/4) -> 40.012766 | IE6: Preço por pacotinho | IF6: =OFFSET($D$52, 0, (COLUMN()-4)/4) -> 38.636151 | II6: Preço por pacotinho | IJ6: =OFFSET($D$52, 0, (COLUMN()-4)/4) -> 39.223379 | IM6: Preço por pacotinho | IN6: =OFFSET($D$52, 0, (COLUMN()-4)/4) -> 40.964821 | IQ6: Preço por pacotinho | IR6: =OFFSET($D$52, 0, (COLUMN()-4)/4) -> 38.437483 | IU6: Preço por pacotinho | IV6: =OFFSET($D$52, 0, (COLUMN()-4)/4) -> 40.305144 | IY6: Preço por pacotinho | IZ6: =OFFSET($D$52, 0, (COLUMN()-4)/4) -> 40.55937 | JC6: Preço por pacotinho | JD6: =OFFSET($D$52, 0, (COLUMN()-4)/4) -> 39.76617 | JG6: Preço por pacotinho | JH6: =OFFSET($D$52, 0, (COLUMN()-4)/4) -> 40.836566 | JK6: Preço por pacotinho | JL6: =OFFSET($D$52, 0, (COLUMN()-4)/4) -> 39.50645 | JO6: Preço por pacotinho | JP6: =OFFSET($D$52, 0, (COLUMN()-4)/4) -> 41.271121 | JS6: Preço por pacotinho | JT6: =OFFSET($D$52, 0, (COLUMN()-4)/4) -> 39.177372 | JW6: Preço por pacotinho | JX6: =OFFSET($D$52, 0, (COLUMN()-4)/4) -> 38.69973 | KA6: Preço por pacotinho | KB6: =OFFSET($D$52, 0, (COLUMN()-4)/4) -> 40.581314
C8: Total receitas | D8: =SUM(D$4) -> 29661.515 | G8: Total receitas | H8: =SUM(H$4) -> 31296.373 | K8: Total receitas | L8: =SUM(L$4) -> 30043.169 | O8: Total receitas | P8: =SUM(P$4) -> 32802.401 | S8: Total receitas | T8: =SUM(T$4) -> 37032.099 | W8: Total receitas | X8: =SUM(X$4) -> 33254.992 | AA8: Total receitas | AB8: =SUM(AB$4) -> 36566.243 | AE8: Total receitas | AF8: =SUM(AF$4) -> 40073.896 | AI8: Total receitas | AJ8: =SUM(AJ$4) -> 36474.938 | AM8: Total receitas | AN8: =SUM(AN$4) -> 38122.205 | AQ8: Total receitas | AR8: =SUM(AR$4) -> 48380.712 | AU8: Total receitas | AV8: =SUM(AV$4) -> 49916.11 | AY8: Total receitas | AZ8: =SUM(AZ$4) -> 49433.993 | BC8: Total receitas | BD8: =SUM(BD$4) -> 42020.638 | BG8: Total receitas | BH8: =SUM(BH$4) -> 43598.813 | BK8: Total receitas | BL8: =SUM(BL$4) -> 43913.663 | BO8: Total receitas | BP8: =SUM(BP$4) -> 49432.18 | BS8: Total receitas | BT8: =SUM(BT$4) -> 44015.831 | BW8: Total receitas | BX8: =SUM(BX$4) -> 53020.167 | CA8: Total receitas | CB8: =SUM(CB$4) -> 56382.16 | CE8: Total receitas | CF8: =SUM(CF$4) -> 64357.704 | CI8: Total receitas | CJ8: =SUM(CJ$4) -> 50982.114 | CM8: Total receitas | CN8: =SUM(CN$4) -> 52590.279 | CQ8: Total receitas | CR8: =SUM(CR$4) -> 63151.192 | CU8: Total receitas | CV8: =SUM(CV$4) -> 58531.79 | CY8: Total receitas | CZ8: =SUM(CZ$4) -> 53190.028 | DC8: Total receitas | DD8: =SUM(DD$4) -> 62409.733 | DG8: Total receitas | DH8: =SUM(DH$4) -> 60915.943 | DK8: Total receitas | DL8: =SUM(DL$4) -> 66000.733 | DO8: Total receitas | DP8: =SUM(DP$4) -> 66452.203 | DS8: Total receitas | DT8: =SUM(DT$4) -> 70221.547 | DW8: Total receitas | DX8: =SUM(DX$4) -> 68023.912 | EA8: Total receitas | EB8: =SUM(EB$4) -> 71176.226 | EE8: Total receitas | EF8: =SUM(EF$4) -> 72515.529 | EI8: Total receitas | EJ8: =SUM(EJ$4) -> 83085.462 | EM8: Total receitas | EN8: =SUM(EN$4) -> 84779.316 | EQ8: Total receitas | ER8: =SUM(ER$4) -> 69834.484 | EU8: Total receitas | EV8: =SUM(EV$4) -> 87311.336 | EY8: Total receitas | EZ8: =SUM(EZ$4) -> 76325.538 | FC8: Total receitas | FD8: =SUM(FD$4) -> 87632.583 | FG8: Total receitas | FH8: =SUM(FH$4) -> 85443.375 | FK8: Total receitas | FL8: =SUM(FL$4) -> 85912.485 | FO8: Total receitas | FP8: =SUM(FP$4) -> 76264.937 | FS8: Total receitas | FT8: =SUM(FT$4) -> 77997.78 | FW8: Total receitas | FX8: =SUM(FX$4) -> 94571.342 | GA8: Total receitas | GB8: =SUM(GB$4) -> 79531.433 | GE8: Total receitas | GF8: =SUM(GF$4) -> 100760.29 | GI8: Total receitas | GJ8: =SUM(GJ$4) -> 99221.445 | GM8: Total receitas | GN8: =SUM(GN$4) -> 81740.568 | GQ8: Total receitas | GR8: =SUM(GR$4) -> 102213.65 | GU8: Total receitas | GV8: =SUM(GV$4) -> 106031.52 | GY8: Total receitas | GZ8: =SUM(GZ$4) -> 86352.37 | HC8: Total receitas | HD8: =SUM(HD$4) -> 95308.379 | HG8: Total receitas | HH8: =SUM(HH$4) -> 109306.35 | HK8: Total receitas | HL8: =SUM(HL$4) -> 99947.324 | HO8: Total receitas | HP8: =SUM(HP$4) -> 117268.67 | HS8: Total receitas | HT8: =SUM(HT$4) -> 95758.079 | HW8: Total receitas | HX8: =SUM(HX$4) -> 119087.13 | IA8: Total receitas | IB8: =SUM(IB$4) -> 96990.945 | IE8: Total receitas | IF8: =SUM(IF$4) -> 105708.51 | II8: Total receitas | IJ8: =SUM(IJ$4) -> 96018.833 | IM8: Total receitas | IN8: =SUM(IN$4) -> 112079.75 | IQ8: Total receitas | IR8: =SUM(IR$4) -> 104242.45 | IU8: Total receitas | IV8: =SUM(IV$4) -> 125752.05 | IY8: Total receitas | IZ8: =SUM(IZ$4) -> 117784.41 | JC8: Total receitas | JD8: =SUM(JD$4) -> 125024.84 | JG8: Total receitas | JH8: =SUM(JH$4) -> 130350.32 | JK8: Total receitas | JL8: =SUM(JL$4) -> 112830.42 | JO8: Total receitas | JP8: =SUM(JP$4) -> 128765.9 | JS8: Total receitas | JT8: =SUM(JT$4) -> 123173.66 | JW8: Total receitas | JX8: =SUM(JX$4) -> 117956.78 | KA8: Total receitas | KB8: =SUM(KB$4) -> 140249.02
C10: Despesas | D10: R$ | G10: Despesas | H10: R$ | K10: Despesas | L10: R$ | O10: Despesas | P10: R$ | S10: Despesas | T10: R$ | W10: Despesas | X10: R$ | AA10: Despesas | AB10: R$ | AE10: Despesas | AF10: R$ | AI10: Despesas | AJ10: R$ | AM10: Despesas | AN10: R$ | AQ10: Despesas | AR10: R$ | AU10: Despesas | AV10: R$ | AY10: Despesas | AZ10: R$ | BC10: Despesas | BD10: R$ | BG10: Despesas | BH10: R$ | BK10: Despesas | BL10: R$ | BO10: Despesas | BP10: R$ | BS10: Despesas | BT10: R$ | BW10: Despesas | BX10: R$ | CA10: Despesas | CB10: R$ | CE10: Despesas | CF10: R$ | CI10: Despesas | CJ10: R$ | CM10: Despesas | CN10: R$ | CQ10: Despesas | CR10: R$ | CU10: Despesas | CV10: R$ | CY10: Despesas | CZ10: R$ | DC10: Despesas | DD10: R$ | DG10: Despesas | DH10: R$ | DK10: Despesas | DL10: R$ | DO10: Despesas | DP10: R$ | DS10: Despesas | DT10: R$ | DW10: Despesas | DX10: R$ | EA10: Despesas | EB10: R$ | EE10: Despesas | EF10: R$ | EI10: Despesas | EJ10: R$ | EM10: Despesas | EN10: R$ | EQ10: Despesas | ER10: R$ | EU10: Despesas | EV10: R$ | EY10: Despesas | EZ10: R$ | FC10: Despesas | FD10: R$ | FG10: Despesas | FH10: R$ | FK10: Despesas | FL10: R$ | FO10: Despesas | FP10: R$ | FS10: Despesas | FT10: R$ | FW10: Despesas | FX10: R$ | GA10: Despesas | GB10: R$ | GE10: Despesas | GF10: R$ | GI10: Despesas | GJ10: R$ | GM10: Despesas | GN10: R$ | GQ10: Despesas | GR10: R$ | GU10: Despesas | GV10: R$ | GY10: Despesas | GZ10: R$ | HC10: Despesas | HD10: R$ | HG10: Despesas | HH10: R$ | HK10: Despesas | HL10: R$ | HO10: Despesas | HP10: R$ | HS10: Despesas | HT10: R$ | HW10: Despesas | HX10: R$ | IA10: Despesas | IB10: R$ | IE10: Despesas | IF10: R$ | II10: Despesas | IJ10: R$ | IM10: Despesas | IN10: R$ | IQ10: Despesas | IR10: R$ | IU10: Despesas | IV10: R$ | IY10: Despesas | IZ10: R$ | JC10: Despesas | JD10: R$ | JG10: Despesas | JH10: R$ | JK10: Despesas | JL10: R$ | JO10: Despesas | JP10: R$ | JS10: Despesas | JT10: R$ | JW10: Despesas | JX10: R$ | KA10: Despesas | KB10: R$
A11: Custos e Despesas iniciais | C11: Investimento inicial | D11: -146000
